Workbook

Sheet PRODUCT ENQUIRY
A1: PRODUCT ENQUIRY
B6: PLEASE ENTER YOUR PRODUCT REFERENCE CODE | C6: TO-JA-DE-NU-10
B8: Product: | C8: =IFERROR(VLOOKUP(C6,'REFERENCING & DATABASE'!$D$2:$K$131,2,FALSE),"Reference code does not exist") -> Denim Jacket
B9: Description: | C9: =IFERROR(VLOOKUP(C6,'REFERENCING & DATABASE'!$D$2:$K$131,3,FALSE),"Reference code does not exist") -> A timeless and versatile jacket that adds an edge to any outfit.
B10: Colour: | C10: =IFERROR(VLOOKUP(C6,'REFERENCING & DATABASE'!$D$2:$K$131,4,FALSE),"Reference code does not exist") -> Nude, Purple
B11: Size: | C11: =IFERROR(VLOOKUP(C6,'REFERENCING & DATABASE'!$D$2:$K$131,5,FALSE),"Reference code does not exist") -> 10
B12: Price: | C12: =IFERROR(VLOOKUP(C6,'REFERENCING & DATABASE'!$D$2:$K$131,6,FALSE),"Reference code does not exist") -> 45
B13: Available stock in store: | C13: =IFERROR(VLOOKUP($C$6,'STORE STK & SALES MGT'!$A2:$V514,9,FALSE)-VLOOKUP($C$6,'STORE STK & SALES MGT'!$A2:$V514,10,FALSE),"Reference code does not exist") -> 10
B14: Available stock in warehouse: | C14: =IFERROR(VLOOKUP(C6,'WHS STK MGT & ALLOC.'!$A$2:$K$105,9,FALSE),"Reference code does not exist") -> 90

Sheet REFERENCING & DATABASE
A1: REFERENCING & DATABASE
B4: TOTAL NO OF PRODUCTS
B5: =SUM(A7:A13) -> 2050
A6: NO OF PRODUCTS | B6: CATEGORY | C6: SUB-CATEGORY | D6: REFERENCE | E6: PRODUCT NAME | F6: DESCRIPTION | G6: COLOUR | H6: SIZE | I6: COST PRICE (€) | J6: MARGIN (%) | K6: RETAIL PRICE (€)
A7: 450 | B7: TOPS | C7: TEES | D7: =CONCATENATE(UPPER(LEFT(B7,1)&MID(B7,2,1)&"-"&LEFT(C7,1)&MID(C7,2,1)&"-"&LEFT(E7,1)&MID(E7,2,1)&"-"&LEFT(G7,1)&MID(G7,2,1)&"-"&LEFT(H7,1)&MID(H7,2,1))) -> TO-TE-CO-GR-58 | E7: Cozy Comfort Tee | F7: A relaxed-fit tee made from super-soft cotton, perfect for everyday wear. | G7: Grey,Black,Blue | H7: 58 | I7: 17 | J7: =ROUND((K7-I7)/I7*100,2) -> 105.88 | K7: 35
A8: 300 | B8: TOPS | C8: TEES | D8: =CONCATENATE(UPPER(LEFT(B8,1)&MID(B8,2,1)&"-"&LEFT(C8,1)&MID(C8,2,1)&"-"&LEFT(E8,1)&MID(E8,2,1)&"-"&LEFT(G8,1)&MID(G8,2,1)&"-"&LEFT(H8,1)&MID(H8,2,1))) -> TO-TE-GR-BL-58 | E8: Graphic Statement Tee | F8: A bold graphic tee that expresses your unique style. | G8: Blue,Black,White | H8: 58 | I8: 20 | J8: =ROUND((K8-I8)/I8*100,2) -> 100 | K8: 40
A9: 300 | B9: TOPS | C9: SHIRTS | D9: =CONCATENATE(UPPER(LEFT(B9,1)&MID(B9,2,1)&"-"&LEFT(C9,1)&MID(C9,2,1)&"-"&LEFT(E9,1)&MID(E9,2,1)&"-"&LEFT(G9,1)&MID(G9,2,1)&"-"&LEFT(H9,1)&MID(H9,2,1))) -> TO-SH-CL-PI-10 | E9: Classic Button-Down Shirt | F9: A timeless and versatile shirt for work or casual occasions. | G9: Pink, Brown,Yellow | H9: 10 | I9: 25 | J9: =ROUND((K9-I9)/I9*100,2) -> 60 | K9: 40
A10: 400 | B10: TOPS | C10: SHIRTS | D10: =CONCATENATE(UPPER(LEFT(B10,1)&MID(B10,2,1)&"-"&LEFT(C10,1)&MID(C10,2,1)&"-"&LEFT(E10,1)&MID(E10,2,1)&"-"&LEFT(G10,1)&MID(G10,2,1)&"-"&LEFT(H10,1)&MID(H10,2,1))) -> TO-SH-LI-PI-10 | E10: Linen Blend Shirt | F10: A lightweight and breathable shirt for warmer weather. | G10: Pink, Clear | H10: 10 | I10: 25 | J10: =ROUND((K10-I10)/I10*100,2) -> 100 | K10: 50
A11: 200 | B11: TOPS | C11: SWEATERS | D11: =CONCATENATE(UPPER(LEFT(B11,1)&MID(B11,2,1)&"-"&LEFT(C11,1)&MID(C11,2,1)&"-"&LEFT(E11,1)&MID(E11,2,1)&"-"&LEFT(G11,1)&MID(G11,2,1)&"-"&LEFT(H11,1)&MID(H11,2,1))) -> TO-SW-CO-NU-10 | E11: Cozy Cable-Knit Sweater | F11: A warm and stylish sweater for cooler days. | G11: Nude, Brown | H11: 10 | I11: 40 | J11: =ROUND((K11-I11)/I11*100,2) -> 75 | K11: 70
A12: 300 | B12: TOPS | C12: SWEATERS | D12: =CONCATENATE(UPPER(LEFT(B12,1)&MID(B12,2,1)&"-"&LEFT(C12,1)&MID(C12,2,1)&"-"&LEFT(E12,1)&MID(E12,2,1)&"-"&LEFT(G12,1)&MID(G12,2,1)&"-"&LEFT(H12,1)&MID(H12,2,1))) -> TO-SW-HO-BL-10 | E12: Hooded Sweatshirt | F12: A comfortable and casual sweatshirt perfect for lounging or layering. | G12: Black,Grey | H12: 10 | I12: 45 | J12: =ROUND((K12-I12)/I12*100,2) -> 51.11 | K12: 68
A13: 100 | B13: TOPS | C13: JACKETS | D13: =CONCATENATE(UPPER(LEFT(B13,1)&MID(B13,2,1)&"-"&LEFT(C13,1)&MID(C13,2,1)&"-"&LEFT(E13,1)&MID(E13,2,1)&"-"&LEFT(G13,1)&MID(G13,2,1)&"-"&LEFT(H13,1)&MID(H13,2,1))) -> TO-JA-DE-NU-10 | E13: Denim Jacket | F13: A timeless and versatile jacket that adds an edge to any outfit. | G13: Nude, Purple | H13: 10 | I13: 45 | J13: =ROUND((K13-I13)/I13*100,2) -> 88.89 | K13: 85
A14: 150 | B14: TOPS | C14: JACKETS | D14: =CONCATENATE(UPPER(LEFT(B14,1)&MID(B14,2,1)&"-"&LEFT(C14,1)&MID(C14,2,1)&"-"&LEFT(E14,1)&MID(E14,2,1)&"-"&LEFT(G14,1)&MID(G14,2,1)&"-"&LEFT(H14,1)&MID(H14,2,1))) -> TO-JA-LI-NU-10 | E14: Lightweight Puffer Jacket | F14: : A warm and packable jacket for all your adventures. | G14: Nude, Pink, Red | H14: 10 | I14: 65 | J14: =ROUND((K14-I14)/I14*100,2) -> 38.46 | K14: 90
B16: TOTAL NO OF PRODUCTS
B17: =SUM(A19:A35) -> 7134
A18: NO OF PRODUCTS | B18: CATEGORY | C18: SUB-CATEGORY | D18: REFERENCE | E18: PRODUCT NAME | F18: DESCRIPTION | G18: COLOUR | H18: SIZE | I18: COST PRICE (€) | J18: MARGIN (%) | K18: PRICE (€)
A19: 626 | B19: BOTTOMS | C19: JEANS | D19: =CONCATENATE(UPPER(LEFT(B19,1)&MID(B19,2,1)&"-"&LEFT(C19,1)&MID(C19,2,1)&"-"&LEFT(E19,1)&MID(E19,2,1)&"-"&LEFT(G19,1)&MID(G19,2,1)&"-"&LEFT(H19,1)&MID(H19,2,1))) -> BO-JE-CL-BL-10 | E19: Classic Straight Leg Jeans | F19: A timeless and versatile style that flatters all body types. | G19: Blue,Black,Grey | H19: 10 | I19: 35 | J19: =ROUND((K19-I19)/I19*100,2) -> 42.86 | K19: 50
A20: 207 | B20: BOTTOMS | C20: JEANS | D20: =CONCATENATE(UPPER(LEFT(B20,1)&MID(B20,2,1)&"-"&LEFT(C20,1)&MID(C20,2,1)&"-"&LEFT(E20,1)&MID(E20,2,1)&"-"&LEFT(G20,1)&MID(G20,2,1)&"-"&LEFT(H20,1)&MID(H20,2,1))) -> BO-JE-SK-BL-10 | E20: Skinny Fit Jeans | F20: A form-fitting silhouette that hugs your curves. | G20: Blue,Black,Grey | H20: 10 | I20: 30 | J20: =ROUND((K20-I20)/I20*100,2) -> 50 | K20: 45
A21: 644 | B21: BOTTOMS | C21: JEANS | D21: =CONCATENATE(UPPER(LEFT(B21,1)&MID(B21,2,1)&"-"&LEFT(C21,1)&MID(C21,2,1)&"-"&LEFT(E21,1)&MID(E21,2,1)&"-"&LEFT(G21,1)&MID(G21,2,1)&"-"&LEFT(H21,1)&MID(H21,2,1))) -> BO-JE-BO-BL-10 | E21: Bootcut Jeans | F21: A flattering style that flares slightly at the ankle. | G21: Blue,Black,Grey | H21: 10 | I21: 35 | J21: =ROUND((K21-I21)/I21*100,2) -> 37.14 | K21: 48
A22: 585 | B22: BOTTOMS | C22: JEANS | D22: =CONCATENATE(UPPER(LEFT(B22,1)&MID(B22,2,1)&"-"&LEFT(C22,1)&MID(C22,2,1)&"-"&LEFT(E22,1)&MID(E22,2,1)&"-"&LEFT(G22,1)&MID(G22,2,1)&"-"&LEFT(H22,1)&MID(H22,2,1))) -> BO-JE-HI-BL-10 | E22: High-Waisted Jeans | F22: A high-rise silhouette that elongates your legs and flatters your figure. | G22: Blue,Black,Grey | H22: 10 | I22: 38 | J22: =ROUND((K22-I22)/I22*100,2) -> 39.47 | K22: 53
A23: 597 | B23: BOTTOMS | C23: PANTS | D23: =CONCATENATE(UPPER(LEFT(B23,1)&MID(B23,2,1)&"-"&LEFT(C23,1)&MID(C23,2,1)&"-"&LEFT(E23,1)&MID(E23,2,1)&"-"&LEFT(G23,1)&MID(G23,2,1)&"-"&LEFT(H23,1)&MID(H23,2,1))) -> BO-PA-KH-BR-10 | E23: Khaki Chinos | F23: A versatile and comfortable option for work or casual wear. | G23: Brown,Black | H23: 10 | I23: 30 | J23: =ROUND((K23-I23)/I23*100,2) -> 33.33 | K23: 40
A24: 638 | B24: BOTTOMS | C24: PANTS | D24: =CONCATENATE(UPPER(LEFT(B24,1)&MID(B24,2,1)&"-"&LEFT(C24,1)&MID(C24,2,1)&"-"&LEFT(E24,1)&MID(E24,2,1)&"-"&LEFT(G24,1)&MID(G24,2,1)&"-"&LEFT(H24,1)&MID(H24,2,1))) -> BO-PA-SL-GR-10 | E24: Slim-Fit Dress Pants | F24: A polished and professional style for work or special occasions. | G24: green, yellow and lavender | H24: 10 | I24: 34 | J24: =ROUND((K24-I24)/I24*100,2) -> 61.76 | K24: 55
A25: 717 | B25: BOTTOMS | C25: PANTS | D25: =CONCATENATE(UPPER(LEFT(B25,1)&MID(B25,2,1)&"-"&LEFT(C25,1)&MID(C25,2,1)&"-"&LEFT(E25,1)&MID(E25,2,1)&"-"&LEFT(G25,1)&MID(G25,2,1)&"-"&LEFT(H25,1)&MID(H25,2,1))) -> BO-PA-UT-BL-10 | E25: Utility Cargo Pants | F25: A functional and stylish option with multiple pockets. | G25: Blue,Black,Grey | H25: 10 | I25: 25 | J25: =ROUND((K25-I25)/I25*100,2) -> 92 | K25: 48
A26: 755 | B26: BOTTOMS | C26: PANTS | D26: =CONCATENATE(UPPER(LEFT(B26,1)&MID(B26,2,1)&"-"&LEFT(C26,1)&MID(C26,2,1)&"-"&LEFT(E26,1)&MID(E26,2,1)&"-"&LEFT(G26,1)&MID(G26,2,1)&"-"&LEFT(H26,1)&MID(H26,2,1))) -> BO-PA-CO-GR-10 | E26: Cozy Joggers | F26: A comfortable and relaxed-fit style for lounging or exercising. | G26: Grey | H26: 10 | I26: 20 | J26: =ROUND((K26-I26)/I26*100,2) -> 75 | K26: 35
A27: 499 | B27: BOTTOMS | C27: PANTS | D27: =CONCATENATE(UPPER(LEFT(B27,1)&MID(B27,2,1)&"-"&LEFT(C27,1)&MID(C27,2,1)&"-"&LEFT(E27,1)&MID(E27,2,1)&"-"&LEFT(G27,1)&MID(G27,2,1)&"-"&LEFT(H27,1)&MID(H27,2,1))) -> BO-PA-TE-MU-10 | E27: Tech Fleece Track Pants | F27: Breathable and moisture-wicking pants for athletic activities or everyday wear. | G27: Multi-colors | H27: 10 | I27: 23 | J27: =ROUND((K27-I27)/I27*100,2) -> 86.96 | K27: 43
A28: 625 | B28: BOTTOMS | C28: SHORTS | D28: =CONCATENATE(UPPER(LEFT(B28,1)&MID(B28,2,1)&"-"&LEFT(C28,1)&MID(C28,2,1)&"-"&LEFT(E28,1)&MID(E28,2,1)&"-"&LEFT(G28,1)&MID(G28,2,1)&"-"&LEFT(H28,1)&MID(H28,2,1))) -> BO-SH-DI-LI-30 | E28: Distressed Denim Shorts | F28: A classic and casual style with a relaxed fit. | G28: light beige, medium beige, dark beige | H28: 30 | I28: 40 | J28: =ROUND((K28-I28)/I28*100,2) -> -25 | K28: 30
A29: 488 | B29: BOTTOMS | C29: SHORTS | D29: =CONCATENATE(UPPER(LEFT(B29,1)&MID(B29,2,1)&"-"&LEFT(C29,1)&MID(C29,2,1)&"-"&LEFT(E29,1)&MID(E29,2,1)&"-"&LEFT(G29,1)&MID(G29,2,1)&"-"&LEFT(H29,1)&MID(H29,2,1))) -> BO-SH-KH-LI-30 | E29: Khaki Chino Shorts | F29: A versatile option for warmer weather. | G29: light beige, Brown | H29: 30 | I29: 15 | J29: =ROUND((K29-I29)/I29*100,2) -> 66.67 | K29: 25
A30: 363 | B30: BOTTOMS | C30: SHORTS | D30: =CONCATENATE(UPPER(LEFT(B30,1)&MID(B30,2,1)&"-"&LEFT(C30,1)&MID(C30,2,1)&"-"&LEFT(E30,1)&MID(E30,2,1)&"-"&LEFT(G30,1)&MID(G30,2,1)&"-"&LEFT(H30,1)&MID(H30,2,1))) -> BO-SH-PE-MU-30 | E30: Performance Athletic Shorts | F30: Lightweight and breathable shorts for workouts or running. | G30: Multi-colors | H30: 30 | I30: 17 | J30: =ROUND((K30-I30)/I30*100,2) -> 94.12 | K30: 33
A31: 390 | B31: BOTTOMS | C31: SHORTS | D31: =CONCATENATE(UPPER(LEFT(B31,1)&MID(B31,2,1)&"-"&LEFT(C31,1)&MID(C31,2,1)&"-"&LEFT(E31,1)&MID(E31,2,1)&"-"&LEFT(G31,1)&MID(G31,2,1)&"-"&LEFT(H31,1)&MID(H31,2,1))) -> BO-SH-UT-GR-30 | E31: Utility Cargo Shorts | F31: Functional and stylish shorts with multiple pockets. | G31: Green,Brown,Black | H31: 30 | I31: 20 | J31: =ROUND((K31-I31)/I31*100,2) -> 100 | K31: 40
B38: TOTAL NO OF PRODUCTS
B39: =SUM(A41:A48) -> 3420
A40: NO OF PRODUCTS | B40: CATEGORY | C40: SUB-CATEGORY | D40: REFERENCE | E40: PRODUCT NAME | F40: DESCRIPTION | G40: COLOUR | H40: SIZE | I40: COST PRICE (€) | J40: MARGIN (%) | K40: PRICE (€)
A41: 488 | B41: SLEEPWEAR | C41: PAJAMAS | D41: =CONCATENATE(UPPER(LEFT(B41,1)&MID(B41,2,1)&"-"&LEFT(C41,1)&MID(C41,2,1)&"-"&LEFT(E41,1)&MID(E41,2,1)&"-"&LEFT(G41,1)&MID(G41,2,1)&"-"&LEFT(H41,1))) -> SL-PA-CO-MU-L | E41: Cozy Flannel Pajama Set | F41: A soft and warm set perfect for cooler nights. | G41: Multi-colors | H41: L,XL,XXL | I41: 25 | J41: =ROUND((K41-I41)/I41*100,2) -> 60 | K41: 40
A42: 267 | B42: SLEEPWEAR | C42: PAJAMAS | D42: =CONCATENATE(UPPER(LEFT(B42,1)&MID(B42,2,1)&"-"&LEFT(C42,1)&MID(C42,2,1)&"-"&LEFT(E42,1)&MID(E42,2,1)&"-"&LEFT(G42,1)&MID(G42,2,1)&"-"&LEFT(H42,1))) -> SL-PA-MO-MU-M | E42: Modal Jersey PJ Set | F42: A lightweight and breathable set for year-round comfort. | G42: Multi-colors | H42: M,L,XL,XXL | I42: 26 | J42: =ROUND((K42-I42)/I42*100,2) -> 73.08 | K42: 45
A43: 220 | B43: SLEEPWEAR | C43: PAJAMAS | D43: =CONCATENATE(UPPER(LEFT(B43,1)&MID(B43,2,1)&"-"&LEFT(C43,1)&MID(C43,2,1)&"-"&LEFT(E43,1)&MID(E43,2,1)&"-"&LEFT(G43,1)&MID(G43,2,1)&"-"&LEFT(H43,1))) -> SL-PA-ST-WH-L | E43: Striped Cotton Onesie | F43: A comfortable and playful option for lounging or sleeping. | G43: White,Grey | H43: L,XL,XXL | I43: 19 | J43: =ROUND((K43-I43)/I43*100,2) -> 57.89 | K43: 30
A44: 541 | B44: SLEEPWEAR | C44: PAJAMAS | D44: =CONCATENATE(UPPER(LEFT(B44,1)&MID(B44,2,1)&"-"&LEFT(C44,1)&MID(C44,2,1)&"-"&LEFT(E44,1)&MID(E44,2,1)&"-"&LEFT(G44,1)&MID(G44,2,1)&"-"&LEFT(H44,1))) -> SL-PA-FL-MU-L | E44: Floral Lace Nightgown | F44: A feminine and elegant nightgown for a luxurious feel. | G44: Multi-colors | H44: L,XL,XXL | I44: 27 | J44: =ROUND((K44-I44)/I44*100,2) -> 85.19 | K44: 50
A45: 586 | B45: SLEEPWEAR | C45: LOUNGEWEAR | D45: =CONCATENATE(UPPER(LEFT(B45,1)&MID(B45,2,1)&"-"&LEFT(C45,1)&MID(C45,2,1)&"-"&LEFT(E45,1)&MID(E45,2,1)&"-"&LEFT(G45,1)&MID(G45,2,1)&"-"&LEFT(H45,1))) -> SL-LO-FR-BL-S | E45: French Terry Loungewear Set | F45: A soft and stylish set for relaxing at home. | G45: Black,Dark Red | H45: S,L,XL,XXL | I45: 24 | J45: =ROUND((K45-I45)/I45*100,2) -> 79.17 | K45: 43
A46: 529 | B46: SLEEPWEAR | C46: LOUNGEWEAR | D46: =CONCATENATE(UPPER(LEFT(B46,1)&MID(B46,2,1)&"-"&LEFT(C46,1)&MID(C46,2,1)&"-"&LEFT(E46,1)&MID(E46,2,1)&"-"&LEFT(G46,1)&MID(G46,2,1)&"-"&LEFT(H46,1))) -> SL-LO-FL-BL-S | E46: Fleece Robe | F46: A warm and cozy robe perfect for mornings or evenings. | G46: Black | H46: S,L,XL,XXL | I46: 17 | J46: =ROUND((K46-I46)/I46*100,2) -> 105.88 | K46: 35
A47: 354 | B47: SLEEPWEAR | C47: LOUNGEWEAR | D47: =CONCATENATE(UPPER(LEFT(B47,1)&MID(B47,2,1)&"-"&LEFT(C47,1)&MID(C47,2,1)&"-"&LEFT(E47,1)&MID(E47,2,1)&"-"&LEFT(G47,1)&MID(G47,2,1)&"-"&LEFT(H47,1))) -> SL-LO-ME-BL-1 | E47: Memory Foam Slippers | F47: Plush and comfortable slippers for ultimate relaxation. | G47: Black,Grey | H47: 10 | I47: 14 | J47: =ROUND((K47-I47)/I47*100,2) -> 78.57 | K47: 25
A48: 435 | B48: SLEEPWEAR | C48: UNDERWEAR | D48: =CONCATENATE(UPPER(LEFT(B48,1)&MID(B48,2,1)&"-"&LEFT(C48,1)&MID(C48,2,1)&"-"&LEFT(E48,1)&MID(E48,2,1)&"-"&LEFT(G48,1)&MID(G48,2,1)&"-"&LEFT(H48,1))) -> SL-UN-SU-MU-L | E48: Supportive Sleep Bra | F48: Supportive Sleep Bra: Provides gentle support and comfort while sleeping. | G48: Multi-colors | H48: L,XL | I48: 15 | J48: =ROUND((K48-I48)/I48*100,2) -> 100 | K48: 30
A49: 175 | B49: SLEEPWEAR | C49: UNDERWEAR | D49: =CONCATENATE(UPPER(LEFT(B49,1)&MID(B49,2,1)&"-"&LEFT(C49,1)&MID(C49,2,1)&"-"&LEFT(E49,1)&MID(E49,2,1)&"-"&LEFT(G49,1)&MID(G49,2,1)&"-"&LEFT(H49,1))) -> SL-UN-SO-MU-L | E49: Soft Modal Sleep Shorts | F49: Breathable and lightweight shorts for a comfortable night's sleep. | G49: Multi-colors | H49: L,XL,XXL | I49: 12 | J49: =ROUND((K49-I49)/I49*100,2) -> 66.67 | K49: 20
A50: 476 | B50: SLEEPWEAR | C50: UNDERWEAR | D50: =CONCATENATE(UPPER(LEFT(B50,1)&MID(B50,2,1)&"-"&LEFT(C50,1)&MID(C50,2,1)&"-"&LEFT(E50,1)&MID(E50,2,1)&"-"&LEFT(G50,1)&MID(G50,2,1)&"-"&LEFT(H50,1))) -> SL-UN-RE-MU-L | E50: Relaxed-Fit Sleep Shirt | F50: A comfortable and loose-fitting top for added comfort. | G50: Multi-colors | H50: L,XL,XXL | I50: 13 | J50: =ROUND((K50-I50)/I50*100,2) -> 76.92 | K50: 23
B53: TOTAL NO OF PRODUCTS
B54: =SUM(A56:A71) -> 5239
A55: NO OF PRODUCTS | B55: CATEGORY | C55: SUB-CATEGORY | D55: REFERENCE | E55: PRODUCT NAME | F55: DESCRIPTION | G55: COLOUR | H55: SIZE | I55: COST PRICE (€) | J55: MARGIN (%) | K55: PRICE (€)
A56: 656 | B56: ACCESSORIES | C56: BAGS | D56: =CONCATENATE(UPPER(LEFT(B56,1)&MID(B56,2,1)&"-"&LEFT(C56,1)&MID(C56,2,1)&"-"&LEFT(E56,1)&MID(E56,2,1)&"-"&LEFT(G56,1)&MID(G56,2,1)&"-"&LEFT(H56,1)&MID(H56,2,1))) -> AC-BA-SP-RE-M | E56: Spacious Tote Bag | F56: Spacious Tote Bag: Perfect for carrying everyday essentials or larger items. | G56: red, yellow, brown, nude, pink, white, blue, green | H56: M | I56: 32 | J56: =ROUND((K56-I56)/I56*100,2) -> 34.38 | K56: 43
A57: 390 | B57: ACCESSORIES | C57: BAGS | D57: =CONCATENATE(UPPER(LEFT(B57,1)&MID(B57,2,1)&"-"&LEFT(C57,1)&MID(C57,2,1)&"-"&LEFT(E57,1)&MID(E57,2,1)&"-"&LEFT(G57,1)&MID(G57,2,1)&"-"&LEFT(H57,1)&MID(H57,2,1))) -> AC-BA-FU-BL-M | E57: Functional Backpack | F57: Ideal for carrying school supplies, work essentials, or travel items. | G57: Black,nude,red | H57: M | I57: 45 | J57: =ROUND((K57-I57)/I57*100,2) -> 33.33 | K57: 60
A58: 707 | B58: ACCESSORIES | C58: BAGS | D58: =CONCATENATE(UPPER(LEFT(B58,1)&MID(B58,2,1)&"-"&LEFT(C58,1)&MID(C58,2,1)&"-"&LEFT(E58,1)&MID(E58,2,1)&"-"&LEFT(G58,1)&MID(G58,2,1)&"-"&LEFT(H58,1)&MID(H58,2,1))) -> AC-BA-SL-RE-M | E58: Sleek Crossbody Bag | F58: A stylish and convenient option for hands-free carrying. | G58: red, yellow, brown, nude, pink, white, blue, green | H58: M | I58: 21 | J58: =ROUND((K58-I58)/I58*100,2) -> 66.67 | K58: 35
A59: 343 | B59: ACCESSORIES | C59: BAGS | D59: =CONCATENATE(UPPER(LEFT(B59,1)&MID(B59,2,1)&"-"&LEFT(C59,1)&MID(C59,2,1)&"-"&LEFT(E59,1)&MID(E59,2,1)&"-"&LEFT(G59,1)&MID(G59,2,1)&"-"&LEFT(H59,1)&MID(H59,2,1))) -> AC-BA-EL-RE-M | E59: Elegant Clutch | F59: A sophisticated and compact bag for formal occasions. | G59: red, yellow, brown, nude, pink, white, blue, green | H59: M | I59: 38 | J59: =ROUND((K59-I59)/I59*100,2) -> 31.58 | K59: 50
A60: 345 | B60: ACCESSORIES | C60: BAGS | D60: =CONCATENATE(UPPER(LEFT(B60,1)&MID(B60,2,1)&"-"&LEFT(C60,1)&MID(C60,2,1)&"-"&LEFT(E60,1)&MID(E60,2,1)&"-"&LEFT(G60,1)&MID(G60,2,1)&"-"&LEFT(H60,1)&MID(H60,2,1))) -> AC-BA-PR-RE-M | E60: Professional Briefcase | F60: A structured and durable bag for carrying work documents and laptops. | G60: red, yellow, brown, nude, pink, white, blue, green | H60: M | I60: 60 | J60: =ROUND((K60-I60)/I60*100,2) -> 25 | K60: 75
A61: 765 | B61: ACCESSORIES | C61: BELTS | D61: =CONCATENATE(UPPER(LEFT(B61,1)&MID(B61,2,1)&"-"&LEFT(C61,1)&MID(C61,2,1)&"-"&LEFT(E61,1)&MID(E61,2,1)&"-"&LEFT(G61,1)&MID(G61,2,1)&"-"&LEFT(H61,1)&MID(H61,2,1))) -> AC-BE-GE-BL-35 | E61: Genuine Leather Belt | F61: A classic and durable belt for everyday use. | G61: Black,Brown | H61: 35 | I61: 25 | J61: =ROUND((K61-I61)/I61*100,2) -> 80 | K61: 45
A62: 445 | B62: ACCESSORIES | C62: BELTS | D62: =CONCATENATE(UPPER(LEFT(B62,1)&MID(B62,2,1)&"-"&LEFT(C62,1)&MID(C62,2,1)&"-"&LEFT(E62,1)&MID(E62,2,1)&"-"&LEFT(G62,1)&MID(G62,2,1)&"-"&LEFT(H62,1)&MID(H62,2,1))) -> AC-BE-WO-BL-35 | E62: Woven Canvas Belt | F62: A casual and stylish belt perfect for summer outfits. | G62: Black,Brown | H62: 35 | I62: 20 | J62: =ROUND((K62-I62)/I62*100,2) -> 50 | K62: 30
A63: 200 | B63: ACCESSORIES | C63: BELTS | D63: =CONCATENATE(UPPER(LEFT(B63,1)&MID(B63,2,1)&"-"&LEFT(C63,1)&MID(C63,2,1)&"-"&LEFT(E63,1)&MID(E63,2,1)&"-"&LEFT(G63,1)&MID(G63,2,1)&"-"&LEFT(H63,1)&MID(H63,2,1))) -> AC-BE-BR-BL-35 | E63: Braided Leather Belt | F63: Adds a touch of western-inspired style to your look. | G63: Black,Brown | H63: 35 | I63: 20 | J63: =ROUND((K63-I63)/I63*100,2) -> 65 | K63: 33
A64: 230 | B64: ACCESSORIES | C64: BELTS | D64: =CONCATENATE(UPPER(LEFT(B64,1)&MID(B64,2,1)&"-"&LEFT(C64,1)&MID(C64,2,1)&"-"&LEFT(E64,1)&MID(E64,2,1)&"-"&LEFT(G64,1)&MID(G64,2,1)&"-"&LEFT(H64,1)&MID(H64,2,1))) -> AC-BE-SL-BL-35 | E64: Slim Dress Belt | F64: A polished and sophisticated belt for formal occasions. | G64: Black,Brown | H64: 35 | I64: 23 | J64: =ROUND((K64-I64)/I64*100,2) -> 73.91 | K64: 40
A65: 120 | B65: ACCESSORIES | C65: BELTS | D65: =CONCATENATE(UPPER(LEFT(B65,1)&MID(B65,2,1)&"-"&LEFT(C65,1)&MID(C65,2,1)&"-"&LEFT(E65,1)&MID(E65,2,1)&"-"&LEFT(G65,1)&MID(G65,2,1)&"-"&LEFT(H65,1)&MID(H65,2,1))) -> AC-BE-CA-BL-35 | E65: Canvas Webbing Belt | F65: A versatile and adjustable belt for casual wear. | G65: Black,Brown | H65: 35 | I65: 18 | J65: =ROUND((K65-I65)/I65*100,2) -> 38.89 | K65: 25
A66: 200 | B66: ACCESSORIES | C66: HATS | D66: =CONCATENATE(UPPER(LEFT(B66,1)&MID(B66,2,1)&"-"&LEFT(C66,1)&MID(C66,2,1)&"-"&LEFT(E66,1)&MID(E66,2,1)&"-"&LEFT(G66,1)&MID(G66,2,1)&"-"&LEFT(H66,1)&MID(H66,2,1))) -> AC-HA-CO-BL-7 | E66: Cozy Cable-Knit Beanie | F66: : A warm and stylish beanie perfect for winter weather. | G66: Blue | H66: 7 | I66: 10 | J66: =ROUND((K66-I66)/I66*100,2) -> 150 | K66: 25
A67: 305 | B67: ACCESSORIES | C67: HATS | D67: =CONCATENATE(UPPER(LEFT(B67,1)&MID(B67,2,1)&"-"&LEFT(C67,1)&MID(C67,2,1)&"-"&LEFT(E67,1)&MID(E67,2,1)&"-"&LEFT(G67,1)&MID(G67,2,1)&"-"&LEFT(H67,1)&MID(H67,2,1))) -> AC-HA-CL-GR-7 | E67: Classic Baseball Cap | F67: : A timeless and versatile cap with an adjustable strap. | G67: Grey,Orange | H67: 7 | I67: 9 | J67: =ROUND((K67-I67)/I67*100,2) -> 122.22 | K67: 20
A68: 103 | B68: ACCESSORIES | C68: HATS | D68: =CONCATENATE(UPPER(LEFT(B68,1)&MID(B68,2,1)&"-"&LEFT(C68,1)&MID(C68,2,1)&"-"&LEFT(E68,1)&MID(E68,2,1)&"-"&LEFT(G68,1)&MID(G68,2,1)&"-"&LEFT(H68,1)&MID(H68,2,1))) -> AC-HA-RE-BR-7 | E68: Reversible Bucket Hat | F68: : A trendy and practical bucket hat with two color options. | G68: Brown | H68: 7 | I68: 15 | J68: =ROUND((K68-I68)/I68*100,2) -> 100 | K68: 30
A69: 200 | B69: ACCESSORIES | C69: HATS | D69: =CONCATENATE(UPPER(LEFT(B69,1)&MID(B69,2,1)&"-"&LEFT(C69,1)&MID(C69,2,1)&"-"&LEFT(E69,1)&MID(E69,2,1)&"-"&LEFT(G69,1)&MID(G69,2,1)&"-"&LEFT(H69,1)&MID(H69,2,1))) -> AC-HA-WI-BR-7 | E69: Wide-Brim Sun Hat | F69: : Provides shade and protection from the sun on hot days. | G69: Brown | H69: 7 | I69: 21 | J69: =ROUND((K69-I69)/I69*100,2) -> 66.67 | K69: 35
A70: 230 | B70: ACCESSORIES | C70: HATS | D70: =CONCATENATE(UPPER(LEFT(B70,1)&MID(B70,2,1)&"-"&LEFT(C70,1)&MID(C70,2,1)&"-"&LEFT(E70,1)&MID(E70,2,1)&"-"&LEFT(G70,1)&MID(G70,2,1)&"-"&LEFT(H70,1)&MID(H70,2,1))) -> AC-HA-FE-BL-6 | E70: Felt Fedora | F70: : A sophisticated and stylish fedora for a classic look. | G70: Black,Brown | H70: 6 | I70: 35 | J70: =ROUND((K70-I70)/I70*100,2) -> 42.86 | K70: 50

Sheet WHS STK MGT & ALLOC.
A1: WAREHOUSE STOCK MANAGEMENT AND ALLOCATION
J4: WEEKLY STOCK ALLOCATION
A6: REFERENCE | B6: PRODUCT NAME | C6: CATEGORY | D6: SUB-CATEGORY | E6: DESCRIPTION | F6: COLOUR | G6: SIZE | H6: TOTAL STOCK | I6: REMANING STOCK | J6: 1ST WEEK % ALLOCATION | K6: 1ST WEEK | L6: 2ND WEEK % ALLOCATION | M6: 2ND WEEK | N6: 3RD WEEK % ALLOCATION | O6: 3RD WEEK | P6: 4TH WEEK % ALLOCATION | Q6: 4TH WEEK | R6: 5TH WEEK % ALLOCATION | S6: 5TH WEEK | T6: 6TH WEEK % ALLOCATION | U6: 6TH WEEK | V6: 7TH WEEK % ALLOCATION | W6: 7TH WEEK | X6: 8TH WEEK % ALLOCATION | Y6: 8TH WEEK
A7: TO-TE-CO-GR-58 | B7: =IFERROR(INDEX('REFERENCING & DATABASE'!$E$7:$E$131,MATCH($A7,'REFERENCING & DATABASE'!$D$7:$D$131,0)),"") -> Cozy Comfort Tee | C7: =IFERROR(INDEX('REFERENCING & DATABASE'!$B$7:$B$131,MATCH($A7,'REFERENCING & DATABASE'!$D$7:$D$131,0)),"") -> TOPS | D7: =IFERROR(INDEX('REFERENCING & DATABASE'!$C$7:$C$131,MATCH($A7,'REFERENCING & DATABASE'!$D$7:$D$131,0)),"") -> TEES | E7: =IFERROR(INDEX('REFERENCING & DATABASE'!$F$7:$F$131,MATCH($A7,'REFERENCING & DATABASE'!$D$7:$D$131,0)),"") -> A relaxed-fit tee made from super-soft cotton, perfect for everyday wear. | F7: =IFERROR(INDEX('REFERENCING & DATABASE'!$G$7:$G$131,MATCH($A7,'REFERENCING & DATABASE'!$D$7:$D$131,0)),"") -> Grey,Black,Blue | G7: =IFERROR(INDEX('REFERENCING & DATABASE'!$H$7:$H$131,MATCH($A7,'REFERENCING & DATABASE'!$D$7:$D$131,0)),"") -> 58 | H7: =IFERROR(INDEX('REFERENCING & DATABASE'!$A$7:$A$131,MATCH($A7,'REFERENCING & DATABASE'!$D$7:$D$131,0)),"") -> 450 | I7: =H7-SUM($K7,$M7,$O7,$Q7) -> 400 | J7: =ROUND((($K7/$H7)*100),3) -> 11.111 | K7: =SUMIFS('IN STORE SALES RECORD'!$E$6:$E$97,'IN STORE SALES RECORD'!$A$6:$A$97, "WEEK 1",'IN STORE SALES RECORD'!$D$6:$D$97,'WHS STK MGT & ALLOC.'!$A7)+10 -> 50 | L7: =ROUND(($M7/($H7-$K7))*100,3) -> 0 | M7: =SUMIFS('IN STORE SALES RECORD'!$E$6:$E$97,'IN STORE SALES RECORD'!$A$6:$A$97, "WEEK 6",'IN STORE SALES RECORD'!$D$6:$D$97,'WHS STK MGT & ALLOC.'!$A7) -> 0 | N7: =ROUND(($O7/($H7-($M7+$K7))*100),3) -> 0 | O7: =SUMIFS('IN STORE SALES RECORD'!$E$6:$E$97,'IN STORE SALES RECORD'!$A$6:$A$97, "WEEK 6",'IN STORE SALES RECORD'!$D$6:$D$97,'WHS STK MGT & ALLOC.'!$A7) -> 0 | P7: =ROUND(($Q7/($H7-($M7+$K7+$O7))*100),3) -> 0 | Q7: =SUMIFS('IN STORE SALES RECORD'!$E$6:$E$97,'IN STORE SALES RECORD'!$A$6:$A$97, "WEEK 6",'IN STORE SALES RECORD'!$D$6:$D$97,'WHS STK MGT & ALLOC.'!$A7) -> 0 | R7: =ROUND(($S7/($H7-($M7+$K7+$O7+$Q7))*100),3) -> 0 | S7: =SUMIFS('IN STORE SALES RECORD'!$E$6:$E$97,'IN STORE SALES RECORD'!$A$6:$A$97, "WEEK 6",'IN STORE SALES RECORD'!$D$6:$D$97,'WHS STK MGT & ALLOC.'!$A7) -> 0 | T7: =ROUND(($U7/($H7-($M7+$K7+$O7+$Q7+$S7))*100),3) -> 0 | U7: =SUMIFS('IN STORE SALES RECORD'!$E$6:$E$97,'IN STORE SALES RECORD'!$A$6:$A$97, "WEEK 6",'IN STORE SALES RECORD'!$D$6:$D$97,'WHS STK MGT & ALLOC.'!$A7) -> 0 | V7: =ROUND(($W7/($H7-($M7+$K7+$O7+$Q7+$S7+$U7))*100),3) -> 0 | W7: =SUMIFS('IN STORE SALES RECORD'!$E$6:$E$97,'IN STORE SALES RECORD'!$A$6:$A$97, "WEEK 6",'IN STORE SALES RECORD'!$D$6:$D$97,'WHS STK MGT & ALLOC.'!$A7) -> 0 | X7: =ROUND(($Y7/($H7-($M7+$K7+$O7+$Q7+$S7+$U7+$W7))*100),3) -> 0 | Y7: =SUMIFS('IN STORE SALES RECORD'!$E$6:$E$97,'IN STORE SALES RECORD'!$A$6:$A$97, "WEEK 6",'IN STORE SALES RECORD'!$D$6:$D$97,'WHS STK MGT & ALLOC.'!$A7) -> 0
A8: TO-TE-GR-BL-58 | B8: =IFERROR(INDEX('REFERENCING & DATABASE'!$E$7:$E$131,MATCH($A8,'REFERENCING & DATABASE'!$D$7:$D$131,0)),"") -> Graphic Statement Tee | C8: =IFERROR(INDEX('REFERENCING & DATABASE'!$B$7:$B$131,MATCH($A8,'REFERENCING & DATABASE'!$D$7:$D$131,0)),"") -> TOPS | D8: =IFERROR(INDEX('REFERENCING & DATABASE'!$C$7:$C$131,MATCH($A8,'REFERENCING & DATABASE'!$D$7:$D$131,0)),"") -> TEES | E8: =IFERROR(INDEX('REFERENCING & DATABASE'!$F$7:$F$131,MATCH($A8,'REFERENCING & DATABASE'!$D$7:$D$131,0)),"") -> A bold graphic tee that expresses your unique style. | F8: =IFERROR(INDEX('REFERENCING & DATABASE'!$G$7:$G$131,MATCH($A8,'REFERENCING & DATABASE'!$D$7:$D$131,0)),"") -> Blue,Black,White | G8: =IFERROR(INDEX('REFERENCING & DATABASE'!$H$7:$H$131,MATCH($A8,'REFERENCING & DATABASE'!$D$7:$D$131,0)),"") -> 58 | H8: =IFERROR(INDEX('REFERENCING & DATABASE'!$A$7:$A$131,MATCH($A8,'REFERENCING & DATABASE'!$D$7:$D$131,0)),"") -> 300 | I8: =H8-SUM($K8,$M8,$O8,$Q8) -> 290 | J8: =ROUND((($K8/$H8)*100),3) -> 3.333 | K8: =SUMIFS('IN STORE SALES RECORD'!$E$6:$E$97,'IN STORE SALES RECORD'!$A$6:$A$97, "WEEK 1",'IN STORE SALES RECORD'!$D$6:$D$97,'WHS STK MGT & ALLOC.'!$A8)+10 -> 10 | L8: =ROUND(($M8/($H8-$K8))*100,3) -> 0 | M8: =SUMIFS('IN STORE SALES RECORD'!$E$6:$E$97,'IN STORE SALES RECORD'!$A$6:$A$97, "WEEK 6",'IN STORE SALES RECORD'!$D$6:$D$97,'WHS STK MGT & ALLOC.'!$A8) -> 0 | N8: =ROUND(($O8/($H8-($M8+$K8))*100),3) -> 0 | O8: =SUMIFS('IN STORE SALES RECORD'!$E$6:$E$97,'IN STORE SALES RECORD'!$A$6:$A$97, "WEEK 6",'IN STORE SALES RECORD'!$D$6:$D$97,'WHS STK MGT & ALLOC.'!$A8) -> 0 | P8: =ROUND(($Q8/($H8-($M8+$K8+$O8))*100),3) -> 0 | Q8: =SUMIFS('IN STORE SALES RECORD'!$E$6:$E$97,'IN STORE SALES RECORD'!$A$6:$A$97, "WEEK 6",'IN STORE SALES RECORD'!$D$6:$D$97,'WHS STK MGT & ALLOC.'!$A8) -> 0 | R8: =ROUND(($S8/($H8-($M8+$K8+$O8+$Q8))*100),3) -> 0 | S8: =SUMIFS('IN STORE SALES RECORD'!$E$6:$E$97,'IN STORE SALES RECORD'!$A$6:$A$97, "WEEK 6",'IN STORE SALES RECORD'!$D$6:$D$97,'WHS STK MGT & ALLOC.'!$A8) -> 0 | T8: =ROUND(($U8/($H8-($M8+$K8+$O8+$Q8+$S8))*100),3) -> 0 | U8: =SUMIFS('IN STORE SALES RECORD'!$E$6:$E$97,'IN STORE SALES RECORD'!$A$6:$A$97, "WEEK 6",'IN STORE SALES RECORD'!$D$6:$D$97,'WHS STK MGT & ALLOC.'!$A8) -> 0 | V8: =ROUND(($W8/($H8-($M8+$K8+$O8+$Q8+$S8+$U8))*100),3) -> 0 | W8: =SUMIFS('IN STORE SALES RECORD'!$E$6:$E$97,'IN STORE SALES RECORD'!$A$6:$A$97, "WEEK 6",'IN STORE SALES RECORD'!$D$6:$D$97,'WHS STK MGT & ALLOC.'!$A8) -> 0 | X8: =ROUND(($Y8/($H8-($M8+$K8+$O8+$Q8+$S8+$U8+$W8))*100),3) -> 0 | Y8: =SUMIFS('IN STORE SALES RECORD'!$E$6:$E$97,'IN STORE SALES RECORD'!$A$6:$A$97, "WEEK 6",'IN STORE SALES RECORD'!$D$6:$D$97,'WHS STK MGT & ALLOC.'!$A8) -> 0
A9: TO-SH-CL-PI-10 | B9: =IFERROR(INDEX('REFERENCING & DATABASE'!$E$7:$E$131,MATCH($A9,'REFERENCING & DATABASE'!$D$7:$D$131,0)),"") -> Classic Button-Down Shirt | C9: =IFERROR(INDEX('REFERENCING & DATABASE'!$B$7:$B$131,MATCH($A9,'REFERENCING & DATABASE'!$D$7:$D$131,0)),"") -> TOPS | D9: =IFERROR(INDEX('REFERENCING & DATABASE'!$C$7:$C$131,MATCH($A9,'REFERENCING & DATABASE'!$D$7:$D$131,0)),"") -> SHIRTS | E9: =IFERROR(INDEX('REFERENCING & DATABASE'!$F$7:$F$131,MATCH($A9,'REFERENCING & DATABASE'!$D$7:$D$131,0)),"") -> A timeless and versatile shirt for work or casual occasions. | F9: =IFERROR(INDEX('REFERENCING & DATABASE'!$G$7:$G$131,MATCH($A9,'REFERENCING & DATABASE'!$D$7:$D$131,0)),"") -> Pink, Brown,Yellow | G9: =IFERROR(INDEX('REFERENCING & DATABASE'!$H$7:$H$131,MATCH($A9,'REFERENCING & DATABASE'!$D$7:$D$131,0)),"") -> 10 | H9: =IFERROR(INDEX('REFERENCING & DATABASE'!$A$7:$A$131,MATCH($A9,'REFERENCING & DATABASE'!$D$7:$D$131,0)),"") -> 300 | I9: =H9-SUM($K9,$M9,$O9,$Q9,$S9,$U9,$W9,$Y9) -> 60 | J9: =ROUND((($K9/$H9)*100),3) -> 80 | K9: =SUMIFS('IN STORE SALES RECORD'!$E$6:$E$97,'IN STORE SALES RECORD'!$A$6:$A$97, "WEEK 1",'IN STORE SALES RECORD'!$D$6:$D$97,'WHS STK MGT & ALLOC.'!$A9)+10 -> 240 | L9: =ROUND(($M9/($H9-$K9))*100,3) -> 0 | M9: =SUMIFS('IN STORE SALES RECORD'!$E$6:$E$97,'IN STORE SALES RECORD'!$A$6:$A$97, "WEEK 6",'IN STORE SALES RECORD'!$D$6:$D$97,'WHS STK MGT & ALLOC.'!$A9) -> 0 | N9: =ROUND(($O9/($H9-($M9+$K9))*100),3) -> 0 | O9: =SUMIFS('IN STORE SALES RECORD'!$E$6:$E$97,'IN STORE SALES RECORD'!$A$6:$A$97, "WEEK 6",'IN STORE SALES RECORD'!$D$6:$D$97,'WHS STK MGT & ALLOC.'!$A9) -> 0 | P9: =ROUND(($Q9/($H9-($M9+$K9+$O9))*100),3) -> 0 | Q9: =SUMIFS('IN STORE SALES RECORD'!$E$6:$E$97,'IN STORE SALES RECORD'!$A$6:$A$97, "WEEK 6",'IN STORE SALES RECORD'!$D$6:$D$97,'WHS STK MGT & ALLOC.'!$A9) -> 0 | R9: =ROUND(($S9/($H9-($M9+$K9+$O9+$Q9))*100),3) -> 0 | S9: =SUMIFS('IN STORE SALES RECORD'!$E$6:$E$97,'IN STORE SALES RECORD'!$A$6:$A$97, "WEEK 6",'IN STORE SALES RECORD'!$D$6:$D$97,'WHS STK MGT & ALLOC.'!$A9) -> 0 | T9: =ROUND(($U9/($H9-($M9+$K9+$O9+$Q9+$S9))*100),3) -> 0 | U9: =SUMIFS('IN STORE SALES RECORD'!$E$6:$E$97,'IN STORE SALES RECORD'!$A$6:$A$97, "WEEK 6",'IN STORE SALES RECORD'!$D$6:$D$97,'WHS STK MGT & ALLOC.'!$A9) -> 0 | V9: =ROUND(($W9/($H9-($M9+$K9+$O9+$Q9+$S9+$U9))*100),3) -> 0 | W9: =SUMIFS('IN STORE SALES RECORD'!$E$6:$E$97,'IN STORE SALES RECORD'!$A$6:$A$97, "WEEK 6",'IN STORE SALES RECORD'!$D$6:$D$97,'WHS STK MGT & ALLOC.'!$A9) -> 0 | X9: =ROUND(($Y9/($H9-($M9+$K9+$O9+$Q9+$S9+$U9+$W9))*100),3) -> 0 | Y9: =SUMIFS('IN STORE SALES RECORD'!$E$6:$E$97,'IN STORE SALES RECORD'!$A$6:$A$97, "WEEK 6",'IN STORE SALES RECORD'!$D$6:$D$97,'WHS STK MGT & ALLOC.'!$A9) -> 0
A10: TO-SH-LI-PI-10 | B10: =IFERROR(INDEX('REFERENCING & DATABASE'!$E$7:$E$131,MATCH($A10,'REFERENCING & DATABASE'!$D$7:$D$131,0)),"") -> Linen Blend Shirt | C10: =IFERROR(INDEX('REFERENCING & DATABASE'!$B$7:$B$131,MATCH($A10,'REFERENCING & DATABASE'!$D$7:$D$131,0)),"") -> TOPS | D10: =IFERROR(INDEX('REFERENCING & DATABASE'!$C$7:$C$131,MATCH($A10,'REFERENCING & DATABASE'!$D$7:$D$131,0)),"") -> SHIRTS | E10: =IFERROR(INDEX('REFERENCING & DATABASE'!$F$7:$F$131,MATCH($A10,'REFERENCING & DATABASE'!$D$7:$D$131,0)),"") -> A lightweight and breathable shirt for warmer weather. | F10: =IFERROR(INDEX('REFERENCING & DATABASE'!$G$7:$G$131,MATCH($A10,'REFERENCING & DATABASE'!$D$7:$D$131,0)),"") -> Pink, Clear | G10: =IFERROR(INDEX('REFERENCING & DATABASE'!$H$7:$H$131,MATCH($A10,'REFERENCING & DATABASE'!$D$7:$D$131,0)),"") -> 10 | H10: =IFERROR(INDEX('REFERENCING & DATABASE'!$A$7:$A$131,MATCH($A10,'REFERENCING & DATABASE'!$D$7:$D$131,0)),"") -> 400 | I10: =H10-SUM($K10,$M10,$O10,$Q10) -> 390 | J10: =ROUND((($K10/$H10)*100),3) -> 2.5 | K10: =SUMIFS('IN STORE SALES RECORD'!$E$6:$E$97,'IN STORE SALES RECORD'!$A$6:$A$97, "WEEK 1",'IN STORE SALES RECORD'!$D$6:$D$97,'WHS STK MGT & ALLOC.'!$A10)+10 -> 10 | L10: =ROUND(($M10/($H10-$K10))*100,3) -> 0 | M10: =SUMIFS('IN STORE SALES RECORD'!$E$6:$E$97,'IN STORE SALES RECORD'!$A$6:$A$97, "WEEK 6",'IN STORE SALES RECORD'!$D$6:$D$97,'WHS STK MGT & ALLOC.'!$A10) -> 0 | N10: =ROUND(($O10/($H10-($M10+$K10))*100),3) -> 0 | O10: =SUMIFS('IN STORE SALES RECORD'!$E$6:$E$97,'IN STORE SALES RECORD'!$A$6:$A$97, "WEEK 6",'IN STORE SALES RECORD'!$D$6:$D$97,'WHS STK MGT & ALLOC.'!$A10) -> 0 | P10: =ROUND(($Q10/($H10-($M10+$K10+$O10))*100),3) -> 0 | Q10: =SUMIFS('IN STORE SALES RECORD'!$E$6:$E$97,'IN STORE SALES RECORD'!$A$6:$A$97, "WEEK 6",'IN STORE SALES RECORD'!$D$6:$D$97,'WHS STK MGT & ALLOC.'!$A10) -> 0 | R10: =ROUND(($S10/($H10-($M10+$K10+$O10+$Q10))*100),3) -> 0 | S10: =SUMIFS('IN STORE SALES RECORD'!$E$6:$E$97,'IN STORE SALES RECORD'!$A$6:$A$97, "WEEK 6",'IN STORE SALES RECORD'!$D$6:$D$97,'WHS STK MGT & ALLOC.'!$A10) -> 0 | T10: =ROUND(($U10/($H10-($M10+$K10+$O10+$Q10+$S10))*100),3) -> 0 | U10: =SUMIFS('IN STORE SALES RECORD'!$E$6:$E$97,'IN STORE SALES RECORD'!$A$6:$A$97, "WEEK 6",'IN STORE SALES RECORD'!$D$6:$D$97,'WHS STK MGT & ALLOC.'!$A10) -> 0 | V10: =ROUND(($W10/($H10-($M10+$K10+$O10+$Q10+$S10+$U10))*100),3) -> 0 | W10: =SUMIFS('IN STORE SALES RECORD'!$E$6:$E$97,'IN STORE SALES RECORD'!$A$6:$A$97, "WEEK 6",'IN STORE SALES RECORD'!$D$6:$D$97,'WHS STK MGT & ALLOC.'!$A10) -> 0 | X10: =ROUND(($Y10/($H10-($M10+$K10+$O10+$Q10+$S10+$U10+$W10))*100),3) -> 0 | Y10: =SUMIFS('IN STORE SALES RECORD'!$E$6:$E$97,'IN STORE SALES RECORD'!$A$6:$A$97, "WEEK 6",'IN STORE SALES RECORD'!$D$6:$D$97,'WHS STK MGT & ALLOC.'!$A10) -> 0
A11: TO-SW-CO-NU-10 | B11: =IFERROR(INDEX('REFERENCING & DATABASE'!$E$7:$E$131,MATCH($A11,'REFERENCING & DATABASE'!$D$7:$D$131,0)),"") -> Cozy Cable-Knit Sweater | C11: =IFERROR(INDEX('REFERENCING & DATABASE'!$B$7:$B$131,MATCH($A11,'REFERENCING & DATABASE'!$D$7:$D$131,0)),"") -> TOPS | D11: =IFERROR(INDEX('REFERENCING & DATABASE'!$C$7:$C$131,MATCH($A11,'REFERENCING & DATABASE'!$D$7:$D$131,0)),"") -> SWEATERS | E11: =IFERROR(INDEX('REFERENCING & DATABASE'!$F$7:$F$131,MATCH($A11,'REFERENCING & DATABASE'!$D$7:$D$131,0)),"") -> A warm and stylish sweater for cooler days. | F11: =IFERROR(INDEX('REFERENCING & DATABASE'!$G$7:$G$131,MATCH($A11,'REFERENCING & DATABASE'!$D$7:$D$131,0)),"") -> Nude, Brown | G11: =IFERROR(INDEX('REFERENCING & DATABASE'!$H$7:$H$131,MATCH($A11,'REFERENCING & DATABASE'!$D$7:$D$131,0)),"") -> 10 | H11: =IFERROR(INDEX('REFERENCING & DATABASE'!$A$7:$A$131,MATCH($A11,'REFERENCING & DATABASE'!$D$7:$D$131,0)),"") -> 200 | I11: =H11-SUM($K11,$M11,$O11,$Q11) -> 190 | J11: =ROUND((($K11/$H11)*100),3) -> 5 | K11: =SUMIFS('IN STORE SALES RECORD'!$E$6:$E$97,'IN STORE SALES RECORD'!$A$6:$A$97, "WEEK 1",'IN STORE SALES RECORD'!$D$6:$D$97,'WHS STK MGT & ALLOC.'!$A11)+10 -> 10 | L11: =ROUND(($M11/($H11-$K11))*100,3) -> 0 | M11: =SUMIFS('IN STORE SALES RECORD'!$E$6:$E$97,'IN STORE SALES RECORD'!$A$6:$A$97, "WEEK 6",'IN STORE SALES RECORD'!$D$6:$D$97,'WHS STK MGT & ALLOC.'!$A11) -> 0 | N11: =ROUND(($O11/($H11-($M11+$K11))*100),3) -> 0 | O11: =SUMIFS('IN STORE SALES RECORD'!$E$6:$E$97,'IN STORE SALES RECORD'!$A$6:$A$97, "WEEK 6",'IN STORE SALES RECORD'!$D$6:$D$97,'WHS STK MGT & ALLOC.'!$A11) -> 0 | P11: =ROUND(($Q11/($H11-($M11+$K11+$O11))*100),3) -> 0 | Q11: =SUMIFS('IN STORE SALES RECORD'!$E$6:$E$97,'IN STORE SALES RECORD'!$A$6:$A$97, "WEEK 6",'IN STORE SALES RECORD'!$D$6:$D$97,'WHS STK MGT & ALLOC.'!$A11) -> 0 | R11: =ROUND(($S11/($H11-($M11+$K11+$O11+$Q11))*100),3) -> 0 | S11: =SUMIFS('IN STORE SALES RECORD'!$E$6:$E$97,'IN STORE SALES RECORD'!$A$6:$A$97, "WEEK 6",'IN STORE SALES RECORD'!$D$6:$D$97,'WHS STK MGT & ALLOC.'!$A11) -> 0 | T11: =ROUND(($U11/($H11-($M11+$K11+$O11+$Q11+$S11))*100),3) -> 0 | U11: =SUMIFS('IN STORE SALES RECORD'!$E$6:$E$97,'IN STORE SALES RECORD'!$A$6:$A$97, "WEEK 6",'IN STORE SALES RECORD'!$D$6:$D$97,'WHS STK MGT & ALLOC.'!$A11) -> 0 | V11: =ROUND(($W11/($H11-($M11+$K11+$O11+$Q11+$S11+$U11))*100),3) -> 0 | W11: =SUMIFS('IN STORE SALES RECORD'!$E$6:$E$97,'IN STORE SALES RECORD'!$A$6:$A$97, "WEEK 6",'IN STORE SALES RECORD'!$D$6:$D$97,'WHS STK MGT & ALLOC.'!$A11) -> 0 | X11: =ROUND(($Y11/($H11-($M11+$K11+$O11+$Q11+$S11+$U11+$W11))*100),3) -> 0 | Y11: =SUMIFS('IN STORE SALES RECORD'!$E$6:$E$97,'IN STORE SALES RECORD'!$A$6:$A$97, "WEEK 6",'IN STORE SALES RECORD'!$D$6:$D$97,'WHS STK MGT & ALLOC.'!$A11) -> 0
A12: TO-SW-HO-BL-10 | B12: =IFERROR(INDEX('REFERENCING & DATABASE'!$E$7:$E$131,MATCH($A12,'REFERENCING & DATABASE'!$D$7:$D$131,0)),"") -> Hooded Sweatshirt | C12: =IFERROR(INDEX('REFERENCING & DATABASE'!$B$7:$B$131,MATCH($A12,'REFERENCING & DATABASE'!$D$7:$D$131,0)),"") -> TOPS | D12: =IFERROR(INDEX('REFERENCING & DATABASE'!$C$7:$C$131,MATCH($A12,'REFERENCING & DATABASE'!$D$7:$D$131,0)),"") -> SWEATERS | E12: =IFERROR(INDEX('REFERENCING & DATABASE'!$F$7:$F$131,MATCH($A12,'REFERENCING & DATABASE'!$D$7:$D$131,0)),"") -> A comfortable and casual sweatshirt perfect for lounging or layering. | F12: =IFERROR(INDEX('REFERENCING & DATABASE'!$G$7:$G$131,MATCH($A12,'REFERENCING & DATABASE'!$D$7:$D$131,0)),"") -> Black,Grey | G12: =IFERROR(INDEX('REFERENCING & DATABASE'!$H$7:$H$131,MATCH($A12,'REFERENCING & DATABASE'!$D$7:$D$131,0)),"") -> 10 | H12: =IFERROR(INDEX('REFERENCING & DATABASE'!$A$7:$A$131,MATCH($A12,'REFERENCING & DATABASE'!$D$7:$D$131,0)),"") -> 300 | I12: =H12-SUM($K12,$M12,$O12,$Q12) -> 290 | J12: =ROUND((($K12/$H12)*100),3) -> 3.333 | K12: =SUMIFS('IN STORE SALES RECORD'!$E$6:$E$97,'IN STORE SALES RECORD'!$A$6:$A$97, "WEEK 1",'IN STORE SALES RECORD'!$D$6:$D$97,'WHS STK MGT & ALLOC.'!$A12)+10 -> 10 | L12: =ROUND(($M12/($H12-$K12))*100,3) -> 0 | M12: =SUMIFS('IN STORE SALES RECORD'!$E$6:$E$97,'IN STORE SALES RECORD'!$A$6:$A$97, "WEEK 6",'IN STORE SALES RECORD'!$D$6:$D$97,'WHS STK MGT & ALLOC.'!$A12) -> 0 | N12: =ROUND(($O12/($H12-($M12+$K12))*100),3) -> 0 | O12: =SUMIFS('IN STORE SALES RECORD'!$E$6:$E$97,'IN STORE SALES RECORD'!$A$6:$A$97, "WEEK 6",'IN STORE SALES RECORD'!$D$6:$D$97,'WHS STK MGT & ALLOC.'!$A12) -> 0 | P12: =ROUND(($Q12/($H12-($M12+$K12+$O12))*100),3) -> 0 | Q12: =SUMIFS('IN STORE SALES RECORD'!$E$6:$E$97,'IN STORE SALES RECORD'!$A$6:$A$97, "WEEK 6",'IN STORE SALES RECORD'!$D$6:$D$97,'WHS STK MGT & ALLOC.'!$A12) -> 0 | R12: =ROUND(($S12/($H12-($M12+$K12+$O12+$Q12))*100),3) -> 0 | S12: =SUMIFS('IN STORE SALES RECORD'!$E$6:$E$97,'IN STORE SALES RECORD'!$A$6:$A$97, "WEEK 6",'IN STORE SALES RECORD'!$D$6:$D$97,'WHS STK MGT & ALLOC.'!$A12) -> 0 | T12: =ROUND(($U12/($H12-($M12+$K12+$O12+$Q12+$S12))*100),3) -> 0 | U12: =SUMIFS('IN STORE SALES RECORD'!$E$6:$E$97,'IN STORE SALES RECORD'!$A$6:$A$97, "WEEK 6",'IN STORE SALES RECORD'!$D$6:$D$97,'WHS STK MGT & ALLOC.'!$A12) -> 0 | V12: =ROUND(($W12/($H12-($M12+$K12+$O12+$Q12+$S12+$U12))*100),3) -> 0 | W12: =SUMIFS('IN STORE SALES RECORD'!$E$6:$E$97,'IN STORE SALES RECORD'!$A$6:$A$97, "WEEK 6",'IN STORE SALES RECORD'!$D$6:$D$97,'WHS STK MGT & ALLOC.'!$A12) -> 0 | X12: =ROUND(($Y12/($H12-($M12+$K12+$O12+$Q12+$S12+$U12+$W12))*100),3) -> 0 | Y12: =SUMIFS('IN STORE SALES RECORD'!$E$6:$E$97,'IN STORE SALES RECORD'!$A$6:$A$97, "WEEK 6",'IN STORE SALES RECORD'!$D$6:$D$97,'WHS STK MGT & ALLOC.'!$A12) -> 0
A13: TO-JA-DE-NU-10 | B13: =IFERROR(INDEX('REFERENCING & DATABASE'!$E$7:$E$131,MATCH($A13,'REFERENCING & DATABASE'!$D$7:$D$131,0)),"") -> Denim Jacket | C13: =IFERROR(INDEX('REFERENCING & DATABASE'!$B$7:$B$131,MATCH($A13,'REFERENCING & DATABASE'!$D$7:$D$131,0)),"") -> TOPS | D13: =IFERROR(INDEX('REFERENCING & DATABASE'!$C$7:$C$131,MATCH($A13,'REFERENCING & DATABASE'!$D$7:$D$131,0)),"") -> JACKETS | E13: =IFERROR(INDEX('REFERENCING & DATABASE'!$F$7:$F$131,MATCH($A13,'REFERENCING & DATABASE'!$D$7:$D$131,0)),"") -> A timeless and versatile jacket that adds an edge to any outfit. | F13: =IFERROR(INDEX('REFERENCING & DATABASE'!$G$7:$G$131,MATCH($A13,'REFERENCING & DATABASE'!$D$7:$D$131,0)),"") -> Nude, Purple | G13: =IFERROR(INDEX('REFERENCING & DATABASE'!$H$7:$H$131,MATCH($A13,'REFERENCING & DATABASE'!$D$7:$D$131,0)),"") -> 10 | H13: =IFERROR(INDEX('REFERENCING & DATABASE'!$A$7:$A$131,MATCH($A13,'REFERENCING & DATABASE'!$D$7:$D$131,0)),"") -> 100 | I13: =H13-SUM($K13,$M13,$O13,$Q13) -> 90 | J13: =ROUND((($K13/$H13)*100),3) -> 10 | K13: =SUMIFS('IN STORE SALES RECORD'!$E$6:$E$97,'IN STORE SALES RECORD'!$A$6:$A$97, "WEEK 1",'IN STORE SALES RECORD'!$D$6:$D$97,'WHS STK MGT & ALLOC.'!$A13)+10 -> 10 | L13: =ROUND(($M13/($H13-$K13))*100,3) -> 0 | M13: =SUMIFS('IN STORE SALES RECORD'!$E$6:$E$97,'IN STORE SALES RECORD'!$A$6:$A$97, "WEEK 6",'IN STORE SALES RECORD'!$D$6:$D$97,'WHS STK MGT & ALLOC.'!$A13) -> 0 | N13: =ROUND(($O13/($H13-($M13+$K13))*100),3) -> 0 | O13: =SUMIFS('IN STORE SALES RECORD'!$E$6:$E$97,'IN STORE SALES RECORD'!$A$6:$A$97, "WEEK 6",'IN STORE SALES RECORD'!$D$6:$D$97,'WHS STK MGT & ALLOC.'!$A13) -> 0 | P13: =ROUND(($Q13/($H13-($M13+$K13+$O13))*100),3) -> 0 | Q13: =SUMIFS('IN STORE SALES RECORD'!$E$6:$E$97,'IN STORE SALES RECORD'!$A$6:$A$97, "WEEK 6",'IN STORE SALES RECORD'!$D$6:$D$97,'WHS STK MGT & ALLOC.'!$A13) -> 0 | R13: =ROUND(($S13/($H13-($M13+$K13+$O13+$Q13))*100),3) -> 0 | S13: =SUMIFS('IN STORE SALES RECORD'!$E$6:$E$97,'IN STORE SALES RECORD'!$A$6:$A$97, "WEEK 6",'IN STORE SALES RECORD'!$D$6:$D$97,'WHS STK MGT & ALLOC.'!$A13) -> 0 | T13: =ROUND(($U13/($H13-($M13+$K13+$O13+$Q13+$S13))*100),3) -> 0 | U13: =SUMIFS('IN STORE SALES RECORD'!$E$6:$E$97,'IN STORE SALES RECORD'!$A$6:$A$97, "WEEK 6",'IN STORE SALES RECORD'!$D$6:$D$97,'WHS STK MGT & ALLOC.'!$A13) -> 0 | V13: =ROUND(($W13/($H13-($M13+$K13+$O13+$Q13+$S13+$U13))*100),3) -> 0 | W13: =SUMIFS('IN STORE SALES RECORD'!$E$6:$E$97,'IN STORE SALES RECORD'!$A$6:$A$97, "WEEK 6",'IN STORE SALES RECORD'!$D$6:$D$97,'WHS STK MGT & ALLOC.'!$A13) -> 0 | X13: =ROUND(($Y13/($H13-($M13+$K13+$O13+$Q13+$S13+$U13+$W13))*100),3) -> 0 | Y13: =SUMIFS('IN STORE SALES RECORD'!$E$6:$E$97,'IN STORE SALES RECORD'!$A$6:$A$97, "WEEK 6",'IN STORE SALES RECORD'!$D$6:$D$97,'WHS STK MGT & ALLOC.'!$A13) -> 0
A14: TO-JA-LI-NU-10 | B14: =IFERROR(INDEX('REFERENCING & DATABASE'!$E$7:$E$131,MATCH($A14,'REFERENCING & DATABASE'!$D$7:$D$131,0)),"") -> Lightweight Puffer Jacket | C14: =IFERROR(INDEX('REFERENCING & DATABASE'!$B$7:$B$131,MATCH($A14,'REFERENCING & DATABASE'!$D$7:$D$131,0)),"") -> TOPS | D14: =IFERROR(INDEX('REFERENCING & DATABASE'!$C$7:$C$131,MATCH($A14,'REFERENCING & DATABASE'!$D$7:$D$131,0)),"") -> JACKETS | E14: =IFERROR(INDEX('REFERENCING & DATABASE'!$F$7:$F$131,MATCH($A14,'REFERENCING & DATABASE'!$D$7:$D$131,0)),"") -> : A warm and packable jacket for all your adventures. | F14: =IFERROR(INDEX('REFERENCING & DATABASE'!$G$7:$G$131,MATCH($A14,'REFERENCING & DATABASE'!$D$7:$D$131,0)),"") -> Nude, Pink, Red | G14: =IFERROR(INDEX('REFERENCING & DATABASE'!$H$7:$H$131,MATCH($A14,'REFERENCING & DATABASE'!$D$7:$D$131,0)),"") -> 10 | H14: =IFERROR(INDEX('REFERENCING & DATABASE'!$A$7:$A$131,MATCH($A14,'REFERENCING & DATABASE'!$D$7:$D$131,0)),"") -> 150 | I14: =H14-SUM($K14,$M14,$O14,$Q14) -> 140 | J14: =ROUND((($K14/$H14)*100),3) -> 6.667 | K14: =SUMIFS('IN STORE SALES RECORD'!$E$6:$E$97,'IN STORE SALES RECORD'!$A$6:$A$97, "WEEK 1",'IN STORE SALES RECORD'!$D$6:$D$97,'WHS STK MGT & ALLOC.'!$A14)+10 -> 10 | L14: =ROUND(($M14/($H14-$K14))*100,3) -> 0 | M14: =SUMIFS('IN STORE SALES RECORD'!$E$6:$E$97,'IN STORE SALES RECORD'!$A$6:$A$97, "WEEK 6",'IN STORE SALES RECORD'!$D$6:$D$97,'WHS STK MGT & ALLOC.'!$A14) -> 0 | N14: =ROUND(($O14/($H14-($M14+$K14))*100),3) -> 0 | O14: =SUMIFS('IN STORE SALES RECORD'!$E$6:$E$97,'IN STORE SALES RECORD'!$A$6:$A$97, "WEEK 6",'IN STORE SALES RECORD'!$D$6:$D$97,'WHS STK MGT & ALLOC.'!$A14) -> 0 | P14: =ROUND(($Q14/($H14-($M14+$K14+$O14))*100),3) -> 0 | Q14: =SUMIFS('IN STORE SALES RECORD'!$E$6:$E$97,'IN STORE SALES RECORD'!$A$6:$A$97, "WEEK 6",'IN STORE SALES RECORD'!$D$6:$D$97,'WHS STK MGT & ALLOC.'!$A14) -> 0 | R14: =ROUND(($S14/($H14-($M14+$K14+$O14+$Q14))*100),3) -> 0 | S14: =SUMIFS('IN STORE SALES RECORD'!$E$6:$E$97,'IN STORE SALES RECORD'!$A$6:$A$97, "WEEK 6",'IN STORE SALES RECORD'!$D$6:$D$97,'WHS STK MGT & ALLOC.'!$A14) -> 0 | T14: =ROUND(($U14/($H14-($M14+$K14+$O14+$Q14+$S14))*100),3) -> 0 | U14: =SUMIFS('IN STORE SALES RECORD'!$E$6:$E$97,'IN STORE SALES RECORD'!$A$6:$A$97, "WEEK 6",'IN STORE SALES RECORD'!$D$6:$D$97,'WHS STK MGT & ALLOC.'!$A14) -> 0 | V14: =ROUND(($W14/($H14-($M14+$K14+$O14+$Q14+$S14+$U14))*100),3) -> 0 | W14: =SUMIFS('IN STORE SALES RECORD'!$E$6:$E$97,'IN STORE SALES RECORD'!$A$6:$A$97, "WEEK 6",'IN STORE SALES RECORD'!$D$6:$D$97,'WHS STK MGT & ALLOC.'!$A14) -> 0 | X14: =ROUND(($Y14/($H14-($M14+$K14+$O14+$Q14+$S14+$U14+$W14))*100),3) -> 0 | Y14: =SUMIFS('IN STORE SALES RECORD'!$E$6:$E$97,'IN STORE SALES RECORD'!$A$6:$A$97, "WEEK 6",'IN STORE SALES RECORD'!$D$6:$D$97,'WHS STK MGT & ALLOC.'!$A14) -> 0
A18: =A$6 -> REFERENCE | B18: =B$6 -> PRODUCT NAME | C18: =C$6 -> CATEGORY | D18: =D$6 -> SUB-CATEGORY | E18: =E$6 -> DESCRIPTION | F18: =F$6 -> COLOUR | G18: =G$6 -> SIZE | H18: =H$6 -> TOTAL STOCK | ... Q18: =Q$6 -> 4TH WEEK | R18: 5TH WEEK % ALLOCATION | S18: 5TH WEEK | T18: 6TH WEEK % ALLOCATION | U18: 6TH WEEK | V18: 7TH WEEK % ALLOCATION | W18: 7TH WEEK | X18: 8TH WEEK % ALLOCATION | Y18: 8TH WEEK
A19: BO-JE-CL-BL-10 | B19: =IFERROR(INDEX('REFERENCING & DATABASE'!$E$7:$E$131,MATCH($A19,'REFERENCING & DATABASE'!$D$7:$D$131,0)),"") -> Classic Straight Leg Jeans | C19: =IFERROR(INDEX('REFERENCING & DATABASE'!$B$7:$B$131,MATCH($A19,'REFERENCING & DATABASE'!$D$7:$D$131,0)),"") -> BOTTOMS | D19: =IFERROR(INDEX('REFERENCING & DATABASE'!$C$7:$C$131,MATCH($A19,'REFERENCING & DATABASE'!$D$7:$D$131,0)),"") -> JEANS | E19: =IFERROR(INDEX('REFERENCING & DATABASE'!$F$7:$F$131,MATCH($A19,'REFERENCING & DATABASE'!$D$7:$D$131,0)),"") -> A timeless and versatile style that flatters all body types. | F19: =IFERROR(INDEX('REFERENCING & DATABASE'!$G$7:$G$131,MATCH($A19,'REFERENCING & DATABASE'!$D$7:$D$131,0)),"") -> Blue,Black,Grey | G19: =IFERROR(INDEX('REFERENCING & DATABASE'!$H$7:$H$131,MATCH($A19,'REFERENCING & DATABASE'!$D$7:$D$131,0)),"") -> 10 | H19: =IFERROR(INDEX('REFERENCING & DATABASE'!$A$7:$A$131,MATCH($A19,'REFERENCING & DATABASE'!$D$7:$D$131,0)),"") -> 626 | I19: =H19-SUM($K19,$M19,$O19,$Q19) -> 616 | J19: =ROUND((($K19/$H19)*100),3) -> 1.597 | K19: =SUMIFS('IN STORE SALES RECORD'!$E$6:$E$97,'IN STORE SALES RECORD'!$A$6:$A$97, "WEEK 1",'IN STORE SALES RECORD'!$D$6:$D$97,'WHS STK MGT & ALLOC.'!$A19)+10 -> 10 | L19: =ROUND(($M19/($H19-$K19))*100,3) -> 0 | M19: =SUMIFS('IN STORE SALES RECORD'!$E$6:$E$97,'IN STORE SALES RECORD'!$A$6:$A$97, "WEEK 6",'IN STORE SALES RECORD'!$D$6:$D$97,'WHS STK MGT & ALLOC.'!$A19) -> 0 | N19: =ROUND(($O19/($H19-($M19+$K19))*100),3) -> 0 | O19: =SUMIFS('IN STORE SALES RECORD'!$E$6:$E$97,'IN STORE SALES RECORD'!$A$6:$A$97, "WEEK 6",'IN STORE SALES RECORD'!$D$6:$D$97,'WHS STK MGT & ALLOC.'!$A19) -> 0 | P19: =ROUND(($Q19/($H19-($M19+$K19+$O19))*100),3) -> 0 | Q19: =SUMIFS('IN STORE SALES RECORD'!$E$6:$E$97,'IN STORE SALES RECORD'!$A$6:$A$97, "WEEK 6",'IN STORE SALES RECORD'!$D$6:$D$97,'WHS STK MGT & ALLOC.'!$A19) -> 0 | R19: =ROUND(($S19/($H19-($M19+$K19+$O19+$Q19))*100),3) -> 0 | S19: =SUMIFS('IN STORE SALES RECORD'!$E$6:$E$97,'IN STORE SALES RECORD'!$A$6:$A$97, "WEEK 6",'IN STORE SALES RECORD'!$D$6:$D$97,'WHS STK MGT & ALLOC.'!$A19) -> 0 | T19: =ROUND(($U19/($H19-($M19+$K19+$O19+$Q19+$S19))*100),3) -> 0 | U19: =SUMIFS('IN STORE SALES RECORD'!$E$6:$E$97,'IN STORE SALES RECORD'!$A$6:$A$97, "WEEK 6",'IN STORE SALES RECORD'!$D$6:$D$97,'WHS STK MGT & ALLOC.'!$A19) -> 0 | V19: =ROUND(($W19/($H19-($M19+$K19+$O19+$Q19+$S19+$U19))*100),3) -> 0 | W19: =SUMIFS('IN STORE SALES RECORD'!$E$6:$E$97,'IN STORE SALES RECORD'!$A$6:$A$97, "WEEK 6",'IN STORE SALES RECORD'!$D$6:$D$97,'WHS STK MGT & ALLOC.'!$A19) -> 0 | X19: =ROUND(($Y19/($H19-($M19+$K19+$O19+$Q19+$S19+$U19+$W19))*100),3) -> 0 | Y19: =SUMIFS('IN STORE SALES RECORD'!$E$6:$E$97,'IN STORE SALES RECORD'!$A$6:$A$97, "WEEK 6",'IN STORE SALES RECORD'!$D$6:$D$97,'WHS STK MGT & ALLOC.'!$A19) -> 0
A20: BO-JE-SK-BL-10 | B20: =IFERROR(INDEX('REFERENCING & DATABASE'!$E$7:$E$131,MATCH($A20,'REFERENCING & DATABASE'!$D$7:$D$131,0)),"") -> Skinny Fit Jeans | C20: =IFERROR(INDEX('REFERENCING & DATABASE'!$B$7:$B$131,MATCH($A20,'REFERENCING & DATABASE'!$D$7:$D$131,0)),"") -> BOTTOMS | D20: =IFERROR(INDEX('REFERENCING & DATABASE'!$C$7:$C$131,MATCH($A20,'REFERENCING & DATABASE'!$D$7:$D$131,0)),"") -> JEANS | E20: =IFERROR(INDEX('REFERENCING & DATABASE'!$F$7:$F$131,MATCH($A20,'REFERENCING & DATABASE'!$D$7:$D$131,0)),"") -> A form-fitting silhouette that hugs your curves. | F20: =IFERROR(INDEX('REFERENCING & DATABASE'!$G$7:$G$131,MATCH($A20,'REFERENCING & DATABASE'!$D$7:$D$131,0)),"") -> Blue,Black,Grey | G20: =IFERROR(INDEX('REFERENCING & DATABASE'!$H$7:$H$131,MATCH($A20,'REFERENCING & DATABASE'!$D$7:$D$131,0)),"") -> 10 | H20: =IFERROR(INDEX('REFERENCING & DATABASE'!$A$7:$A$131,MATCH($A20,'REFERENCING & DATABASE'!$D$7:$D$131,0)),"") -> 207 | I20: =H20-SUM($K20,$M20,$O20,$Q20) -> 197 | J20: =ROUND((($K20/$H20)*100),3) -> 4.831 | K20: =SUMIFS('IN STORE SALES RECORD'!$E$6:$E$97,'IN STORE SALES RECORD'!$A$6:$A$97, "WEEK 1",'IN STORE SALES RECORD'!$D$6:$D$97,'WHS STK MGT & ALLOC.'!$A20)+10 -> 10 | L20: =ROUND(($M20/($H20-$K20))*100,3) -> 0 | M20: =SUMIFS('IN STORE SALES RECORD'!$E$6:$E$97,'IN STORE SALES RECORD'!$A$6:$A$97, "WEEK 6",'IN STORE SALES RECORD'!$D$6:$D$97,'WHS STK MGT & ALLOC.'!$A20) -> 0 | N20: =ROUND(($O20/($H20-($M20+$K20))*100),3) -> 0 | O20: =SUMIFS('IN STORE SALES RECORD'!$E$6:$E$97,'IN STORE SALES RECORD'!$A$6:$A$97, "WEEK 6",'IN STORE SALES RECORD'!$D$6:$D$97,'WHS STK MGT & ALLOC.'!$A20) -> 0 | P20: =ROUND(($Q20/($H20-($M20+$K20+$O20))*100),3) -> 0 | Q20: =SUMIFS('IN STORE SALES RECORD'!$E$6:$E$97,'IN STORE SALES RECORD'!$A$6:$A$97, "WEEK 6",'IN STORE SALES RECORD'!$D$6:$D$97,'WHS STK MGT & ALLOC.'!$A20) -> 0 | R20: =ROUND(($S20/($H20-($M20+$K20+$O20+$Q20))*100),3) -> 0 | S20: =SUMIFS('IN STORE SALES RECORD'!$E$6:$E$97,'IN STORE SALES RECORD'!$A$6:$A$97, "WEEK 6",'IN STORE SALES RECORD'!$D$6:$D$97,'WHS STK MGT & ALLOC.'!$A20) -> 0 | T20: =ROUND(($U20/($H20-($M20+$K20+$O20+$Q20+$S20))*100),3) -> 0 | U20: =SUMIFS('IN STORE SALES RECORD'!$E$6:$E$97,'IN STORE SALES RECORD'!$A$6:$A$97, "WEEK 6",'IN STORE SALES RECORD'!$D$6:$D$97,'WHS STK MGT & ALLOC.'!$A20) -> 0 | V20: =ROUND(($W20/($H20-($M20+$K20+$O20+$Q20+$S20+$U20))*100),3) -> 0 | W20: =SUMIFS('IN STORE SALES RECORD'!$E$6:$E$97,'IN STORE SALES RECORD'!$A$6:$A$97, "WEEK 6",'IN STORE SALES RECORD'!$D$6:$D$97,'WHS STK MGT & ALLOC.'!$A20) -> 0 | X20: =ROUND(($Y20/($H20-($M20+$K20+$O20+$Q20+$S20+$U20+$W20))*100),3) -> 0 | Y20: =SUMIFS('IN STORE SALES RECORD'!$E$6:$E$97,'IN STORE SALES RECORD'!$A$6:$A$97, "WEEK 6",'IN STORE SALES RECORD'!$D$6:$D$97,'WHS STK MGT & ALLOC.'!$A20) -> 0
A21: BO-JE-BO-BL-10 | B21: =IFERROR(INDEX('REFERENCING & DATABASE'!$E$7:$E$131,MATCH($A21,'REFERENCING & DATABASE'!$D$7:$D$131,0)),"") -> Bootcut Jeans | C21: =IFERROR(INDEX('REFERENCING & DATABASE'!$B$7:$B$131,MATCH($A21,'REFERENCING & DATABASE'!$D$7:$D$131,0)),"") -> BOTTOMS | D21: =IFERROR(INDEX('REFERENCING & DATABASE'!$C$7:$C$131,MATCH($A21,'REFERENCING & DATABASE'!$D$7:$D$131,0)),"") -> JEANS | E21: =IFERROR(INDEX('REFERENCING & DATABASE'!$F$7:$F$131,MATCH($A21,'REFERENCING & DATABASE'!$D$7:$D$131,0)),"") -> A flattering style that flares slightly at the ankle. | F21: =IFERROR(INDEX('REFERENCING & DATABASE'!$G$7:$G$131,MATCH($A21,'REFERENCING & DATABASE'!$D$7:$D$131,0)),"") -> Blue,Black,Grey | G21: =IFERROR(INDEX('REFERENCING & DATABASE'!$H$7:$H$131,MATCH($A21,'REFERENCING & DATABASE'!$D$7:$D$131,0)),"") -> 10 | H21: =IFERROR(INDEX('REFERENCING & DATABASE'!$A$7:$A$131,MATCH($A21,'REFERENCING & DATABASE'!$D$7:$D$131,0)),"") -> 644 | I21: =H21-SUM($K21,$M21,$O21,$Q21) -> 634 | J21: =ROUND((($K21/$H21)*100),3) -> 1.553 | K21: =SUMIFS('IN STORE SALES RECORD'!$E$6:$E$97,'IN STORE SALES RECORD'!$A$6:$A$97, "WEEK 1",'IN STORE SALES RECORD'!$D$6:$D$97,'WHS STK MGT & ALLOC.'!$A21)+10 -> 10 | L21: =ROUND(($M21/($H21-$K21))*100,3) -> 0 | M21: =SUMIFS('IN STORE SALES RECORD'!$E$6:$E$97,'IN STORE SALES RECORD'!$A$6:$A$97, "WEEK 6",'IN STORE SALES RECORD'!$D$6:$D$97,'WHS STK MGT & ALLOC.'!$A21) -> 0 | N21: =ROUND(($O21/($H21-($M21+$K21))*100),3) -> 0 | O21: =SUMIFS('IN STORE SALES RECORD'!$E$6:$E$97,'IN STORE SALES RECORD'!$A$6:$A$97, "WEEK 6",'IN STORE SALES RECORD'!$D$6:$D$97,'WHS STK MGT & ALLOC.'!$A21) -> 0 | P21: =ROUND(($Q21/($H21-($M21+$K21+$O21))*100),3) -> 0 | Q21: =SUMIFS('IN STORE SALES RECORD'!$E$6:$E$97,'IN STORE SALES RECORD'!$A$6:$A$97, "WEEK 6",'IN STORE SALES RECORD'!$D$6:$D$97,'WHS STK MGT & ALLOC.'!$A21) -> 0 | R21: =ROUND(($S21/($H21-($M21+$K21+$O21+$Q21))*100),3) -> 0 | S21: =SUMIFS('IN STORE SALES RECORD'!$E$6:$E$97,'IN STORE SALES RECORD'!$A$6:$A$97, "WEEK 6",'IN STORE SALES RECORD'!$D$6:$D$97,'WHS STK MGT & ALLOC.'!$A21) -> 0 | T21: =ROUND(($U21/($H21-($M21+$K21+$O21+$Q21+$S21))*100),3) -> 0 | U21: =SUMIFS('IN STORE SALES RECORD'!$E$6:$E$97,'IN STORE SALES RECORD'!$A$6:$A$97, "WEEK 6",'IN STORE SALES RECORD'!$D$6:$D$97,'WHS STK MGT & ALLOC.'!$A21) -> 0 | V21: =ROUND(($W21/($H21-($M21+$K21+$O21+$Q21+$S21+$U21))*100),3) -> 0 | W21: =SUMIFS('IN STORE SALES RECORD'!$E$6:$E$97,'IN STORE SALES RECORD'!$A$6:$A$97, "WEEK 6",'IN STORE SALES RECORD'!$D$6:$D$97,'WHS STK MGT & ALLOC.'!$A21) -> 0 | X21: =ROUND(($Y21/($H21-($M21+$K21+$O21+$Q21+$S21+$U21+$W21))*100),3) -> 0 | Y21: =SUMIFS('IN STORE SALES RECORD'!$E$6:$E$97,'IN STORE SALES RECORD'!$A$6:$A$97, "WEEK 6",'IN STORE SALES RECORD'!$D$6:$D$97,'WHS STK MGT & ALLOC.'!$A21) -> 0
A22: BO-JE-HI-BL-10 | B22: =IFERROR(INDEX('REFERENCING & DATABASE'!$E$7:$E$131,MATCH($A22,'REFERENCING & DATABASE'!$D$7:$D$131,0)),"") -> High-Waisted Jeans | C22: =IFERROR(INDEX('REFERENCING & DATABASE'!$B$7:$B$131,MATCH($A22,'REFERENCING & DATABASE'!$D$7:$D$131,0)),"") -> BOTTOMS | D22: =IFERROR(INDEX('REFERENCING & DATABASE'!$C$7:$C$131,MATCH($A22,'REFERENCING & DATABASE'!$D$7:$D$131,0)),"") -> JEANS | E22: =IFERROR(INDEX('REFERENCING & DATABASE'!$F$7:$F$131,MATCH($A22,'REFERENCING & DATABASE'!$D$7:$D$131,0)),"") -> A high-rise silhouette that elongates your legs and flatters your figure. | F22: =IFERROR(INDEX('REFERENCING & DATABASE'!$G$7:$G$131,MATCH($A22,'REFERENCING & DATABASE'!$D$7:$D$131,0)),"") -> Blue,Black,Grey | G22: =IFERROR(INDEX('REFERENCING & DATABASE'!$H$7:$H$131,MATCH($A22,'REFERENCING & DATABASE'!$D$7:$D$131,0)),"") -> 10 | H22: =IFERROR(INDEX('REFERENCING & DATABASE'!$A$7:$A$131,MATCH($A22,'REFERENCING & DATABASE'!$D$7:$D$131,0)),"") -> 585 | I22: =H22-SUM($K22,$M22,$O22,$Q22) -> 485 | J22: =ROUND((($K22/$H22)*100),3) -> 17.094 | K22: =SUMIFS('IN STORE SALES RECORD'!$E$6:$E$97,'IN STORE SALES RECORD'!$A$6:$A$97, "WEEK 1",'IN STORE SALES RECORD'!$D$6:$D$97,'WHS STK MGT & ALLOC.'!$A22)+10 -> 100 | L22: =ROUND(($M22/($H22-$K22))*100,3) -> 0 | M22: =SUMIFS('IN STORE SALES RECORD'!$E$6:$E$97,'IN STORE SALES RECORD'!$A$6:$A$97, "WEEK 6",'IN STORE SALES RECORD'!$D$6:$D$97,'WHS STK MGT & ALLOC.'!$A22) -> 0 | N22: =ROUND(($O22/($H22-($M22+$K22))*100),3) -> 0 | O22: =SUMIFS('IN STORE SALES RECORD'!$E$6:$E$97,'IN STORE SALES RECORD'!$A$6:$A$97, "WEEK 6",'IN STORE SALES RECORD'!$D$6:$D$97,'WHS STK MGT & ALLOC.'!$A22) -> 0 | P22: =ROUND(($Q22/($H22-($M22+$K22+$O22))*100),3) -> 0 | Q22: =SUMIFS('IN STORE SALES RECORD'!$E$6:$E$97,'IN STORE SALES RECORD'!$A$6:$A$97, "WEEK 6",'IN STORE SALES RECORD'!$D$6:$D$97,'WHS STK MGT & ALLOC.'!$A22) -> 0 | R22: =ROUND(($S22/($H22-($M22+$K22+$O22+$Q22))*100),3) -> 0 | S22: =SUMIFS('IN STORE SALES RECORD'!$E$6:$E$97,'IN STORE SALES RECORD'!$A$6:$A$97, "WEEK 6",'IN STORE SALES RECORD'!$D$6:$D$97,'WHS STK MGT & ALLOC.'!$A22) -> 0 | T22: =ROUND(($U22/($H22-($M22+$K22+$O22+$Q22+$S22))*100),3) -> 0 | U22: =SUMIFS('IN STORE SALES RECORD'!$E$6:$E$97,'IN STORE SALES RECORD'!$A$6:$A$97, "WEEK 6",'IN STORE SALES RECORD'!$D$6:$D$97,'WHS STK MGT & ALLOC.'!$A22) -> 0 | V22: =ROUND(($W22/($H22-($M22+$K22+$O22+$Q22+$S22+$U22))*100),3) -> 0 | W22: =SUMIFS('IN STORE SALES RECORD'!$E$6:$E$97,'IN STORE SALES RECORD'!$A$6:$A$97, "WEEK 6",'IN STORE SALES RECORD'!$D$6:$D$97,'WHS STK MGT & ALLOC.'!$A22) -> 0 | X22: =ROUND(($Y22/($H22-($M22+$K22+$O22+$Q22+$S22+$U22+$W22))*100),3) -> 0 | Y22: =SUMIFS('IN STORE SALES RECORD'!$E$6:$E$97,'IN STORE SALES RECORD'!$A$6:$A$97, "WEEK 6",'IN STORE SALES RECORD'!$D$6:$D$97,'WHS STK MGT & ALLOC.'!$A22) -> 0
A23: BO-PA-KH-BR-10 | B23: =IFERROR(INDEX('REFERENCING & DATABASE'!$E$7:$E$131,MATCH($A23,'REFERENCING & DATABASE'!$D$7:$D$131,0)),"") -> Khaki Chinos | C23: =IFERROR(INDEX('REFERENCING & DATABASE'!$B$7:$B$131,MATCH($A23,'REFERENCING & DATABASE'!$D$7:$D$131,0)),"") -> BOTTOMS | D23: =IFERROR(INDEX('REFERENCING & DATABASE'!$C$7:$C$131,MATCH($A23,'REFERENCING & DATABASE'!$D$7:$D$131,0)),"") -> PANTS | E23: =IFERROR(INDEX('REFERENCING & DATABASE'!$F$7:$F$131,MATCH($A23,'REFERENCING & DATABASE'!$D$7:$D$131,0)),"") -> A versatile and comfortable option for work or casual wear. | F23: =IFERROR(INDEX('REFERENCING & DATABASE'!$G$7:$G$131,MATCH($A23,'REFERENCING & DATABASE'!$D$7:$D$131,0)),"") -> Brown,Black | G23: =IFERROR(INDEX('REFERENCING & DATABASE'!$H$7:$H$131,MATCH($A23,'REFERENCING & DATABASE'!$D$7:$D$131,0)),"") -> 10 | H23: =IFERROR(INDEX('REFERENCING & DATABASE'!$A$7:$A$131,MATCH($A23,'REFERENCING & DATABASE'!$D$7:$D$131,0)),"") -> 597 | I23: =H23-SUM($K23,$M23,$O23,$Q23) -> 587 | J23: =ROUND((($K23/$H23)*100),3) -> 1.675 | K23: =SUMIFS('IN STORE SALES RECORD'!$E$6:$E$97,'IN STORE SALES RECORD'!$A$6:$A$97, "WEEK 1",'IN STORE SALES RECORD'!$D$6:$D$97,'WHS STK MGT & ALLOC.'!$A23)+10 -> 10 | L23: =ROUND(($M23/($H23-$K23))*100,3) -> 0 | M23: =SUMIFS('IN STORE SALES RECORD'!$E$6:$E$97,'IN STORE SALES RECORD'!$A$6:$A$97, "WEEK 6",'IN STORE SALES RECORD'!$D$6:$D$97,'WHS STK MGT & ALLOC.'!$A23) -> 0 | N23: =ROUND(($O23/($H23-($M23+$K23))*100),3) -> 0 | O23: =SUMIFS('IN STORE SALES RECORD'!$E$6:$E$97,'IN STORE SALES RECORD'!$A$6:$A$97, "WEEK 6",'IN STORE SALES RECORD'!$D$6:$D$97,'WHS STK MGT & ALLOC.'!$A23) -> 0 | P23: =ROUND(($Q23/($H23-($M23+$K23+$O23))*100),3) -> 0 | Q23: =SUMIFS('IN STORE SALES RECORD'!$E$6:$E$97,'IN STORE SALES RECORD'!$A$6:$A$97, "WEEK 6",'IN STORE SALES RECORD'!$D$6:$D$97,'WHS STK MGT & ALLOC.'!$A23) -> 0 | R23: =ROUND(($S23/($H23-($M23+$K23+$O23+$Q23))*100),3) -> 0 | S23: =SUMIFS('IN STORE SALES RECORD'!$E$6:$E$97,'IN STORE SALES RECORD'!$A$6:$A$97, "WEEK 6",'IN STORE SALES RECORD'!$D$6:$D$97,'WHS STK MGT & ALLOC.'!$A23) -> 0 | T23: =ROUND(($U23/($H23-($M23+$K23+$O23+$Q23+$S23))*100),3) -> 0 | U23: =SUMIFS('IN STORE SALES RECORD'!$E$6:$E$97,'IN STORE SALES RECORD'!$A$6:$A$97, "WEEK 6",'IN STORE SALES RECORD'!$D$6:$D$97,'WHS STK MGT & ALLOC.'!$A23) -> 0 | V23: =ROUND(($W23/($H23-($M23+$K23+$O23+$Q23+$S23+$U23))*100),3) -> 0 | W23: =SUMIFS('IN STORE SALES RECORD'!$E$6:$E$97,'IN STORE SALES RECORD'!$A$6:$A$97, "WEEK 6",'IN STORE SALES RECORD'!$D$6:$D$97,'WHS STK MGT & ALLOC.'!$A23) -> 0 | X23: =ROUND(($Y23/($H23-($M23+$K23+$O23+$Q23+$S23+$U23+$W23))*100),3) -> 0 | Y23: =SUMIFS('IN STORE SALES RECORD'!$E$6:$E$97,'IN STORE SALES RECORD'!$A$6:$A$97, "WEEK 6",'IN STORE SALES RECORD'!$D$6:$D$97,'WHS STK MGT & ALLOC.'!$A23) -> 0
A24: BO-PA-SL-GR-10 | B24: =IFERROR(INDEX('REFERENCING & DATABASE'!$E$7:$E$131,MATCH($A24,'REFERENCING & DATABASE'!$D$7:$D$131,0)),"") -> Slim-Fit Dress Pants | C24: =IFERROR(INDEX('REFERENCING & DATABASE'!$B$7:$B$131,MATCH($A24,'REFERENCING & DATABASE'!$D$7:$D$131,0)),"") -> BOTTOMS | D24: =IFERROR(INDEX('REFERENCING & DATABASE'!$C$7:$C$131,MATCH($A24,'REFERENCING & DATABASE'!$D$7:$D$131,0)),"") -> PANTS | E24: =IFERROR(INDEX('REFERENCING & DATABASE'!$F$7:$F$131,MATCH($A24,'REFERENCING & DATABASE'!$D$7:$D$131,0)),"") -> A polished and professional style for work or special occasions. | F24: =IFERROR(INDEX('REFERENCING & DATABASE'!$G$7:$G$131,MATCH($A24,'REFERENCING & DATABASE'!$D$7:$D$131,0)),"") -> green, yellow and lavender | G24: =IFERROR(INDEX('REFERENCING & DATABASE'!$H$7:$H$131,MATCH($A24,'REFERENCING & DATABASE'!$D$7:$D$131,0)),"") -> 10 | H24: =IFERROR(INDEX('REFERENCING & DATABASE'!$A$7:$A$131,MATCH($A24,'REFERENCING & DATABASE'!$D$7:$D$131,0)),"") -> 638 | I24: =H24-SUM($K24,$M24,$O24,$Q24) -> 628 | J24: =ROUND((($K24/$H24)*100),3) -> 1.567 | K24: =SUMIFS('IN STORE SALES RECORD'!$E$6:$E$97,'IN STORE SALES RECORD'!$A$6:$A$97, "WEEK 1",'IN STORE SALES RECORD'!$D$6:$D$97,'WHS STK MGT & ALLOC.'!$A24)+10 -> 10 | L24: =ROUND(($M24/($H24-$K24))*100,3) -> 0 | M24: =SUMIFS('IN STORE SALES RECORD'!$E$6:$E$97,'IN STORE SALES RECORD'!$A$6:$A$97, "WEEK 6",'IN STORE SALES RECORD'!$D$6:$D$97,'WHS STK MGT & ALLOC.'!$A24) -> 0 | N24: =ROUND(($O24/($H24-($M24+$K24))*100),3) -> 0 | O24: =SUMIFS('IN STORE SALES RECORD'!$E$6:$E$97,'IN STORE SALES RECORD'!$A$6:$A$97, "WEEK 6",'IN STORE SALES RECORD'!$D$6:$D$97,'WHS STK MGT & ALLOC.'!$A24) -> 0 | P24: =ROUND(($Q24/($H24-($M24+$K24+$O24))*100),3) -> 0 | Q24: =SUMIFS('IN STORE SALES RECORD'!$E$6:$E$97,'IN STORE SALES RECORD'!$A$6:$A$97, "WEEK 6",'IN STORE SALES RECORD'!$D$6:$D$97,'WHS STK MGT & ALLOC.'!$A24) -> 0 | R24: =ROUND(($S24/($H24-($M24+$K24+$O24+$Q24))*100),3) -> 0 | S24: =SUMIFS('IN STORE SALES RECORD'!$E$6:$E$97,'IN STORE SALES RECORD'!$A$6:$A$97, "WEEK 6",'IN STORE SALES RECORD'!$D$6:$D$97,'WHS STK MGT & ALLOC.'!$A24) -> 0 | T24: =ROUND(($U24/($H24-($M24+$K24+$O24+$Q24+$S24))*100),3) -> 0 | U24: =SUMIFS('IN STORE SALES RECORD'!$E$6:$E$97,'IN STORE SALES RECORD'!$A$6:$A$97, "WEEK 6",'IN STORE SALES RECORD'!$D$6:$D$97,'WHS STK MGT & ALLOC.'!$A24) -> 0 | V24: =ROUND(($W24/($H24-($M24+$K24+$O24+$Q24+$S24+$U24))*100),3) -> 0 | W24: =SUMIFS('IN STORE SALES RECORD'!$E$6:$E$97,'IN STORE SALES RECORD'!$A$6:$A$97, "WEEK 6",'IN STORE SALES RECORD'!$D$6:$D$97,'WHS STK MGT & ALLOC.'!$A24) -> 0 | X24: =ROUND(($Y24/($H24-($M24+$K24+$O24+$Q24+$S24+$U24+$W24))*100),3) -> 0 | Y24: =SUMIFS('IN STORE SALES RECORD'!$E$6:$E$97,'IN STORE SALES RECORD'!$A$6:$A$97, "WEEK 6",'IN STORE SALES RECORD'!$D$6:$D$97,'WHS STK MGT & ALLOC.'!$A24) -> 0
A25: BO-PA-UT-BL-10 | B25: =IFERROR(INDEX('REFERENCING & DATABASE'!$E$7:$E$131,MATCH($A25,'REFERENCING & DATABASE'!$D$7:$D$131,0)),"") -> Utility Cargo Pants | C25: =IFERROR(INDEX('REFERENCING & DATABASE'!$B$7:$B$131,MATCH($A25,'REFERENCING & DATABASE'!$D$7:$D$131,0)),"") -> BOTTOMS | D25: =IFERROR(INDEX('REFERENCING & DATABASE'!$C$7:$C$131,MATCH($A25,'REFERENCING & DATABASE'!$D$7:$D$131,0)),"") -> PANTS | E25: =IFERROR(INDEX('REFERENCING & DATABASE'!$F$7:$F$131,MATCH($A25,'REFERENCING & DATABASE'!$D$7:$D$131,0)),"") -> A functional and stylish option with multiple pockets. | F25: =IFERROR(INDEX('REFERENCING & DATABASE'!$G$7:$G$131,MATCH($A25,'REFERENCING & DATABASE'!$D$7:$D$131,0)),"") -> Blue,Black,Grey | G25: =IFERROR(INDEX('REFERENCING & DATABASE'!$H$7:$H$131,MATCH($A25,'REFERENCING & DATABASE'!$D$7:$D$131,0)),"") -> 10 | H25: =IFERROR(INDEX('REFERENCING & DATABASE'!$A$7:$A$131,MATCH($A25,'REFERENCING & DATABASE'!$D$7:$D$131,0)),"") -> 717 | I25: =H25-SUM($K25,$M25,$O25,$Q25) -> 707 | J25: =ROUND((($K25/$H25)*100),3) -> 1.395 | K25: =SUMIFS('IN STORE SALES RECORD'!$E$6:$E$97,'IN STORE SALES RECORD'!$A$6:$A$97, "WEEK 1",'IN STORE SALES RECORD'!$D$6:$D$97,'WHS STK MGT & ALLOC.'!$A25)+10 -> 10 | L25: =ROUND(($M25/($H25-$K25))*100,3) -> 0 | M25: =SUMIFS('IN STORE SALES RECORD'!$E$6:$E$97,'IN STORE SALES RECORD'!$A$6:$A$97, "WEEK 6",'IN STORE SALES RECORD'!$D$6:$D$97,'WHS STK MGT & ALLOC.'!$A25) -> 0 | N25: =ROUND(($O25/($H25-($M25+$K25))*100),3) -> 0 | O25: =SUMIFS('IN STORE SALES RECORD'!$E$6:$E$97,'IN STORE SALES RECORD'!$A$6:$A$97, "WEEK 6",'IN STORE SALES RECORD'!$D$6:$D$97,'WHS STK MGT & ALLOC.'!$A25) -> 0 | P25: =ROUND(($Q25/($H25-($M25+$K25+$O25))*100),3) -> 0 | Q25: =SUMIFS('IN STORE SALES RECORD'!$E$6:$E$97,'IN STORE SALES RECORD'!$A$6:$A$97, "WEEK 6",'IN STORE SALES RECORD'!$D$6:$D$97,'WHS STK MGT & ALLOC.'!$A25) -> 0 | R25: =ROUND(($S25/($H25-($M25+$K25+$O25+$Q25))*100),3) -> 0 | S25: =SUMIFS('IN STORE SALES RECORD'!$E$6:$E$97,'IN STORE SALES RECORD'!$A$6:$A$97, "WEEK 6",'IN STORE SALES RECORD'!$D$6:$D$97,'WHS STK MGT & ALLOC.'!$A25) -> 0 | T25: =ROUND(($U25/($H25-($M25+$K25+$O25+$Q25+$S25))*100),3) -> 0 | U25: =SUMIFS('IN STORE SALES RECORD'!$E$6:$E$97,'IN STORE SALES RECORD'!$A$6:$A$97, "WEEK 6",'IN STORE SALES RECORD'!$D$6:$D$97,'WHS STK MGT & ALLOC.'!$A25) -> 0 | V25: =ROUND(($W25/($H25-($M25+$K25+$O25+$Q25+$S25+$U25))*100),3) -> 0 | W25: =SUMIFS('IN STORE SALES RECORD'!$E$6:$E$97,'IN STORE SALES RECORD'!$A$6:$A$97, "WEEK 6",'IN STORE SALES RECORD'!$D$6:$D$97,'WHS STK MGT & ALLOC.'!$A25) -> 0 | X25: =ROUND(($Y25/($H25-($M25+$K25+$O25+$Q25+$S25+$U25+$W25))*100),3) -> 0 | Y25: =SUMIFS('IN STORE SALES RECORD'!$E$6:$E$97,'IN STORE SALES RECORD'!$A$6:$A$97, "WEEK 6",'IN STORE SALES RECORD'!$D$6:$D$97,'WHS STK MGT & ALLOC.'!$A25) -> 0
A26: BO-PA-CO-GR-10 | B26: =IFERROR(INDEX('REFERENCING & DATABASE'!$E$7:$E$131,MATCH($A26,'REFERENCING & DATABASE'!$D$7:$D$131,0)),"") -> Cozy Joggers | C26: =IFERROR(INDEX('REFERENCING & DATABASE'!$B$7:$B$131,MATCH($A26,'REFERENCING & DATABASE'!$D$7:$D$131,0)),"") -> BOTTOMS | D26: =IFERROR(INDEX('REFERENCING & DATABASE'!$C$7:$C$131,MATCH($A26,'REFERENCING & DATABASE'!$D$7:$D$131,0)),"") -> PANTS | E26: =IFERROR(INDEX('REFERENCING & DATABASE'!$F$7:$F$131,MATCH($A26,'REFERENCING & DATABASE'!$D$7:$D$131,0)),"") -> A comfortable and relaxed-fit style for lounging or exercising. | F26: =IFERROR(INDEX('REFERENCING & DATABASE'!$G$7:$G$131,MATCH($A26,'REFERENCING & DATABASE'!$D$7:$D$131,0)),"") -> Grey | G26: =IFERROR(INDEX('REFERENCING & DATABASE'!$H$7:$H$131,MATCH($A26,'REFERENCING & DATABASE'!$D$7:$D$131,0)),"") -> 10 | H26: =IFERROR(INDEX('REFERENCING & DATABASE'!$A$7:$A$131,MATCH($A26,'REFERENCING & DATABASE'!$D$7:$D$131,0)),"") -> 755 | I26: =H26-SUM($K26,$M26,$O26,$Q26) -> 745 | J26: =ROUND((($K26/$H26)*100),3) -> 1.325 | K26: =SUMIFS('IN STORE SALES RECORD'!$E$6:$E$97,'IN STORE SALES RECORD'!$A$6:$A$97, "WEEK 1",'IN STORE SALES RECORD'!$D$6:$D$97,'WHS STK MGT & ALLOC.'!$A26)+10 -> 10 | L26: =ROUND(($M26/($H26-$K26))*100,3) -> 0 | M26: =SUMIFS('IN STORE SALES RECORD'!$E$6:$E$97,'IN STORE SALES RECORD'!$A$6:$A$97, "WEEK 6",'IN STORE SALES RECORD'!$D$6:$D$97,'WHS STK MGT & ALLOC.'!$A26) -> 0 | N26: =ROUND(($O26/($H26-($M26+$K26))*100),3) -> 0 | O26: =SUMIFS('IN STORE SALES RECORD'!$E$6:$E$97,'IN STORE SALES RECORD'!$A$6:$A$97, "WEEK 6",'IN STORE SALES RECORD'!$D$6:$D$97,'WHS STK MGT & ALLOC.'!$A26) -> 0 | P26: =ROUND(($Q26/($H26-($M26+$K26+$O26))*100),3) -> 0 | Q26: =SUMIFS('IN STORE SALES RECORD'!$E$6:$E$97,'IN STORE SALES RECORD'!$A$6:$A$97, "WEEK 6",'IN STORE SALES RECORD'!$D$6:$D$97,'WHS STK MGT & ALLOC.'!$A26) -> 0 | R26: =ROUND(($S26/($H26-($M26+$K26+$O26+$Q26))*100),3) -> 0 | S26: =SUMIFS('IN STORE SALES RECORD'!$E$6:$E$97,'IN STORE SALES RECORD'!$A$6:$A$97, "WEEK 6",'IN STORE SALES RECORD'!$D$6:$D$97,'WHS STK MGT & ALLOC.'!$A26) -> 0 | T26: =ROUND(($U26/($H26-($M26+$K26+$O26+$Q26+$S26))*100),3) -> 0 | U26: =SUMIFS('IN STORE SALES RECORD'!$E$6:$E$97,'IN STORE SALES RECORD'!$A$6:$A$97, "WEEK 6",'IN STORE SALES RECORD'!$D$6:$D$97,'WHS STK MGT & ALLOC.'!$A26) -> 0 | V26: =ROUND(($W26/($H26-($M26+$K26+$O26+$Q26+$S26+$U26))*100),3) -> 0 | W26: =SUMIFS('IN STORE SALES RECORD'!$E$6:$E$97,'IN STORE SALES RECORD'!$A$6:$A$97, "WEEK 6",'IN STORE SALES RECORD'!$D$6:$D$97,'WHS STK MGT & ALLOC.'!$A26) -> 0 | X26: =ROUND(($Y26/($H26-($M26+$K26+$O26+$Q26+$S26+$U26+$W26))*100),3) -> 0 | Y26: =SUMIFS('IN STORE SALES RECORD'!$E$6:$E$97,'IN STORE SALES RECORD'!$A$6:$A$97, "WEEK 6",'IN STORE SALES RECORD'!$D$6:$D$97,'WHS STK MGT & ALLOC.'!$A26) -> 0
A27: BO-PA-TE-MU-10 | B27: =IFERROR(INDEX('REFERENCING & DATABASE'!$E$7:$E$131,MATCH($A27,'REFERENCING & DATABASE'!$D$7:$D$131,0)),"") -> Tech Fleece Track Pants | C27: =IFERROR(INDEX('REFERENCING & DATABASE'!$B$7:$B$131,MATCH($A27,'REFERENCING & DATABASE'!$D$7:$D$131,0)),"") -> BOTTOMS | D27: =IFERROR(INDEX('REFERENCING & DATABASE'!$C$7:$C$131,MATCH($A27,'REFERENCING & DATABASE'!$D$7:$D$131,0)),"") -> PANTS | E27: =IFERROR(INDEX('REFERENCING & DATABASE'!$F$7:$F$131,MATCH($A27,'REFERENCING & DATABASE'!$D$7:$D$131,0)),"") -> Breathable and moisture-wicking pants for athletic activities or everyday wear. | F27: =IFERROR(INDEX('REFERENCING & DATABASE'!$G$7:$G$131,MATCH($A27,'REFERENCING & DATABASE'!$D$7:$D$131,0)),"") -> Multi-colors | G27: =IFERROR(INDEX('REFERENCING & DATABASE'!$H$7:$H$131,MATCH($A27,'REFERENCING & DATABASE'!$D$7:$D$131,0)),"") -> 10 | H27: =IFERROR(INDEX('REFERENCING & DATABASE'!$A$7:$A$131,MATCH($A27,'REFERENCING & DATABASE'!$D$7:$D$131,0)),"") -> 499 | I27: =H27-SUM($K27,$M27,$O27,$Q27) -> 489 | J27: =ROUND((($K27/$H27)*100),3) -> 2.004 | K27: =SUMIFS('IN STORE SALES RECORD'!$E$6:$E$97,'IN STORE SALES RECORD'!$A$6:$A$97, "WEEK 1",'IN STORE SALES RECORD'!$D$6:$D$97,'WHS STK MGT & ALLOC.'!$A27)+10 -> 10 | L27: =ROUND(($M27/($H27-$K27))*100,3) -> 0 | M27: =SUMIFS('IN STORE SALES RECORD'!$E$6:$E$97,'IN STORE SALES RECORD'!$A$6:$A$97, "WEEK 6",'IN STORE SALES RECORD'!$D$6:$D$97,'WHS STK MGT & ALLOC.'!$A27) -> 0 | N27: =ROUND(($O27/($H27-($M27+$K27))*100),3) -> 0 | O27: =SUMIFS('IN STORE SALES RECORD'!$E$6:$E$97,'IN STORE SALES RECORD'!$A$6:$A$97, "WEEK 6",'IN STORE SALES RECORD'!$D$6:$D$97,'WHS STK MGT & ALLOC.'!$A27) -> 0 | P27: =ROUND(($Q27/($H27-($M27+$K27+$O27))*100),3) -> 0 | Q27: =SUMIFS('IN STORE SALES RECORD'!$E$6:$E$97,'IN STORE SALES RECORD'!$A$6:$A$97, "WEEK 6",'IN STORE SALES RECORD'!$D$6:$D$97,'WHS STK MGT & ALLOC.'!$A27) -> 0 | R27: =ROUND(($S27/($H27-($M27+$K27+$O27+$Q27))*100),3) -> 0 | S27: =SUMIFS('IN STORE SALES RECORD'!$E$6:$E$97,'IN STORE SALES RECORD'!$A$6:$A$97, "WEEK 6",'IN STORE SALES RECORD'!$D$6:$D$97,'WHS STK MGT & ALLOC.'!$A27) -> 0 | T27: =ROUND(($U27/($H27-($M27+$K27+$O27+$Q27+$S27))*100),3) -> 0 | U27: =SUMIFS('IN STORE SALES RECORD'!$E$6:$E$97,'IN STORE SALES RECORD'!$A$6:$A$97, "WEEK 6",'IN STORE SALES RECORD'!$D$6:$D$97,'WHS STK MGT & ALLOC.'!$A27) -> 0 | V27: =ROUND(($W27/($H27-($M27+$K27+$O27+$Q27+$S27+$U27))*100),3) -> 0 | W27: =SUMIFS('IN STORE SALES RECORD'!$E$6:$E$97,'IN STORE SALES RECORD'!$A$6:$A$97, "WEEK 6",'IN STORE SALES RECORD'!$D$6:$D$97,'WHS STK MGT & ALLOC.'!$A27) -> 0 | X27: =ROUND(($Y27/($H27-($M27+$K27+$O27+$Q27+$S27+$U27+$W27))*100),3) -> 0 | Y27: =SUMIFS('IN STORE SALES RECORD'!$E$6:$E$97,'IN STORE SALES RECORD'!$A$6:$A$97, "WEEK 6",'IN STORE SALES RECORD'!$D$6:$D$97,'WHS STK MGT & ALLOC.'!$A27) -> 0
A28: BO-SH-DI-LI-30 | B28: =IFERROR(INDEX('REFERENCING & DATABASE'!$E$7:$E$131,MATCH($A28,'REFERENCING & DATABASE'!$D$7:$D$131,0)),"") -> Distressed Denim Shorts | C28: =IFERROR(INDEX('REFERENCING & DATABASE'!$B$7:$B$131,MATCH($A28,'REFERENCING & DATABASE'!$D$7:$D$131,0)),"") -> BOTTOMS | D28: =IFERROR(INDEX('REFERENCING & DATABASE'!$C$7:$C$131,MATCH($A28,'REFERENCING & DATABASE'!$D$7:$D$131,0)),"") -> SHORTS | E28: =IFERROR(INDEX('REFERENCING & DATABASE'!$F$7:$F$131,MATCH($A28,'REFERENCING & DATABASE'!$D$7:$D$131,0)),"") -> A classic and casual style with a relaxed fit. | F28: =IFERROR(INDEX('REFERENCING & DATABASE'!$G$7:$G$131,MATCH($A28,'REFERENCING & DATABASE'!$D$7:$D$131,0)),"") -> light beige, medium beige, dark beige | G28: =IFERROR(INDEX('REFERENCING & DATABASE'!$H$7:$H$131,MATCH($A28,'REFERENCING & DATABASE'!$D$7:$D$131,0)),"") -> 30 | H28: =IFERROR(INDEX('REFERENCING & DATABASE'!$A$7:$A$131,MATCH($A28,'REFERENCING & DATABASE'!$D$7:$D$131,0)),"") -> 625 | I28: =H28-SUM($K28,$M28,$O28,$Q28) -> 615 | J28: =ROUND((($K28/$H28)*100),3) -> 1.6 | K28: =SUMIFS('IN STORE SALES RECORD'!$E$6:$E$97,'IN STORE SALES RECORD'!$A$6:$A$97, "WEEK 1",'IN STORE SALES RECORD'!$D$6:$D$97,'WHS STK MGT & ALLOC.'!$A28)+10 -> 10 | L28: =ROUND(($M28/($H28-$K28))*100,3) -> 0 | M28: =SUMIFS('IN STORE SALES RECORD'!$E$6:$E$97,'IN STORE SALES RECORD'!$A$6:$A$97, "WEEK 6",'IN STORE SALES RECORD'!$D$6:$D$97,'WHS STK MGT & ALLOC.'!$A28) -> 0 | N28: =ROUND(($O28/($H28-($M28+$K28))*100),3) -> 0 | O28: =SUMIFS('IN STORE SALES RECORD'!$E$6:$E$97,'IN STORE SALES RECORD'!$A$6:$A$97, "WEEK 6",'IN STORE SALES RECORD'!$D$6:$D$97,'WHS STK MGT & ALLOC.'!$A28) -> 0 | P28: =ROUND(($Q28/($H28-($M28+$K28+$O28))*100),3) -> 0 | Q28: =SUMIFS('IN STORE SALES RECORD'!$E$6:$E$97,'IN STORE SALES RECORD'!$A$6:$A$97, "WEEK 6",'IN STORE SALES RECORD'!$D$6:$D$97,'WHS STK MGT & ALLOC.'!$A28) -> 0 | R28: =ROUND(($S28/($H28-($M28+$K28+$O28+$Q28))*100),3) -> 0 | S28: =SUMIFS('IN STORE SALES RECORD'!$E$6:$E$97,'IN STORE SALES RECORD'!$A$6:$A$97, "WEEK 6",'IN STORE SALES RECORD'!$D$6:$D$97,'WHS STK MGT & ALLOC.'!$A28) -> 0 | T28: =ROUND(($U28/($H28-($M28+$K28+$O28+$Q28+$S28))*100),3) -> 0 | U28: =SUMIFS('IN STORE SALES RECORD'!$E$6:$E$97,'IN STORE SALES RECORD'!$A$6:$A$97, "WEEK 6",'IN STORE SALES RECORD'!$D$6:$D$97,'WHS STK MGT & ALLOC.'!$A28) -> 0 | V28: =ROUND(($W28/($H28-($M28+$K28+$O28+$Q28+$S28+$U28))*100),3) -> 0 | W28: =SUMIFS('IN STORE SALES RECORD'!$E$6:$E$97,'IN STORE SALES RECORD'!$A$6:$A$97, "WEEK 6",'IN STORE SALES RECORD'!$D$6:$D$97,'WHS STK MGT & ALLOC.'!$A28) -> 0 | X28: =ROUND(($Y28/($H28-($M28+$K28+$O28+$Q28+$S28+$U28+$W28))*100),3) -> 0 | Y28: =SUMIFS('IN STORE SALES RECORD'!$E$6:$E$97,'IN STORE SALES RECORD'!$A$6:$A$97, "WEEK 6",'IN STORE SALES RECORD'!$D$6:$D$97,'WHS STK MGT & ALLOC.'!$A28) -> 0
A29: BO-SH-KH-LI-30 | B29: =IFERROR(INDEX('REFERENCING & DATABASE'!$E$7:$E$131,MATCH($A29,'REFERENCING & DATABASE'!$D$7:$D$131,0)),"") -> Khaki Chino Shorts | C29: =IFERROR(INDEX('REFERENCING & DATABASE'!$B$7:$B$131,MATCH($A29,'REFERENCING & DATABASE'!$D$7:$D$131,0)),"") -> BOTTOMS | D29: =IFERROR(INDEX('REFERENCING & DATABASE'!$C$7:$C$131,MATCH($A29,'REFERENCING & DATABASE'!$D$7:$D$131,0)),"") -> SHORTS | E29: =IFERROR(INDEX('REFERENCING & DATABASE'!$F$7:$F$131,MATCH($A29,'REFERENCING & DATABASE'!$D$7:$D$131,0)),"") -> A versatile option for warmer weather. | F29: =IFERROR(INDEX('REFERENCING & DATABASE'!$G$7:$G$131,MATCH($A29,'REFERENCING & DATABASE'!$D$7:$D$131,0)),"") -> light beige, Brown | G29: =IFERROR(INDEX('REFERENCING & DATABASE'!$H$7:$H$131,MATCH($A29,'REFERENCING & DATABASE'!$D$7:$D$131,0)),"") -> 30 | H29: =IFERROR(INDEX('REFERENCING & DATABASE'!$A$7:$A$131,MATCH($A29,'REFERENCING & DATABASE'!$D$7:$D$131,0)),"") -> 488 | I29: =H29-SUM($K29,$M29,$O29,$Q29) -> 478 | J29: =ROUND((($K29/$H29)*100),3) -> 2.049 | K29: =SUMIFS('IN STORE SALES RECORD'!$E$6:$E$97,'IN STORE SALES RECORD'!$A$6:$A$97, "WEEK 1",'IN STORE SALES RECORD'!$D$6:$D$97,'WHS STK MGT & ALLOC.'!$A29)+10 -> 10 | L29: =ROUND(($M29/($H29-$K29))*100,3) -> 0 | M29: =SUMIFS('IN STORE SALES RECORD'!$E$6:$E$97,'IN STORE SALES RECORD'!$A$6:$A$97, "WEEK 6",'IN STORE SALES RECORD'!$D$6:$D$97,'WHS STK MGT & ALLOC.'!$A29) -> 0 | N29: =ROUND(($O29/($H29-($M29+$K29))*100),3) -> 0 | O29: =SUMIFS('IN STORE SALES RECORD'!$E$6:$E$97,'IN STORE SALES RECORD'!$A$6:$A$97, "WEEK 6",'IN STORE SALES RECORD'!$D$6:$D$97,'WHS STK MGT & ALLOC.'!$A29) -> 0 | P29: =ROUND(($Q29/($H29-($M29+$K29+$O29))*100),3) -> 0 | Q29: =SUMIFS('IN STORE SALES RECORD'!$E$6:$E$97,'IN STORE SALES RECORD'!$A$6:$A$97, "WEEK 6",'IN STORE SALES RECORD'!$D$6:$D$97,'WHS STK MGT & ALLOC.'!$A29) -> 0 | R29: =ROUND(($S29/($H29-($M29+$K29+$O29+$Q29))*100),3) -> 0 | S29: =SUMIFS('IN STORE SALES RECORD'!$E$6:$E$97,'IN STORE SALES RECORD'!$A$6:$A$97, "WEEK 6",'IN STORE SALES RECORD'!$D$6:$D$97,'WHS STK MGT & ALLOC.'!$A29) -> 0 | T29: =ROUND(($U29/($H29-($M29+$K29+$O29+$Q29+$S29))*100),3) -> 0 | U29: =SUMIFS('IN STORE SALES RECORD'!$E$6:$E$97,'IN STORE SALES RECORD'!$A$6:$A$97, "WEEK 6",'IN STORE SALES RECORD'!$D$6:$D$97,'WHS STK MGT & ALLOC.'!$A29) -> 0 | V29: =ROUND(($W29/($H29-($M29+$K29+$O29+$Q29+$S29+$U29))*100),3) -> 0 | W29: =SUMIFS('IN STORE SALES RECORD'!$E$6:$E$97,'IN STORE SALES RECORD'!$A$6:$A$97, "WEEK 6",'IN STORE SALES RECORD'!$D$6:$D$97,'WHS STK MGT & ALLOC.'!$A29) -> 0 | X29: =ROUND(($Y29/($H29-($M29+$K29+$O29+$Q29+$S29+$U29+$W29))*100),3) -> 0 | Y29: =SUMIFS('IN STORE SALES RECORD'!$E$6:$E$97,'IN STORE SALES RECORD'!$A$6:$A$97, "WEEK 6",'IN STORE SALES RECORD'!$D$6:$D$97,'WHS STK MGT & ALLOC.'!$A29) -> 0
A30: BO-SH-PE-MU-30 | B30: =IFERROR(INDEX('REFERENCING & DATABASE'!$E$7:$E$131,MATCH($A30,'REFERENCING & DATABASE'!$D$7:$D$131,0)),"") -> Performance Athletic Shorts | C30: =IFERROR(INDEX('REFERENCING & DATABASE'!$B$7:$B$131,MATCH($A30,'REFERENCING & DATABASE'!$D$7:$D$131,0)),"") -> BOTTOMS | D30: =IFERROR(INDEX('REFERENCING & DATABASE'!$C$7:$C$131,MATCH($A30,'REFERENCING & DATABASE'!$D$7:$D$131,0)),"") -> SHORTS | E30: =IFERROR(INDEX('REFERENCING & DATABASE'!$F$7:$F$131,MATCH($A30,'REFERENCING & DATABASE'!$D$7:$D$131,0)),"") -> Lightweight and breathable shorts for workouts or running. | F30: =IFERROR(INDEX('REFERENCING & DATABASE'!$G$7:$G$131,MATCH($A30,'REFERENCING & DATABASE'!$D$7:$D$131,0)),"") -> Multi-colors | G30: =IFERROR(INDEX('REFERENCING & DATABASE'!$H$7:$H$131,MATCH($A30,'REFERENCING & DATABASE'!$D$7:$D$131,0)),"") -> 30 | H30: =IFERROR(INDEX('REFERENCING & DATABASE'!$A$7:$A$131,MATCH($A30,'REFERENCING & DATABASE'!$D$7:$D$131,0)),"") -> 363 | I30: =H30-SUM($K30,$M30,$O30,$Q30) -> 353 | J30: =ROUND((($K30/$H30)*100),3) -> 2.755 | K30: =SUMIFS('IN STORE SALES RECORD'!$E$6:$E$97,'IN STORE SALES RECORD'!$A$6:$A$97, "WEEK 1",'IN STORE SALES RECORD'!$D$6:$D$97,'WHS STK MGT & ALLOC.'!$A30)+10 -> 10 | L30: =ROUND(($M30/($H30-$K30))*100,3) -> 0 | M30: =SUMIFS('IN STORE SALES RECORD'!$E$6:$E$97,'IN STORE SALES RECORD'!$A$6:$A$97, "WEEK 6",'IN STORE SALES RECORD'!$D$6:$D$97,'WHS STK MGT & ALLOC.'!$A30) -> 0 | N30: =ROUND(($O30/($H30-($M30+$K30))*100),3) -> 0 | O30: =SUMIFS('IN STORE SALES RECORD'!$E$6:$E$97,'IN STORE SALES RECORD'!$A$6:$A$97, "WEEK 6",'IN STORE SALES RECORD'!$D$6:$D$97,'WHS STK MGT & ALLOC.'!$A30) -> 0 | P30: =ROUND(($Q30/($H30-($M30+$K30+$O30))*100),3) -> 0 | Q30: =SUMIFS('IN STORE SALES RECORD'!$E$6:$E$97,'IN STORE SALES RECORD'!$A$6:$A$97, "WEEK 6",'IN STORE SALES RECORD'!$D$6:$D$97,'WHS STK MGT & ALLOC.'!$A30) -> 0 | R30: =ROUND(($S30/($H30-($M30+$K30+$O30+$Q30))*100),3) -> 0 | S30: =SUMIFS('IN STORE SALES RECORD'!$E$6:$E$97,'IN STORE SALES RECORD'!$A$6:$A$97, "WEEK 6",'IN STORE SALES RECORD'!$D$6:$D$97,'WHS STK MGT & ALLOC.'!$A30) -> 0 | T30: =ROUND(($U30/($H30-($M30+$K30+$O30+$Q30+$S30))*100),3) -> 0 | U30: =SUMIFS('IN STORE SALES RECORD'!$E$6:$E$97,'IN STORE SALES RECORD'!$A$6:$A$97, "WEEK 6",'IN STORE SALES RECORD'!$D$6:$D$97,'WHS STK MGT & ALLOC.'!$A30) -> 0 | V30: =ROUND(($W30/($H30-($M30+$K30+$O30+$Q30+$S30+$U30))*100),3) -> 0 | W30: =SUMIFS('IN STORE SALES RECORD'!$E$6:$E$97,'IN STORE SALES RECORD'!$A$6:$A$97, "WEEK 6",'IN STORE SALES RECORD'!$D$6:$D$97,'WHS STK MGT & ALLOC.'!$A30) -> 0 | X30: =ROUND(($Y30/($H30-($M30+$K30+$O30+$Q30+$S30+$U30+$W30))*100),3) -> 0 | Y30: =SUMIFS('IN STORE SALES RECORD'!$E$6:$E$97,'IN STORE SALES RECORD'!$A$6:$A$97, "WEEK 6",'IN STORE SALES RECORD'!$D$6:$D$97,'WHS STK MGT & ALLOC.'!$A30) -> 0
A31: BO-SH-UT-GR-30 | B31: =IFERROR(INDEX('REFERENCING & DATABASE'!$E$7:$E$131,MATCH($A31,'REFERENCING & DATABASE'!$D$7:$D$131,0)),"") -> Utility Cargo Shorts | C31: =IFERROR(INDEX('REFERENCING & DATABASE'!$B$7:$B$131,MATCH($A31,'REFERENCING & DATABASE'!$D$7:$D$131,0)),"") -> BOTTOMS | D31: =IFERROR(INDEX('REFERENCING & DATABASE'!$C$7:$C$131,MATCH($A31,'REFERENCING & DATABASE'!$D$7:$D$131,0)),"") -> SHORTS | E31: =IFERROR(INDEX('REFERENCING & DATABASE'!$F$7:$F$131,MATCH($A31,'REFERENCING & DATABASE'!$D$7:$D$131,0)),"") -> Functional and stylish shorts with multiple pockets. | F31: =IFERROR(INDEX('REFERENCING & DATABASE'!$G$7:$G$131,MATCH($A31,'REFERENCING & DATABASE'!$D$7:$D$131,0)),"") -> Green,Brown,Black | G31: =IFERROR(INDEX('REFERENCING & DATABASE'!$H$7:$H$131,MATCH($A31,'REFERENCING & DATABASE'!$D$7:$D$131,0)),"") -> 30 | H31: =IFERROR(INDEX('REFERENCING & DATABASE'!$A$7:$A$131,MATCH($A31,'REFERENCING & DATABASE'!$D$7:$D$131,0)),"") -> 390 | I31: =H31-SUM($K31,$M31,$O31,$Q31) -> 380 | J31: =ROUND((($K31/$H31)*100),3) -> 2.564 | K31: =SUMIFS('IN STORE SALES RECORD'!$E$6:$E$97,'IN STORE SALES RECORD'!$A$6:$A$97, "WEEK 1",'IN STORE SALES RECORD'!$D$6:$D$97,'WHS STK MGT & ALLOC.'!$A31)+10 -> 10 | L31: =ROUND(($M31/($H31-$K31))*100,3) -> 0 | M31: =SUMIFS('IN STORE SALES RECORD'!$E$6:$E$97,'IN STORE SALES RECORD'!$A$6:$A$97, "WEEK 6",'IN STORE SALES RECORD'!$D$6:$D$97,'WHS STK MGT & ALLOC.'!$A31) -> 0 | N31: =ROUND(($O31/($H31-($M31+$K31))*100),3) -> 0 | O31: =SUMIFS('IN STORE SALES RECORD'!$E$6:$E$97,'IN STORE SALES RECORD'!$A$6:$A$97, "WEEK 6",'IN STORE SALES RECORD'!$D$6:$D$97,'WHS STK MGT & ALLOC.'!$A31) -> 0 | P31: =ROUND(($Q31/($H31-($M31+$K31+$O31))*100),3) -> 0 | Q31: =SUMIFS('IN STORE SALES RECORD'!$E$6:$E$97,'IN STORE SALES RECORD'!$A$6:$A$97, "WEEK 6",'IN STORE SALES RECORD'!$D$6:$D$97,'WHS STK MGT & ALLOC.'!$A31) -> 0 | R31: =ROUND(($S31/($H31-($M31+$K31+$O31+$Q31))*100),3) -> 0 | S31: =SUMIFS('IN STORE SALES RECORD'!$E$6:$E$97,'IN STORE SALES RECORD'!$A$6:$A$97, "WEEK 6",'IN STORE SALES RECORD'!$D$6:$D$97,'WHS STK MGT & ALLOC.'!$A31) -> 0 | T31: =ROUND(($U31/($H31-($M31+$K31+$O31+$Q31+$S31))*100),3) -> 0 | U31: =SUMIFS('IN STORE SALES RECORD'!$E$6:$E$97,'IN STORE SALES RECORD'!$A$6:$A$97, "WEEK 6",'IN STORE SALES RECORD'!$D$6:$D$97,'WHS STK MGT & ALLOC.'!$A31) -> 0 | V31: =ROUND(($W31/($H31-($M31+$K31+$O31+$Q31+$S31+$U31))*100),3) -> 0 | W31: =SUMIFS('IN STORE SALES RECORD'!$E$6:$E$97,'IN STORE SALES RECORD'!$A$6:$A$97, "WEEK 6",'IN STORE SALES RECORD'!$D$6:$D$97,'WHS STK MGT & ALLOC.'!$A31) -> 0 | X31: =ROUND(($Y31/($H31-($M31+$K31+$O31+$Q31+$S31+$U31+$W31))*100),3) -> 0 | Y31: =SUMIFS('IN STORE SALES RECORD'!$E$6:$E$97,'IN STORE SALES RECORD'!$A$6:$A$97, "WEEK 6",'IN STORE SALES RECORD'!$D$6:$D$97,'WHS STK MGT & ALLOC.'!$A31) -> 0
A35: =A$6 -> REFERENCE | B35: =B$6 -> PRODUCT NAME | C35: =C$6 -> CATEGORY | D35: =D$6 -> SUB-CATEGORY | E35: =E$6 -> DESCRIPTION | F35: =F$6 -> COLOUR | G35: =G$6 -> SIZE | H35: =H$6 -> TOTAL STOCK | ... Q35: =Q$6 -> 4TH WEEK | R35: 5TH WEEK % ALLOCATION | S35: 5TH WEEK | T35: 6TH WEEK % ALLOCATION | U35: 6TH WEEK | V35: 7TH WEEK % ALLOCATION | W35: 7TH WEEK | X35: 8TH WEEK % ALLOCATION | Y35: 8TH WEEK
A36: SL-PA-CO-MU-L | B36: =IFERROR(INDEX('REFERENCING & DATABASE'!$E$7:$E$131,MATCH($A36,'REFERENCING & DATABASE'!$D$7:$D$131,0)),"") -> Cozy Flannel Pajama Set | C36: =IFERROR(INDEX('REFERENCING & DATABASE'!$B$7:$B$131,MATCH($A36,'REFERENCING & DATABASE'!$D$7:$D$131,0)),"") -> SLEEPWEAR | D36: =IFERROR(INDEX('REFERENCING & DATABASE'!$C$7:$C$131,MATCH($A36,'REFERENCING & DATABASE'!$D$7:$D$131,0)),"") -> PAJAMAS | E36: =IFERROR(INDEX('REFERENCING & DATABASE'!$F$7:$F$131,MATCH($A36,'REFERENCING & DATABASE'!$D$7:$D$131,0)),"") -> A soft and warm set perfect for cooler nights. | F36: =IFERROR(INDEX('REFERENCING & DATABASE'!$G$7:$G$131,MATCH($A36,'REFERENCING & DATABASE'!$D$7:$D$131,0)),"") -> Multi-colors | G36: =IFERROR(INDEX('REFERENCING & DATABASE'!$H$7:$H$131,MATCH($A36,'REFERENCING & DATABASE'!$D$7:$D$131,0)),"") -> L,XL,XXL | H36: =IFERROR(INDEX('REFERENCING & DATABASE'!$A$7:$A$131,MATCH($A36,'REFERENCING & DATABASE'!$D$7:$D$131,0)),"") -> 488 | I36: =H36-SUM($K36,$M36,$O36,$Q36) -> 478 | J36: =ROUND((($K36/$H36)*100),3) -> 2.049 | K36: =SUMIFS('IN STORE SALES RECORD'!$E$6:$E$97,'IN STORE SALES RECORD'!$A$6:$A$97, "WEEK 1",'IN STORE SALES RECORD'!$D$6:$D$97,'WHS STK MGT & ALLOC.'!$A36)+10 -> 10 | L36: =ROUND(($M36/($H36-$K36))*100,3) -> 0 | M36: =SUMIFS('IN STORE SALES RECORD'!$E$6:$E$97,'IN STORE SALES RECORD'!$A$6:$A$97, "WEEK 6",'IN STORE SALES RECORD'!$D$6:$D$97,'WHS STK MGT & ALLOC.'!$A36) -> 0 | N36: =ROUND(($O36/($H36-($M36+$K36))*100),3) -> 0 | O36: =SUMIFS('IN STORE SALES RECORD'!$E$6:$E$97,'IN STORE SALES RECORD'!$A$6:$A$97, "WEEK 6",'IN STORE SALES RECORD'!$D$6:$D$97,'WHS STK MGT & ALLOC.'!$A36) -> 0 | P36: =ROUND(($Q36/($H36-($M36+$K36+$O36))*100),3) -> 0 | Q36: =SUMIFS('IN STORE SALES RECORD'!$E$6:$E$97,'IN STORE SALES RECORD'!$A$6:$A$97, "WEEK 6",'IN STORE SALES RECORD'!$D$6:$D$97,'WHS STK MGT & ALLOC.'!$A36) -> 0 | R36: =ROUND(($S36/($H36-($M36+$K36+$O36+$Q36))*100),3) -> 0 | S36: =SUMIFS('IN STORE SALES RECORD'!$E$6:$E$97,'IN STORE SALES RECORD'!$A$6:$A$97, "WEEK 6",'IN STORE SALES RECORD'!$D$6:$D$97,'WHS STK MGT & ALLOC.'!$A36) -> 0 | T36: =ROUND(($U36/($H36-($M36+$K36+$O36+$Q36+$S36))*100),3) -> 0 | U36: =SUMIFS('IN STORE SALES RECORD'!$E$6:$E$97,'IN STORE SALES RECORD'!$A$6:$A$97, "WEEK 6",'IN STORE SALES RECORD'!$D$6:$D$97,'WHS STK MGT & ALLOC.'!$A36) -> 0 | V36: =ROUND(($W36/($H36-($M36+$K36+$O36+$Q36+$S36+$U36))*100),3) -> 0 | W36: =SUMIFS('IN STORE SALES RECORD'!$E$6:$E$97,'IN STORE SALES RECORD'!$A$6:$A$97, "WEEK 6",'IN STORE SALES RECORD'!$D$6:$D$97,'WHS STK MGT & ALLOC.'!$A36) -> 0 | X36: =ROUND(($Y36/($H36-($M36+$K36+$O36+$Q36+$S36+$U36+$W36))*100),3) -> 0 | Y36: =SUMIFS('IN STORE SALES RECORD'!$E$6:$E$97,'IN STORE SALES RECORD'!$A$6:$A$97, "WEEK 6",'IN STORE SALES RECORD'!$D$6:$D$97,'WHS STK MGT & ALLOC.'!$A36) -> 0
A37: SL-PA-MO-MU-M | B37: =IFERROR(INDEX('REFERENCING & DATABASE'!$E$7:$E$131,MATCH($A37,'REFERENCING & DATABASE'!$D$7:$D$131,0)),"") -> Modal Jersey PJ Set | C37: =IFERROR(INDEX('REFERENCING & DATABASE'!$B$7:$B$131,MATCH($A37,'REFERENCING & DATABASE'!$D$7:$D$131,0)),"") -> SLEEPWEAR | D37: =IFERROR(INDEX('REFERENCING & DATABASE'!$C$7:$C$131,MATCH($A37,'REFERENCING & DATABASE'!$D$7:$D$131,0)),"") -> PAJAMAS | E37: =IFERROR(INDEX('REFERENCING & DATABASE'!$F$7:$F$131,MATCH($A37,'REFERENCING & DATABASE'!$D$7:$D$131,0)),"") -> A lightweight and breathable set for year-round comfort. | F37: =IFERROR(INDEX('REFERENCING & DATABASE'!$G$7:$G$131,MATCH($A37,'REFERENCING & DATABASE'!$D$7:$D$131,0)),"") -> Multi-colors | G37: =IFERROR(INDEX('REFERENCING & DATABASE'!$H$7:$H$131,MATCH($A37,'REFERENCING & DATABASE'!$D$7:$D$131,0)),"") -> M,L,XL,XXL | H37: =IFERROR(INDEX('REFERENCING & DATABASE'!$A$7:$A$131,MATCH($A37,'REFERENCING & DATABASE'!$D$7:$D$131,0)),"") -> 267 | I37: =H37-SUM($K37,$M37,$O37,$Q37) -> 257 | J37: =ROUND((($K37/$H37)*100),3) -> 3.745 | K37: =SUMIFS('IN STORE SALES RECORD'!$E$6:$E$97,'IN STORE SALES RECORD'!$A$6:$A$97, "WEEK 1",'IN STORE SALES RECORD'!$D$6:$D$97,'WHS STK MGT & ALLOC.'!$A37)+10 -> 10 | L37: =ROUND(($M37/($H37-$K37))*100,3) -> 0 | M37: =SUMIFS('IN STORE SALES RECORD'!$E$6:$E$97,'IN STORE SALES RECORD'!$A$6:$A$97, "WEEK 6",'IN STORE SALES RECORD'!$D$6:$D$97,'WHS STK MGT & ALLOC.'!$A37) -> 0 | N37: =ROUND(($O37/($H37-($M37+$K37))*100),3) -> 0 | O37: =SUMIFS('IN STORE SALES RECORD'!$E$6:$E$97,'IN STORE SALES RECORD'!$A$6:$A$97, "WEEK 6",'IN STORE SALES RECORD'!$D$6:$D$97,'WHS STK MGT & ALLOC.'!$A37) -> 0 | P37: =ROUND(($Q37/($H37-($M37+$K37+$O37))*100),3) -> 0 | Q37: =SUMIFS('IN STORE SALES RECORD'!$E$6:$E$97,'IN STORE SALES RECORD'!$A$6:$A$97, "WEEK 6",'IN STORE SALES RECORD'!$D$6:$D$97,'WHS STK MGT & ALLOC.'!$A37) -> 0 | R37: =ROUND(($S37/($H37-($M37+$K37+$O37+$Q37))*100),3) -> 0 | S37: =SUMIFS('IN STORE SALES RECORD'!$E$6:$E$97,'IN STORE SALES RECORD'!$A$6:$A$97, "WEEK 6",'IN STORE SALES RECORD'!$D$6:$D$97,'WHS STK MGT & ALLOC.'!$A37) -> 0 | T37: =ROUND(($U37/($H37-($M37+$K37+$O37+$Q37+$S37))*100),3) -> 0 | U37: =SUMIFS('IN STORE SALES RECORD'!$E$6:$E$97,'IN STORE SALES RECORD'!$A$6:$A$97, "WEEK 6",'IN STORE SALES RECORD'!$D$6:$D$97,'WHS STK MGT & ALLOC.'!$A37) -> 0 | V37: =ROUND(($W37/($H37-($M37+$K37+$O37+$Q37+$S37+$U37))*100),3) -> 0 | W37: =SUMIFS('IN STORE SALES RECORD'!$E$6:$E$97,'IN STORE SALES RECORD'!$A$6:$A$97, "WEEK 6",'IN STORE SALES RECORD'!$D$6:$D$97,'WHS STK MGT & ALLOC.'!$A37) -> 0 | X37: =ROUND(($Y37/($H37-($M37+$K37+$O37+$Q37+$S37+$U37+$W37))*100),3) -> 0 | Y37: =SUMIFS('IN STORE SALES RECORD'!$E$6:$E$97,'IN STORE SALES RECORD'!$A$6:$A$97, "WEEK 6",'IN STORE SALES RECORD'!$D$6:$D$97,'WHS STK MGT & ALLOC.'!$A37) -> 0
A38: SL-PA-ST-WH-L | B38: =IFERROR(INDEX('REFERENCING & DATABASE'!$E$7:$E$131,MATCH($A38,'REFERENCING & DATABASE'!$D$7:$D$131,0)),"") -> Striped Cotton Onesie | C38: =IFERROR(INDEX('REFERENCING & DATABASE'!$B$7:$B$131,MATCH($A38,'REFERENCING & DATABASE'!$D$7:$D$131,0)),"") -> SLEEPWEAR | D38: =IFERROR(INDEX('REFERENCING & DATABASE'!$C$7:$C$131,MATCH($A38,'REFERENCING & DATABASE'!$D$7:$D$131,0)),"") -> PAJAMAS | E38: =IFERROR(INDEX('REFERENCING & DATABASE'!$F$7:$F$131,MATCH($A38,'REFERENCING & DATABASE'!$D$7:$D$131,0)),"") -> A comfortable and playful option for lounging or sleeping. | F38: =IFERROR(INDEX('REFERENCING & DATABASE'!$G$7:$G$131,MATCH($A38,'REFERENCING & DATABASE'!$D$7:$D$131,0)),"") -> White,Grey | G38: =IFERROR(INDEX('REFERENCING & DATABASE'!$H$7:$H$131,MATCH($A38,'REFERENCING & DATABASE'!$D$7:$D$131,0)),"") -> L,XL,XXL | H38: =IFERROR(INDEX('REFERENCING & DATABASE'!$A$7:$A$131,MATCH($A38,'REFERENCING & DATABASE'!$D$7:$D$131,0)),"") -> 220 | I38: =H38-SUM($K38,$M38,$O38,$Q38) -> 210 | J38: =ROUND((($K38/$H38)*100),3) -> 4.545 | K38: =SUMIFS('IN STORE SALES RECORD'!$E$6:$E$97,'IN STORE SALES RECORD'!$A$6:$A$97, "WEEK 1",'IN STORE SALES RECORD'!$D$6:$D$97,'WHS STK MGT & ALLOC.'!$A38)+10 -> 10 | L38: =ROUND(($M38/($H38-$K38))*100,3) -> 0 | M38: =SUMIFS('IN STORE SALES RECORD'!$E$6:$E$97,'IN STORE SALES RECORD'!$A$6:$A$97, "WEEK 6",'IN STORE SALES RECORD'!$D$6:$D$97,'WHS STK MGT & ALLOC.'!$A38) -> 0 | N38: =ROUND(($O38/($H38-($M38+$K38))*100),3) -> 0 | O38: =SUMIFS('IN STORE SALES RECORD'!$E$6:$E$97,'IN STORE SALES RECORD'!$A$6:$A$97, "WEEK 6",'IN STORE SALES RECORD'!$D$6:$D$97,'WHS STK MGT & ALLOC.'!$A38) -> 0 | P38: =ROUND(($Q38/($H38-($M38+$K38+$O38))*100),3) -> 0 | Q38: =SUMIFS('IN STORE SALES RECORD'!$E$6:$E$97,'IN STORE SALES RECORD'!$A$6:$A$97, "WEEK 6",'IN STORE SALES RECORD'!$D$6:$D$97,'WHS STK MGT & ALLOC.'!$A38) -> 0 | R38: =ROUND(($S38/($H38-($M38+$K38+$O38+$Q38))*100),3) -> 0 | S38: =SUMIFS('IN STORE SALES RECORD'!$E$6:$E$97,'IN STORE SALES RECORD'!$A$6:$A$97, "WEEK 6",'IN STORE SALES RECORD'!$D$6:$D$97,'WHS STK MGT & ALLOC.'!$A38) -> 0 | T38: =ROUND(($U38/($H38-($M38+$K38+$O38+$Q38+$S38))*100),3) -> 0 | U38: =SUMIFS('IN STORE SALES RECORD'!$E$6:$E$97,'IN STORE SALES RECORD'!$A$6:$A$97, "WEEK 6",'IN STORE SALES RECORD'!$D$6:$D$97,'WHS STK MGT & ALLOC.'!$A38) -> 0 | V38: =ROUND(($W38/($H38-($M38+$K38+$O38+$Q38+$S38+$U38))*100),3) -> 0 | W38: =SUMIFS('IN STORE SALES RECORD'!$E$6:$E$97,'IN STORE SALES RECORD'!$A$6:$A$97, "WEEK 6",'IN STORE SALES RECORD'!$D$6:$D$97,'WHS STK MGT & ALLOC.'!$A38) -> 0 | X38: =ROUND(($Y38/($H38-($M38+$K38+$O38+$Q38+$S38+$U38+$W38))*100),3) -> 0 | Y38: =SUMIFS('IN STORE SALES RECORD'!$E$6:$E$97,'IN STORE SALES RECORD'!$A$6:$A$97, "WEEK 6",'IN STORE SALES RECORD'!$D$6:$D$97,'WHS STK MGT & ALLOC.'!$A38) -> 0
A39: SL-PA-FL-MU-L | B39: =IFERROR(INDEX('REFERENCING & DATABASE'!$E$7:$E$131,MATCH($A39,'REFERENCING & DATABASE'!$D$7:$D$131,0)),"") -> Floral Lace Nightgown | C39: =IFERROR(INDEX('REFERENCING & DATABASE'!$B$7:$B$131,MATCH($A39,'REFERENCING & DATABASE'!$D$7:$D$131,0)),"") -> SLEEPWEAR | D39: =IFERROR(INDEX('REFERENCING & DATABASE'!$C$7:$C$131,MATCH($A39,'REFERENCING & DATABASE'!$D$7:$D$131,0)),"") -> PAJAMAS | E39: =IFERROR(INDEX('REFERENCING & DATABASE'!$F$7:$F$131,MATCH($A39,'REFERENCING & DATABASE'!$D$7:$D$131,0)),"") -> A feminine and elegant nightgown for a luxurious feel. | F39: =IFERROR(INDEX('REFERENCING & DATABASE'!$G$7:$G$131,MATCH($A39,'REFERENCING & DATABASE'!$D$7:$D$131,0)),"") -> Multi-colors | G39: =IFERROR(INDEX('REFERENCING & DATABASE'!$H$7:$H$131,MATCH($A39,'REFERENCING & DATABASE'!$D$7:$D$131,0)),"") -> L,XL,XXL | H39: =IFERROR(INDEX('REFERENCING & DATABASE'!$A$7:$A$131,MATCH($A39,'REFERENCING & DATABASE'!$D$7:$D$131,0)),"") -> 541 | I39: =H39-SUM($K39,$M39,$O39,$Q39) -> 531 | J39: =ROUND((($K39/$H39)*100),3) -> 1.848 | K39: =SUMIFS('IN STORE SALES RECORD'!$E$6:$E$97,'IN STORE SALES RECORD'!$A$6:$A$97, "WEEK 1",'IN STORE SALES RECORD'!$D$6:$D$97,'WHS STK MGT & ALLOC.'!$A39)+10 -> 10 | L39: =ROUND(($M39/($H39-$K39))*100,3) -> 0 | M39: =SUMIFS('IN STORE SALES RECORD'!$E$6:$E$97,'IN STORE SALES RECORD'!$A$6:$A$97, "WEEK 6",'IN STORE SALES RECORD'!$D$6:$D$97,'WHS STK MGT & ALLOC.'!$A39) -> 0 | N39: =ROUND(($O39/($H39-($M39+$K39))*100),3) -> 0 | O39: =SUMIFS('IN STORE SALES RECORD'!$E$6:$E$97,'IN STORE SALES RECORD'!$A$6:$A$97, "WEEK 6",'IN STORE SALES RECORD'!$D$6:$D$97,'WHS STK MGT & ALLOC.'!$A39) -> 0 | P39: =ROUND(($Q39/($H39-($M39+$K39+$O39))*100),3) -> 0 | Q39: =SUMIFS('IN STORE SALES RECORD'!$E$6:$E$97,'IN STORE SALES RECORD'!$A$6:$A$97, "WEEK 6",'IN STORE SALES RECORD'!$D$6:$D$97,'WHS STK MGT & ALLOC.'!$A39) -> 0 | R39: =ROUND(($S39/($H39-($M39+$K39+$O39+$Q39))*100),3) -> 0 | S39: =SUMIFS('IN STORE SALES RECORD'!$E$6:$E$97,'IN STORE SALES RECORD'!$A$6:$A$97, "WEEK 6",'IN STORE SALES RECORD'!$D$6:$D$97,'WHS STK MGT & ALLOC.'!$A39) -> 0 | T39: =ROUND(($U39/($H39-($M39+$K39+$O39+$Q39+$S39))*100),3) -> 0 | U39: =SUMIFS('IN STORE SALES RECORD'!$E$6:$E$97,'IN STORE SALES RECORD'!$A$6:$A$97, "WEEK 6",'IN STORE SALES RECORD'!$D$6:$D$97,'WHS STK MGT & ALLOC.'!$A39) -> 0 | V39: =ROUND(($W39/($H39-($M39+$K39+$O39+$Q39+$S39+$U39))*100),3) -> 0 | W39: =SUMIFS('IN STORE SALES RECORD'!$E$6:$E$97,'IN STORE SALES RECORD'!$A$6:$A$97, "WEEK 6",'IN STORE SALES RECORD'!$D$6:$D$97,'WHS STK MGT & ALLOC.'!$A39) -> 0 | X39: =ROUND(($Y39/($H39-($M39+$K39+$O39+$Q39+$S39+$U39+$W39))*100),3) -> 0 | Y39: =SUMIFS('IN STORE SALES RECORD'!$E$6:$E$97,'IN STORE SALES RECORD'!$A$6:$A$97, "WEEK 6",'IN STORE SALES RECORD'!$D$6:$D$97,'WHS STK MGT & ALLOC.'!$A39) -> 0
A40: SL-LO-FR-BL-S | B40: =IFERROR(INDEX('REFERENCING & DATABASE'!$E$7:$E$131,MATCH($A40,'REFERENCING & DATABASE'!$D$7:$D$131,0)),"") -> French Terry Loungewear Set | C40: =IFERROR(INDEX('REFERENCING & DATABASE'!$B$7:$B$131,MATCH($A40,'REFERENCING & DATABASE'!$D$7:$D$131,0)),"") -> SLEEPWEAR | D40: =IFERROR(INDEX('REFERENCING & DATABASE'!$C$7:$C$131,MATCH($A40,'REFERENCING & DATABASE'!$D$7:$D$131,0)),"") -> LOUNGEWEAR | E40: =IFERROR(INDEX('REFERENCING & DATABASE'!$F$7:$F$131,MATCH($A40,'REFERENCING & DATABASE'!$D$7:$D$131,0)),"") -> A soft and stylish set for relaxing at home. | F40: =IFERROR(INDEX('REFERENCING & DATABASE'!$G$7:$G$131,MATCH($A40,'REFERENCING & DATABASE'!$D$7:$D$131,0)),"") -> Black,Dark Red | G40: =IFERROR(INDEX('REFERENCING & DATABASE'!$H$7:$H$131,MATCH($A40,'REFERENCING & DATABASE'!$D$7:$D$131,0)),"") -> S,L,XL,XXL | H40: =IFERROR(INDEX('REFERENCING & DATABASE'!$A$7:$A$131,MATCH($A40,'REFERENCING & DATABASE'!$D$7:$D$131,0)),"") -> 586 | I40: =H40-SUM($K40,$M40,$O40,$Q40) -> 576 | J40: =ROUND((($K40/$H40)*100),3) -> 1.706 | K40: =SUMIFS('IN STORE SALES RECORD'!$E$6:$E$97,'IN STORE SALES RECORD'!$A$6:$A$97, "WEEK 1",'IN STORE SALES RECORD'!$D$6:$D$97,'WHS STK MGT & ALLOC.'!$A40)+10 -> 10 | L40: =ROUND(($M40/($H40-$K40))*100,3) -> 0 | M40: =SUMIFS('IN STORE SALES RECORD'!$E$6:$E$97,'IN STORE SALES RECORD'!$A$6:$A$97, "WEEK 6",'IN STORE SALES RECORD'!$D$6:$D$97,'WHS STK MGT & ALLOC.'!$A40) -> 0 | N40: =ROUND(($O40/($H40-($M40+$K40))*100),3) -> 0 | O40: =SUMIFS('IN STORE SALES RECORD'!$E$6:$E$97,'IN STORE SALES RECORD'!$A$6:$A$97, "WEEK 6",'IN STORE SALES RECORD'!$D$6:$D$97,'WHS STK MGT & ALLOC.'!$A40) -> 0 | P40: =ROUND(($Q40/($H40-($M40+$K40+$O40))*100),3) -> 0 | Q40: =SUMIFS('IN STORE SALES RECORD'!$E$6:$E$97,'IN STORE SALES RECORD'!$A$6:$A$97, "WEEK 6",'IN STORE SALES RECORD'!$D$6:$D$97,'WHS STK MGT & ALLOC.'!$A40) -> 0 | R40: =ROUND(($S40/($H40-($M40+$K40+$O40+$Q40))*100),3) -> 0 | S40: =SUMIFS('IN STORE SALES RECORD'!$E$6:$E$97,'IN STORE SALES RECORD'!$A$6:$A$97, "WEEK 6",'IN STORE SALES RECORD'!$D$6:$D$97,'WHS STK MGT & ALLOC.'!$A40) -> 0 | T40: =ROUND(($U40/($H40-($M40+$K40+$O40+$Q40+$S40))*100),3) -> 0 | U40: =SUMIFS('IN STORE SALES RECORD'!$E$6:$E$97,'IN STORE SALES RECORD'!$A$6:$A$97, "WEEK 6",'IN STORE SALES RECORD'!$D$6:$D$97,'WHS STK MGT & ALLOC.'!$A40) -> 0 | V40: =ROUND(($W40/($H40-($M40+$K40+$O40+$Q40+$S40+$U40))*100),3) -> 0 | W40: =SUMIFS('IN STORE SALES RECORD'!$E$6:$E$97,'IN STORE SALES RECORD'!$A$6:$A$97, "WEEK 6",'IN STORE SALES RECORD'!$D$6:$D$97,'WHS STK MGT & ALLOC.'!$A40) -> 0 | X40: =ROUND(($Y40/($H40-($M40+$K40+$O40+$Q40+$S40+$U40+$W40))*100),3) -> 0 | Y40: =SUMIFS('IN STORE SALES RECORD'!$E$6:$E$97,'IN STORE SALES RECORD'!$A$6:$A$97, "WEEK 6",'IN STORE SALES RECORD'!$D$6:$D$97,'WHS STK MGT & ALLOC.'!$A40) -> 0
A41: SL-LO-FL-BL-S | B41: =IFERROR(INDEX('REFERENCING & DATABASE'!$E$7:$E$131,MATCH($A41,'REFERENCING & DATABASE'!$D$7:$D$131,0)),"") -> Fleece Robe | C41: =IFERROR(INDEX('REFERENCING & DATABASE'!$B$7:$B$131,MATCH($A41,'REFERENCING & DATABASE'!$D$7:$D$131,0)),"") -> SLEEPWEAR | D41: =IFERROR(INDEX('REFERENCING & DATABASE'!$C$7:$C$131,MATCH($A41,'REFERENCING & DATABASE'!$D$7:$D$131,0)),"") -> LOUNGEWEAR | E41: =IFERROR(INDEX('REFERENCING & DATABASE'!$F$7:$F$131,MATCH($A41,'REFERENCING & DATABASE'!$D$7:$D$131,0)),"") -> A warm and cozy robe perfect for mornings or evenings. | F41: =IFERROR(INDEX('REFERENCING & DATABASE'!$G$7:$G$131,MATCH($A41,'REFERENCING & DATABASE'!$D$7:$D$131,0)),"") -> Black | G41: =IFERROR(INDEX('REFERENCING & DATABASE'!$H$7:$H$131,MATCH($A41,'REFERENCING & DATABASE'!$D$7:$D$131,0)),"") -> S,L,XL,XXL | H41: =IFERROR(INDEX('REFERENCING & DATABASE'!$A$7:$A$131,MATCH($A41,'REFERENCING & DATABASE'!$D$7:$D$131,0)),"") -> 529 | I41: =H41-SUM($K41,$M41,$O41,$Q41) -> 519 | J41: =ROUND((($K41/$H41)*100),3) -> 1.89 | K41: =SUMIFS('IN STORE SALES RECORD'!$E$6:$E$97,'IN STORE SALES RECORD'!$A$6:$A$97, "WEEK 1",'IN STORE SALES RECORD'!$D$6:$D$97,'WHS STK MGT & ALLOC.'!$A41)+10 -> 10 | L41: =ROUND(($M41/($H41-$K41))*100,3) -> 0 | M41: =SUMIFS('IN STORE SALES RECORD'!$E$6:$E$97,'IN STORE SALES RECORD'!$A$6:$A$97, "WEEK 6",'IN STORE SALES RECORD'!$D$6:$D$97,'WHS STK MGT & ALLOC.'!$A41) -> 0 | N41: =ROUND(($O41/($H41-($M41+$K41))*100),3) -> 0 | O41: =SUMIFS('IN STORE SALES RECORD'!$E$6:$E$97,'IN STORE SALES RECORD'!$A$6:$A$97, "WEEK 6",'IN STORE SALES RECORD'!$D$6:$D$97,'WHS STK MGT & ALLOC.'!$A41) -> 0 | P41: =ROUND(($Q41/($H41-($M41+$K41+$O41))*100),3) -> 0 | Q41: =SUMIFS('IN STORE SALES RECORD'!$E$6:$E$97,'IN STORE SALES RECORD'!$A$6:$A$97, "WEEK 6",'IN STORE SALES RECORD'!$D$6:$D$97,'WHS STK MGT & ALLOC.'!$A41) -> 0 | R41: =ROUND(($S41/($H41-($M41+$K41+$O41+$Q41))*100),3) -> 0 | S41: =SUMIFS('IN STORE SALES RECORD'!$E$6:$E$97,'IN STORE SALES RECORD'!$A$6:$A$97, "WEEK 6",'IN STORE SALES RECORD'!$D$6:$D$97,'WHS STK MGT & ALLOC.'!$A41) -> 0 | T41: =ROUND(($U41/($H41-($M41+$K41+$O41+$Q41+$S41))*100),3) -> 0 | U41: =SUMIFS('IN STORE SALES RECORD'!$E$6:$E$97,'IN STORE SALES RECORD'!$A$6:$A$97, "WEEK 6",'IN STORE SALES RECORD'!$D$6:$D$97,'WHS STK MGT & ALLOC.'!$A41) -> 0 | V41: =ROUND(($W41/($H41-($M41+$K41+$O41+$Q41+$S41+$U41))*100),3) -> 0 | W41: =SUMIFS('IN STORE SALES RECORD'!$E$6:$E$97,'IN STORE SALES RECORD'!$A$6:$A$97, "WEEK 6",'IN STORE SALES RECORD'!$D$6:$D$97,'WHS STK MGT & ALLOC.'!$A41) -> 0 | X41: =ROUND(($Y41/($H41-($M41+$K41+$O41+$Q41+$S41+$U41+$W41))*100),3) -> 0 | Y41: =SUMIFS('IN STORE SALES RECORD'!$E$6:$E$97,'IN STORE SALES RECORD'!$A$6:$A$97, "WEEK 6",'IN STORE SALES RECORD'!$D$6:$D$97,'WHS STK MGT & ALLOC.'!$A41) -> 0
A42: SL-LO-ME-BL-1 | B42: =IFERROR(INDEX('REFERENCING & DATABASE'!$E$7:$E$131,MATCH($A42,'REFERENCING & DATABASE'!$D$7:$D$131,0)),"") -> Memory Foam Slippers | C42: =IFERROR(INDEX('REFERENCING & DATABASE'!$B$7:$B$131,MATCH($A42,'REFERENCING & DATABASE'!$D$7:$D$131,0)),"") -> SLEEPWEAR | D42: =IFERROR(INDEX('REFERENCING & DATABASE'!$C$7:$C$131,MATCH($A42,'REFERENCING & DATABASE'!$D$7:$D$131,0)),"") -> LOUNGEWEAR | E42: =IFERROR(INDEX('REFERENCING & DATABASE'!$F$7:$F$131,MATCH($A42,'REFERENCING & DATABASE'!$D$7:$D$131,0)),"") -> Plush and comfortable slippers for ultimate relaxation. | F42: =IFERROR(INDEX('REFERENCING & DATABASE'!$G$7:$G$131,MATCH($A42,'REFERENCING & DATABASE'!$D$7:$D$131,0)),"") -> Black,Grey | G42: =IFERROR(INDEX('REFERENCING & DATABASE'!$H$7:$H$131,MATCH($A42,'REFERENCING & DATABASE'!$D$7:$D$131,0)),"") -> 10 | H42: =IFERROR(INDEX('REFERENCING & DATABASE'!$A$7:$A$131,MATCH($A42,'REFERENCING & DATABASE'!$D$7:$D$131,0)),"") -> 354 | I42: =H42-SUM($K42,$M42,$O42,$Q42) -> 344 | J42: =ROUND((($K42/$H42)*100),3) -> 2.825 | K42: =SUMIFS('IN STORE SALES RECORD'!$E$6:$E$97,'IN STORE SALES RECORD'!$A$6:$A$97, "WEEK 1",'IN STORE SALES RECORD'!$D$6:$D$97,'WHS STK MGT & ALLOC.'!$A42)+10 -> 10 | L42: =ROUND(($M42/($H42-$K42))*100,3) -> 0 | M42: =SUMIFS('IN STORE SALES RECORD'!$E$6:$E$97,'IN STORE SALES RECORD'!$A$6:$A$97, "WEEK 6",'IN STORE SALES RECORD'!$D$6:$D$97,'WHS STK MGT & ALLOC.'!$A42) -> 0 | N42: =ROUND(($O42/($H42-($M42+$K42))*100),3) -> 0 | O42: =SUMIFS('IN STORE SALES RECORD'!$E$6:$E$97,'IN STORE SALES RECORD'!$A$6:$A$97, "WEEK 6",'IN STORE SALES RECORD'!$D$6:$D$97,'WHS STK MGT & ALLOC.'!$A42) -> 0 | P42: =ROUND(($Q42/($H42-($M42+$K42+$O42))*100),3) -> 0 | Q42: =SUMIFS('IN STORE SALES RECORD'!$E$6:$E$97,'IN STORE SALES RECORD'!$A$6:$A$97, "WEEK 6",'IN STORE SALES RECORD'!$D$6:$D$97,'WHS STK MGT & ALLOC.'!$A42) -> 0 | R42: =ROUND(($S42/($H42-($M42+$K42+$O42+$Q42))*100),3) -> 0 | S42: =SUMIFS('IN STORE SALES RECORD'!$E$6:$E$97,'IN STORE SALES RECORD'!$A$6:$A$97, "WEEK 6",'IN STORE SALES RECORD'!$D$6:$D$97,'WHS STK MGT & ALLOC.'!$A42) -> 0 | T42: =ROUND(($U42/($H42-($M42+$K42+$O42+$Q42+$S42))*100),3) -> 0 | U42: =SUMIFS('IN STORE SALES RECORD'!$E$6:$E$97,'IN STORE SALES RECORD'!$A$6:$A$97, "WEEK 6",'IN STORE SALES RECORD'!$D$6:$D$97,'WHS STK MGT & ALLOC.'!$A42) -> 0 | V42: =ROUND(($W42/($H42-($M42+$K42+$O42+$Q42+$S42+$U42))*100),3) -> 0 | W42: =SUMIFS('IN STORE SALES RECORD'!$E$6:$E$97,'IN STORE SALES RECORD'!$A$6:$A$97, "WEEK 6",'IN STORE SALES RECORD'!$D$6:$D$97,'WHS STK MGT & ALLOC.'!$A42) -> 0 | X42: =ROUND(($Y42/($H42-($M42+$K42+$O42+$Q42+$S42+$U42+$W42))*100),3) -> 0 | Y42: =SUMIFS('IN STORE SALES RECORD'!$E$6:$E$97,'IN STORE SALES RECORD'!$A$6:$A$97, "WEEK 6",'IN STORE SALES RECORD'!$D$6:$D$97,'WHS STK MGT & ALLOC.'!$A42) -> 0
A43: SL-UN-SU-MU-L | B43: =IFERROR(INDEX('REFERENCING & DATABASE'!$E$7:$E$131,MATCH($A43,'REFERENCING & DATABASE'!$D$7:$D$131,0)),"") -> Supportive Sleep Bra | C43: =IFERROR(INDEX('REFERENCING & DATABASE'!$B$7:$B$131,MATCH($A43,'REFERENCING & DATABASE'!$D$7:$D$131,0)),"") -> SLEEPWEAR | D43: =IFERROR(INDEX('REFERENCING & DATABASE'!$C$7:$C$131,MATCH($A43,'REFERENCING & DATABASE'!$D$7:$D$131,0)),"") -> UNDERWEAR | E43: =IFERROR(INDEX('REFERENCING & DATABASE'!$F$7:$F$131,MATCH($A43,'REFERENCING & DATABASE'!$D$7:$D$131,0)),"") -> Supportive Sleep Bra: Provides gentle support and comfort while sleeping. | F43: =IFERROR(INDEX('REFERENCING & DATABASE'!$G$7:$G$131,MATCH($A43,'REFERENCING & DATABASE'!$D$7:$D$131,0)),"") -> Multi-colors | G43: =IFERROR(INDEX('REFERENCING & DATABASE'!$H$7:$H$131,MATCH($A43,'REFERENCING & DATABASE'!$D$7:$D$131,0)),"") -> L,XL | H43: =IFERROR(INDEX('REFERENCING & DATABASE'!$A$7:$A$131,MATCH($A43,'REFERENCING & DATABASE'!$D$7:$D$131,0)),"") -> 435 | I43: =H43-SUM($K43,$M43,$O43,$Q43) -> 425 | J43: =ROUND((($K43/$H43)*100),3) -> 2.299 | K43: =SUMIFS('IN STORE SALES RECORD'!$E$6:$E$97,'IN STORE SALES RECORD'!$A$6:$A$97, "WEEK 1",'IN STORE SALES RECORD'!$D$6:$D$97,'WHS STK MGT & ALLOC.'!$A43)+10 -> 10 | L43: =ROUND(($M43/($H43-$K43))*100,3) -> 0 | M43: =SUMIFS('IN STORE SALES RECORD'!$E$6:$E$97,'IN STORE SALES RECORD'!$A$6:$A$97, "WEEK 6",'IN STORE SALES RECORD'!$D$6:$D$97,'WHS STK MGT & ALLOC.'!$A43) -> 0 | N43: =ROUND(($O43/($H43-($M43+$K43))*100),3) -> 0 | O43: =SUMIFS('IN STORE SALES RECORD'!$E$6:$E$97,'IN STORE SALES RECORD'!$A$6:$A$97, "WEEK 6",'IN STORE SALES RECORD'!$D$6:$D$97,'WHS STK MGT & ALLOC.'!$A43) -> 0 | P43: =ROUND(($Q43/($H43-($M43+$K43+$O43))*100),3) -> 0 | Q43: =SUMIFS('IN STORE SALES RECORD'!$E$6:$E$97,'IN STORE SALES RECORD'!$A$6:$A$97, "WEEK 6",'IN STORE SALES RECORD'!$D$6:$D$97,'WHS STK MGT & ALLOC.'!$A43) -> 0 | R43: =ROUND(($S43/($H43-($M43+$K43+$O43+$Q43))*100),3) -> 0 | S43: =SUMIFS('IN STORE SALES RECORD'!$E$6:$E$97,'IN STORE SALES RECORD'!$A$6:$A$97, "WEEK 6",'IN STORE SALES RECORD'!$D$6:$D$97,'WHS STK MGT & ALLOC.'!$A43) -> 0 | T43: =ROUND(($U43/($H43-($M43+$K43+$O43+$Q43+$S43))*100),3) -> 0 | U43: =SUMIFS('IN STORE SALES RECORD'!$E$6:$E$97,'IN STORE SALES RECORD'!$A$6:$A$97, "WEEK 6",'IN STORE SALES RECORD'!$D$6:$D$97,'WHS STK MGT & ALLOC.'!$A43) -> 0 | V43: =ROUND(($W43/($H43-($M43+$K43+$O43+$Q43+$S43+$U43))*100),3) -> 0 | W43: =SUMIFS('IN STORE SALES RECORD'!$E$6:$E$97,'IN STORE SALES RECORD'!$A$6:$A$97, "WEEK 6",'IN STORE SALES RECORD'!$D$6:$D$97,'WHS STK MGT & ALLOC.'!$A43) -> 0 | X43: =ROUND(($Y43/($H43-($M43+$K43+$O43+$Q43+$S43+$U43+$W43))*100),3) -> 0 | Y43: =SUMIFS('IN STORE SALES RECORD'!$E$6:$E$97,'IN STORE SALES RECORD'!$A$6:$A$97, "WEEK 6",'IN STORE SALES RECORD'!$D$6:$D$97,'WHS STK MGT & ALLOC.'!$A43) -> 0
A44: SL-UN-SO-MU-L | B44: =IFERROR(INDEX('REFERENCING & DATABASE'!$E$7:$E$131,MATCH($A44,'REFERENCING & DATABASE'!$D$7:$D$131,0)),"") -> Soft Modal Sleep Shorts | C44: =IFERROR(INDEX('REFERENCING & DATABASE'!$B$7:$B$131,MATCH($A44,'REFERENCING & DATABASE'!$D$7:$D$131,0)),"") -> SLEEPWEAR | D44: =IFERROR(INDEX('REFERENCING & DATABASE'!$C$7:$C$131,MATCH($A44,'REFERENCING & DATABASE'!$D$7:$D$131,0)),"") -> UNDERWEAR | E44: =IFERROR(INDEX('REFERENCING & DATABASE'!$F$7:$F$131,MATCH($A44,'REFERENCING & DATABASE'!$D$7:$D$131,0)),"") -> Breathable and lightweight shorts for a comfortable night's sleep. | F44: =IFERROR(INDEX('REFERENCING & DATABASE'!$G$7:$G$131,MATCH($A44,'REFERENCING & DATABASE'!$D$7:$D$131,0)),"") -> Multi-colors | G44: =IFERROR(INDEX('REFERENCING & DATABASE'!$H$7:$H$131,MATCH($A44,'REFERENCING & DATABASE'!$D$7:$D$131,0)),"") -> L,XL,XXL | H44: =IFERROR(INDEX('REFERENCING & DATABASE'!$A$7:$A$131,MATCH($A44,'REFERENCING & DATABASE'!$D$7:$D$131,0)),"") -> 175 | I44: =H44-SUM($K44,$M44,$O44,$Q44) -> 165 | J44: =ROUND((($K44/$H44)*100),3) -> 5.714 | K44: =SUMIFS('IN STORE SALES RECORD'!$E$6:$E$97,'IN STORE SALES RECORD'!$A$6:$A$97, "WEEK 1",'IN STORE SALES RECORD'!$D$6:$D$97,'WHS STK MGT & ALLOC.'!$A44)+10 -> 10 | L44: =ROUND(($M44/($H44-$K44))*100,3) -> 0 | M44: =SUMIFS('IN STORE SALES RECORD'!$E$6:$E$97,'IN STORE SALES RECORD'!$A$6:$A$97, "WEEK 6",'IN STORE SALES RECORD'!$D$6:$D$97,'WHS STK MGT & ALLOC.'!$A44) -> 0 | N44: =ROUND(($O44/($H44-($M44+$K44))*100),3) -> 0 | O44: =SUMIFS('IN STORE SALES RECORD'!$E$6:$E$97,'IN STORE SALES RECORD'!$A$6:$A$97, "WEEK 6",'IN STORE SALES RECORD'!$D$6:$D$97,'WHS STK MGT & ALLOC.'!$A44) -> 0 | P44: =ROUND(($Q44/($H44-($M44+$K44+$O44))*100),3) -> 0 | Q44: =SUMIFS('IN STORE SALES RECORD'!$E$6:$E$97,'IN STORE SALES RECORD'!$A$6:$A$97, "WEEK 6",'IN STORE SALES RECORD'!$D$6:$D$97,'WHS STK MGT & ALLOC.'!$A44) -> 0 | R44: =ROUND(($S44/($H44-($M44+$K44+$O44+$Q44))*100),3) -> 0 | S44: =SUMIFS('IN STORE SALES RECORD'!$E$6:$E$97,'IN STORE SALES RECORD'!$A$6:$A$97, "WEEK 6",'IN STORE SALES RECORD'!$D$6:$D$97,'WHS STK MGT & ALLOC.'!$A44) -> 0 | T44: =ROUND(($U44/($H44-($M44+$K44+$O44+$Q44+$S44))*100),3) -> 0 | U44: =SUMIFS('IN STORE SALES RECORD'!$E$6:$E$97,'IN STORE SALES RECORD'!$A$6:$A$97, "WEEK 6",'IN STORE SALES RECORD'!$D$6:$D$97,'WHS STK MGT & ALLOC.'!$A44) -> 0 | V44: =ROUND(($W44/($H44-($M44+$K44+$O44+$Q44+$S44+$U44))*100),3) -> 0 | W44: =SUMIFS('IN STORE SALES RECORD'!$E$6:$E$97,'IN STORE SALES RECORD'!$A$6:$A$97, "WEEK 6",'IN STORE SALES RECORD'!$D$6:$D$97,'WHS STK MGT & ALLOC.'!$A44) -> 0 | X44: =ROUND(($Y44/($H44-($M44+$K44+$O44+$Q44+$S44+$U44+$W44))*100),3) -> 0 | Y44: =SUMIFS('IN STORE SALES RECORD'!$E$6:$E$97,'IN STORE SALES RECORD'!$A$6:$A$97, "WEEK 6",'IN STORE SALES RECORD'!$D$6:$D$97,'WHS STK MGT & ALLOC.'!$A44) -> 0
A45: SL-UN-RE-MU-L | B45: =IFERROR(INDEX('REFERENCING & DATABASE'!$E$7:$E$131,MATCH($A45,'REFERENCING & DATABASE'!$D$7:$D$131,0)),"") -> Relaxed-Fit Sleep Shirt | C45: =IFERROR(INDEX('REFERENCING & DATABASE'!$B$7:$B$131,MATCH($A45,'REFERENCING & DATABASE'!$D$7:$D$131,0)),"") -> SLEEPWEAR | D45: =IFERROR(INDEX('REFERENCING & DATABASE'!$C$7:$C$131,MATCH($A45,'REFERENCING & DATABASE'!$D$7:$D$131,0)),"") -> UNDERWEAR | E45: =IFERROR(INDEX('REFERENCING & DATABASE'!$F$7:$F$131,MATCH($A45,'REFERENCING & DATABASE'!$D$7:$D$131,0)),"") -> A comfortable and loose-fitting top for added comfort. | F45: =IFERROR(INDEX('REFERENCING & DATABASE'!$G$7:$G$131,MATCH($A45,'REFERENCING & DATABASE'!$D$7:$D$131,0)),"") -> Multi-colors | G45: =IFERROR(INDEX('REFERENCING & DATABASE'!$H$7:$H$131,MATCH($A45,'REFERENCING & DATABASE'!$D$7:$D$131,0)),"") -> L,XL,XXL | H45: =IFERROR(INDEX('REFERENCING & DATABASE'!$A$7:$A$131,MATCH($A45,'REFERENCING & DATABASE'!$D$7:$D$131,0)),"") -> 476 | I45: =H45-SUM($K45,$M45,$O45,$Q45) -> 466 | J45: =ROUND((($K45/$H45)*100),3) -> 2.101 | K45: =SUMIFS('IN STORE SALES RECORD'!$E$6:$E$97,'IN STORE SALES RECORD'!$A$6:$A$97, "WEEK 1",'IN STORE SALES RECORD'!$D$6:$D$97,'WHS STK MGT & ALLOC.'!$A45)+10 -> 10 | L45: =ROUND(($M45/($H45-$K45))*100,3) -> 0 | M45: =SUMIFS('IN STORE SALES RECORD'!$E$6:$E$97,'IN STORE SALES RECORD'!$A$6:$A$97, "WEEK 6",'IN STORE SALES RECORD'!$D$6:$D$97,'WHS STK MGT & ALLOC.'!$A45) -> 0 | N45: =ROUND(($O45/($H45-($M45+$K45))*100),3) -> 0 | O45: =SUMIFS('IN STORE SALES RECORD'!$E$6:$E$97,'IN STORE SALES RECORD'!$A$6:$A$97, "WEEK 6",'IN STORE SALES RECORD'!$D$6:$D$97,'WHS STK MGT & ALLOC.'!$A45) -> 0 | P45: =ROUND(($Q45/($H45-($M45+$K45+$O45))*100),3) -> 0 | Q45: =SUMIFS('IN STORE SALES RECORD'!$E$6:$E$97,'IN STORE SALES RECORD'!$A$6:$A$97, "WEEK 6",'IN STORE SALES RECORD'!$D$6:$D$97,'WHS STK MGT & ALLOC.'!$A45) -> 0 | R45: =ROUND(($S45/($H45-($M45+$K45+$O45+$Q45))*100),3) -> 0 | S45: =SUMIFS('IN STORE SALES RECORD'!$E$6:$E$97,'IN STORE SALES RECORD'!$A$6:$A$97, "WEEK 6",'IN STORE SALES RECORD'!$D$6:$D$97,'WHS STK MGT & ALLOC.'!$A45) -> 0 | T45: =ROUND(($U45/($H45-($M45+$K45+$O45+$Q45+$S45))*100),3) -> 0 | U45: =SUMIFS('IN STORE SALES RECORD'!$E$6:$E$97,'IN STORE SALES RECORD'!$A$6:$A$97, "WEEK 6",'IN STORE SALES RECORD'!$D$6:$D$97,'WHS STK MGT & ALLOC.'!$A45) -> 0 | V45: =ROUND(($W45/($H45-($M45+$K45+$O45+$Q45+$S45+$U45))*100),3) -> 0 | W45: =SUMIFS('IN STORE SALES RECORD'!$E$6:$E$97,'IN STORE SALES RECORD'!$A$6:$A$97, "WEEK 6",'IN STORE SALES RECORD'!$D$6:$D$97,'WHS STK MGT & ALLOC.'!$A45) -> 0 | X45: =ROUND(($Y45/($H45-($M45+$K45+$O45+$Q45+$S45+$U45+$W45))*100),3) -> 0 | Y45: =SUMIFS('IN STORE SALES RECORD'!$E$6:$E$97,'IN STORE SALES RECORD'!$A$6:$A$97, "WEEK 6",'IN STORE SALES RECORD'!$D$6:$D$97,'WHS STK MGT & ALLOC.'!$A45) -> 0
A49: =A$6 -> REFERENCE | B49: =B$6 -> PRODUCT NAME | C49: =C$6 -> CATEGORY | D49: =D$6 -> SUB-CATEGORY | E49: =E$6 -> DESCRIPTION | F49: =F$6 -> COLOUR | G49: =G$6 -> SIZE | H49: =H$6 -> TOTAL STOCK | ... Q49: =Q$6 -> 4TH WEEK | R49: 5TH WEEK % ALLOCATION | S49: 5TH WEEK | T49: 6TH WEEK % ALLOCATION | U49: 6TH WEEK | V49: 7TH WEEK % ALLOCATION | W49: 7TH WEEK | X49: 8TH WEEK % ALLOCATION | Y49: 8TH WEEK
A50: AC-BA-SP-RE-M | B50: =IFERROR(INDEX('REFERENCING & DATABASE'!$E$7:$E$131,MATCH($A50,'REFERENCING & DATABASE'!$D$7:$D$131,0)),"") -> Spacious Tote Bag | C50: =IFERROR(INDEX('REFERENCING & DATABASE'!$B$7:$B$131,MATCH($A50,'REFERENCING & DATABASE'!$D$7:$D$131,0)),"") -> ACCESSORIES | D50: =IFERROR(INDEX('REFERENCING & DATABASE'!$C$7:$C$131,MATCH($A50,'REFERENCING & DATABASE'!$D$7:$D$131,0)),"") -> BAGS | E50: =IFERROR(INDEX('REFERENCING & DATABASE'!$F$7:$F$131,MATCH($A50,'REFERENCING & DATABASE'!$D$7:$D$131,0)),"") -> Spacious Tote Bag: Perfect for carrying everyday essentials or larger items. | F50: =IFERROR(INDEX('REFERENCING & DATABASE'!$G$7:$G$131,MATCH($A50,'REFERENCING & DATABASE'!$D$7:$D$131,0)),"Not Available") -> red, yellow, brown, nude, pink, white, blue, green | G50: =IFERROR(INDEX('REFERENCING & DATABASE'!$H$7:$H$131,MATCH($A50,'REFERENCING & DATABASE'!$D$7:$D$131,0)),"") -> M | H50: =IFERROR(INDEX('REFERENCING & DATABASE'!$A$7:$A$131,MATCH($A50,'REFERENCING & DATABASE'!$D$7:$D$131,0)),"") -> 656 | I50: =H50-SUM($K50,$M50,$O50,$Q50) -> 646 | J50: =ROUND((($K50/$H50)*100),3) -> 1.524 | K50: =SUMIFS('IN STORE SALES RECORD'!$E$6:$E$97,'IN STORE SALES RECORD'!$A$6:$A$97, "WEEK 1",'IN STORE SALES RECORD'!$D$6:$D$97,'WHS STK MGT & ALLOC.'!$A50)+10 -> 10 | L50: =ROUND(($M50/($H50-$K50))*100,3) -> 0 | M50: =SUMIFS('IN STORE SALES RECORD'!$E$6:$E$97,'IN STORE SALES RECORD'!$A$6:$A$97, "WEEK 6",'IN STORE SALES RECORD'!$D$6:$D$97,'WHS STK MGT & ALLOC.'!$A50) -> 0 | N50: =ROUND(($O50/($H50-($M50+$K50))*100),3) -> 0 | O50: =SUMIFS('IN STORE SALES RECORD'!$E$6:$E$97,'IN STORE SALES RECORD'!$A$6:$A$97, "WEEK 6",'IN STORE SALES RECORD'!$D$6:$D$97,'WHS STK MGT & ALLOC.'!$A50) -> 0 | P50: =ROUND(($Q50/($H50-($M50+$K50+$O50))*100),3) -> 0 | Q50: =SUMIFS('IN STORE SALES RECORD'!$E$6:$E$97,'IN STORE SALES RECORD'!$A$6:$A$97, "WEEK 6",'IN STORE SALES RECORD'!$D$6:$D$97,'WHS STK MGT & ALLOC.'!$A50) -> 0 | R50: =ROUND(($S50/($H50-($M50+$K50+$O50+$Q50))*100),3) -> 0 | S50: =SUMIFS('IN STORE SALES RECORD'!$E$6:$E$97,'IN STORE SALES RECORD'!$A$6:$A$97, "WEEK 6",'IN STORE SALES RECORD'!$D$6:$D$97,'WHS STK MGT & ALLOC.'!$A50) -> 0 | T50: =ROUND(($U50/($H50-($M50+$K50+$O50+$Q50+$S50))*100),3) -> 0 | U50: =SUMIFS('IN STORE SALES RECORD'!$E$6:$E$97,'IN STORE SALES RECORD'!$A$6:$A$97, "WEEK 6",'IN STORE SALES RECORD'!$D$6:$D$97,'WHS STK MGT & ALLOC.'!$A50) -> 0 | V50: =ROUND(($W50/($H50-($M50+$K50+$O50+$Q50+$S50+$U50))*100),3) -> 0 | W50: =SUMIFS('IN STORE SALES RECORD'!$E$6:$E$97,'IN STORE SALES RECORD'!$A$6:$A$97, "WEEK 6",'IN STORE SALES RECORD'!$D$6:$D$97,'WHS STK MGT & ALLOC.'!$A50) -> 0 | X50: =ROUND(($Y50/($H50-($M50+$K50+$O50+$Q50+$S50+$U50+$W50))*100),3) -> 0 | Y50: =SUMIFS('IN STORE SALES RECORD'!$E$6:$E$97,'IN STORE SALES RECORD'!$A$6:$A$97, "WEEK 6",'IN STORE SALES RECORD'!$D$6:$D$97,'WHS STK MGT & ALLOC.'!$A50) -> 0
A51: AC-BA-FU-BL-M | B51: =IFERROR(INDEX('REFERENCING & DATABASE'!$E$7:$E$131,MATCH($A51,'REFERENCING & DATABASE'!$D$7:$D$131,0)),"") -> Functional Backpack | C51: =IFERROR(INDEX('REFERENCING & DATABASE'!$B$7:$B$131,MATCH($A51,'REFERENCING & DATABASE'!$D$7:$D$131,0)),"") -> ACCESSORIES | D51: =IFERROR(INDEX('REFERENCING & DATABASE'!$C$7:$C$131,MATCH($A51,'REFERENCING & DATABASE'!$D$7:$D$131,0)),"") -> BAGS | E51: =IFERROR(INDEX('REFERENCING & DATABASE'!$F$7:$F$131,MATCH($A51,'REFERENCING & DATABASE'!$D$7:$D$131,0)),"") -> Ideal for carrying school supplies, work essentials, or travel items. | F51: =IFERROR(INDEX('REFERENCING & DATABASE'!$G$7:$G$131,MATCH($A51,'REFERENCING & DATABASE'!$D$7:$D$131,0)),"Not Available") -> Black,nude,red | G51: =IFERROR(INDEX('REFERENCING & DATABASE'!$H$7:$H$131,MATCH($A51,'REFERENCING & DATABASE'!$D$7:$D$131,0)),"") -> M | H51: =IFERROR(INDEX('REFERENCING & DATABASE'!$A$7:$A$131,MATCH($A51,'REFERENCING & DATABASE'!$D$7:$D$131,0)),"") -> 390 | I51: =H51-SUM($K51,$M51,$O51,$Q51) -> 380 | J51: =ROUND((($K51/$H51)*100),3) -> 2.564 | K51: =SUMIFS('IN STORE SALES RECORD'!$E$6:$E$97,'IN STORE SALES RECORD'!$A$6:$A$97, "WEEK 1",'IN STORE SALES RECORD'!$D$6:$D$97,'WHS STK MGT & ALLOC.'!$A51)+10 -> 10 | L51: =ROUND(($M51/($H51-$K51))*100,3) -> 0 | M51: =SUMIFS('IN STORE SALES RECORD'!$E$6:$E$97,'IN STORE SALES RECORD'!$A$6:$A$97, "WEEK 6",'IN STORE SALES RECORD'!$D$6:$D$97,'WHS STK MGT & ALLOC.'!$A51) -> 0 | N51: =ROUND(($O51/($H51-($M51+$K51))*100),3) -> 0 | O51: =SUMIFS('IN STORE SALES RECORD'!$E$6:$E$97,'IN STORE SALES RECORD'!$A$6:$A$97, "WEEK 6",'IN STORE SALES RECORD'!$D$6:$D$97,'WHS STK MGT & ALLOC.'!$A51) -> 0 | P51: =ROUND(($Q51/($H51-($M51+$K51+$O51))*100),3) -> 0 | Q51: =SUMIFS('IN STORE SALES RECORD'!$E$6:$E$97,'IN STORE SALES RECORD'!$A$6:$A$97, "WEEK 6",'IN STORE SALES RECORD'!$D$6:$D$97,'WHS STK MGT & ALLOC.'!$A51) -> 0 | R51: =ROUND(($S51/($H51-($M51+$K51+$O51+$Q51))*100),3) -> 0 | S51: =SUMIFS('IN STORE SALES RECORD'!$E$6:$E$97,'IN STORE SALES RECORD'!$A$6:$A$97, "WEEK 6",'IN STORE SALES RECORD'!$D$6:$D$97,'WHS STK MGT & ALLOC.'!$A51) -> 0 | T51: =ROUND(($U51/($H51-($M51+$K51+$O51+$Q51+$S51))*100),3) -> 0 | U51: =SUMIFS('IN STORE SALES RECORD'!$E$6:$E$97,'IN STORE SALES RECORD'!$A$6:$A$97, "WEEK 6",'IN STORE SALES RECORD'!$D$6:$D$97,'WHS STK MGT & ALLOC.'!$A51) -> 0 | V51: =ROUND(($W51/($H51-($M51+$K51+$O51+$Q51+$S51+$U51))*100),3) -> 0 | W51: =SUMIFS('IN STORE SALES RECORD'!$E$6:$E$97,'IN STORE SALES RECORD'!$A$6:$A$97, "WEEK 6",'IN STORE SALES RECORD'!$D$6:$D$97,'WHS STK MGT & ALLOC.'!$A51) -> 0 | X51: =ROUND(($Y51/($H51-($M51+$K51+$O51+$Q51+$S51+$U51+$W51))*100),3) -> 0 | Y51: =SUMIFS('IN STORE SALES RECORD'!$E$6:$E$97,'IN STORE SALES RECORD'!$A$6:$A$97, "WEEK 6",'IN STORE SALES RECORD'!$D$6:$D$97,'WHS STK MGT & ALLOC.'!$A51) -> 0
A52: AC-BA-SL-RE-M | B52: =IFERROR(INDEX('REFERENCING & DATABASE'!$E$7:$E$131,MATCH($A52,'REFERENCING & DATABASE'!$D$7:$D$131,0)),"") -> Sleek Crossbody Bag | C52: =IFERROR(INDEX('REFERENCING & DATABASE'!$B$7:$B$131,MATCH($A52,'REFERENCING & DATABASE'!$D$7:$D$131,0)),"") -> ACCESSORIES | D52: =IFERROR(INDEX('REFERENCING & DATABASE'!$C$7:$C$131,MATCH($A52,'REFERENCING & DATABASE'!$D$7:$D$131,0)),"") -> BAGS | E52: =IFERROR(INDEX('REFERENCING & DATABASE'!$F$7:$F$131,MATCH($A52,'REFERENCING & DATABASE'!$D$7:$D$131,0)),"") -> A stylish and convenient option for hands-free carrying. | F52: =IFERROR(INDEX('REFERENCING & DATABASE'!$G$7:$G$131,MATCH($A52,'REFERENCING & DATABASE'!$D$7:$D$131,0)),"Not Available") -> red, yellow, brown, nude, pink, white, blue, green | G52: =IFERROR(INDEX('REFERENCING & DATABASE'!$H$7:$H$131,MATCH($A52,'REFERENCING & DATABASE'!$D$7:$D$131,0)),"") -> M | H52: =IFERROR(INDEX('REFERENCING & DATABASE'!$A$7:$A$131,MATCH($A52,'REFERENCING & DATABASE'!$D$7:$D$131,0)),"") -> 707 | I52: =H52-SUM($K52,$M52,$O52,$Q52) -> 617 | J52: =ROUND((($K52/$H52)*100),3) -> 12.73 | K52: =SUMIFS('IN STORE SALES RECORD'!$E$6:$E$97,'IN STORE SALES RECORD'!$A$6:$A$97, "WEEK 1",'IN STORE SALES RECORD'!$D$6:$D$97,'WHS STK MGT & ALLOC.'!$A52)+10 -> 90 | L52: =ROUND(($M52/($H52-$K52))*100,3) -> 0 | M52: =SUMIFS('IN STORE SALES RECORD'!$E$6:$E$97,'IN STORE SALES RECORD'!$A$6:$A$97, "WEEK 6",'IN STORE SALES RECORD'!$D$6:$D$97,'WHS STK MGT & ALLOC.'!$A52) -> 0 | N52: =ROUND(($O52/($H52-($M52+$K52))*100),3) -> 0 | O52: =SUMIFS('IN STORE SALES RECORD'!$E$6:$E$97,'IN STORE SALES RECORD'!$A$6:$A$97, "WEEK 6",'IN STORE SALES RECORD'!$D$6:$D$97,'WHS STK MGT & ALLOC.'!$A52) -> 0 | P52: =ROUND(($Q52/($H52-($M52+$K52+$O52))*100),3) -> 0 | Q52: =SUMIFS('IN STORE SALES RECORD'!$E$6:$E$97,'IN STORE SALES RECORD'!$A$6:$A$97, "WEEK 6",'IN STORE SALES RECORD'!$D$6:$D$97,'WHS STK MGT & ALLOC.'!$A52) -> 0 | R52: =ROUND(($S52/($H52-($M52+$K52+$O52+$Q52))*100),3) -> 0 | S52: =SUMIFS('IN STORE SALES RECORD'!$E$6:$E$97,'IN STORE SALES RECORD'!$A$6:$A$97, "WEEK 6",'IN STORE SALES RECORD'!$D$6:$D$97,'WHS STK MGT & ALLOC.'!$A52) -> 0 | T52: =ROUND(($U52/($H52-($M52+$K52+$O52+$Q52+$S52))*100),3) -> 0 | U52: =SUMIFS('IN STORE SALES RECORD'!$E$6:$E$97,'IN STORE SALES RECORD'!$A$6:$A$97, "WEEK 6",'IN STORE SALES RECORD'!$D$6:$D$97,'WHS STK MGT & ALLOC.'!$A52) -> 0 | V52: =ROUND(($W52/($H52-($M52+$K52+$O52+$Q52+$S52+$U52))*100),3) -> 0 | W52: =SUMIFS('IN STORE SALES RECORD'!$E$6:$E$97,'IN STORE SALES RECORD'!$A$6:$A$97, "WEEK 6",'IN STORE SALES RECORD'!$D$6:$D$97,'WHS STK MGT & ALLOC.'!$A52) -> 0 | X52: =ROUND(($Y52/($H52-($M52+$K52+$O52+$Q52+$S52+$U52+$W52))*100),3) -> 0 | Y52: =SUMIFS('IN STORE SALES RECORD'!$E$6:$E$97,'IN STORE SALES RECORD'!$A$6:$A$97, "WEEK 6",'IN STORE SALES RECORD'!$D$6:$D$97,'WHS STK MGT & ALLOC.'!$A52) -> 0
A53: AC-BA-EL-RE-M | B53: =IFERROR(INDEX('REFERENCING & DATABASE'!$E$7:$E$131,MATCH($A53,'REFERENCING & DATABASE'!$D$7:$D$131,0)),"") -> Elegant Clutch | C53: =IFERROR(INDEX('REFERENCING & DATABASE'!$B$7:$B$131,MATCH($A53,'REFERENCING & DATABASE'!$D$7:$D$131,0)),"") -> ACCESSORIES | D53: =IFERROR(INDEX('REFERENCING & DATABASE'!$C$7:$C$131,MATCH($A53,'REFERENCING & DATABASE'!$D$7:$D$131,0)),"") -> BAGS | E53: =IFERROR(INDEX('REFERENCING & DATABASE'!$F$7:$F$131,MATCH($A53,'REFERENCING & DATABASE'!$D$7:$D$131,0)),"") -> A sophisticated and compact bag for formal occasions. | F53: =IFERROR(INDEX('REFERENCING & DATABASE'!$G$7:$G$131,MATCH($A53,'REFERENCING & DATABASE'!$D$7:$D$131,0)),"Not Available") -> red, yellow, brown, nude, pink, white, blue, green | G53: =IFERROR(INDEX('REFERENCING & DATABASE'!$H$7:$H$131,MATCH($A53,'REFERENCING & DATABASE'!$D$7:$D$131,0)),"") -> M | H53: =IFERROR(INDEX('REFERENCING & DATABASE'!$A$7:$A$131,MATCH($A53,'REFERENCING & DATABASE'!$D$7:$D$131,0)),"") -> 343 | I53: =H53-SUM($K53,$M53,$O53,$Q53) -> 333 | J53: =ROUND((($K53/$H53)*100),3) -> 2.915 | K53: =SUMIFS('IN STORE SALES RECORD'!$E$6:$E$97,'IN STORE SALES RECORD'!$A$6:$A$97, "WEEK 1",'IN STORE SALES RECORD'!$D$6:$D$97,'WHS STK MGT & ALLOC.'!$A53)+10 -> 10 | L53: =ROUND(($M53/($H53-$K53))*100,3) -> 0 | M53: =SUMIFS('IN STORE SALES RECORD'!$E$6:$E$97,'IN STORE SALES RECORD'!$A$6:$A$97, "WEEK 6",'IN STORE SALES RECORD'!$D$6:$D$97,'WHS STK MGT & ALLOC.'!$A53) -> 0 | N53: =ROUND(($O53/($H53-($M53+$K53))*100),3) -> 0 | O53: =SUMIFS('IN STORE SALES RECORD'!$E$6:$E$97,'IN STORE SALES RECORD'!$A$6:$A$97, "WEEK 6",'IN STORE SALES RECORD'!$D$6:$D$97,'WHS STK MGT & ALLOC.'!$A53) -> 0 | P53: =ROUND(($Q53/($H53-($M53+$K53+$O53))*100),3) -> 0 | Q53: =SUMIFS('IN STORE SALES RECORD'!$E$6:$E$97,'IN STORE SALES RECORD'!$A$6:$A$97, "WEEK 6",'IN STORE SALES RECORD'!$D$6:$D$97,'WHS STK MGT & ALLOC.'!$A53) -> 0 | R53: =ROUND(($S53/($H53-($M53+$K53+$O53+$Q53))*100),3) -> 0 | S53: =SUMIFS('IN STORE SALES RECORD'!$E$6:$E$97,'IN STORE SALES RECORD'!$A$6:$A$97, "WEEK 6",'IN STORE SALES RECORD'!$D$6:$D$97,'WHS STK MGT & ALLOC.'!$A53) -> 0 | T53: =ROUND(($U53/($H53-($M53+$K53+$O53+$Q53+$S53))*100),3) -> 0 | U53: =SUMIFS('IN STORE SALES RECORD'!$E$6:$E$97,'IN STORE SALES RECORD'!$A$6:$A$97, "WEEK 6",'IN STORE SALES RECORD'!$D$6:$D$97,'WHS STK MGT & ALLOC.'!$A53) -> 0 | V53: =ROUND(($W53/($H53-($M53+$K53+$O53+$Q53+$S53+$U53))*100),3) -> 0 | W53: =SUMIFS('IN STORE SALES RECORD'!$E$6:$E$97,'IN STORE SALES RECORD'!$A$6:$A$97, "WEEK 6",'IN STORE SALES RECORD'!$D$6:$D$97,'WHS STK MGT & ALLOC.'!$A53) -> 0 | X53: =ROUND(($Y53/($H53-($M53+$K53+$O53+$Q53+$S53+$U53+$W53))*100),3) -> 0 | Y53: =SUMIFS('IN STORE SALES RECORD'!$E$6:$E$97,'IN STORE SALES RECORD'!$A$6:$A$97, "WEEK 6",'IN STORE SALES RECORD'!$D$6:$D$97,'WHS STK MGT & ALLOC.'!$A53) -> 0
A54: AC-BA-PR-RE-M | B54: =IFERROR(INDEX('REFERENCING & DATABASE'!$E$7:$E$131,MATCH($A54,'REFERENCING & DATABASE'!$D$7:$D$131,0)),"") -> Professional Briefcase | C54: =IFERROR(INDEX('REFERENCING & DATABASE'!$B$7:$B$131,MATCH($A54,'REFERENCING & DATABASE'!$D$7:$D$131,0)),"") -> ACCESSORIES | D54: =IFERROR(INDEX('REFERENCING & DATABASE'!$C$7:$C$131,MATCH($A54,'REFERENCING & DATABASE'!$D$7:$D$131,0)),"") -> BAGS | E54: =IFERROR(INDEX('REFERENCING & DATABASE'!$F$7:$F$131,MATCH($A54,'REFERENCING & DATABASE'!$D$7:$D$131,0)),"") -> A structured and durable bag for carrying work documents and laptops. | F54: =IFERROR(INDEX('REFERENCING & DATABASE'!$G$7:$G$131,MATCH($A54,'REFERENCING & DATABASE'!$D$7:$D$131,0)),"Not Available") -> red, yellow, brown, nude, pink, white, blue, green | G54: =IFERROR(INDEX('REFERENCING & DATABASE'!$H$7:$H$131,MATCH($A54,'REFERENCING & DATABASE'!$D$7:$D$131,0)),"") -> M | H54: =IFERROR(INDEX('REFERENCING & DATABASE'!$A$7:$A$131,MATCH($A54,'REFERENCING & DATABASE'!$D$7:$D$131,0)),"") -> 345 | I54: =H54-SUM($K54,$M54,$O54,$Q54) -> 335 | J54: =ROUND((($K54/$H54)*100),3) -> 2.899 | K54: =SUMIFS('IN STORE SALES RECORD'!$E$6:$E$97,'IN STORE SALES RECORD'!$A$6:$A$97, "WEEK 1",'IN STORE SALES RECORD'!$D$6:$D$97,'WHS STK MGT & ALLOC.'!$A54)+10 -> 10 | L54: =ROUND(($M54/($H54-$K54))*100,3) -> 0 | M54: =SUMIFS('IN STORE SALES RECORD'!$E$6:$E$97,'IN STORE SALES RECORD'!$A$6:$A$97, "WEEK 6",'IN STORE SALES RECORD'!$D$6:$D$97,'WHS STK MGT & ALLOC.'!$A54) -> 0 | N54: =ROUND(($O54/($H54-($M54+$K54))*100),3) -> 0 | O54: =SUMIFS('IN STORE SALES RECORD'!$E$6:$E$97,'IN STORE SALES RECORD'!$A$6:$A$97, "WEEK 6",'IN STORE SALES RECORD'!$D$6:$D$97,'WHS STK MGT & ALLOC.'!$A54) -> 0 | P54: =ROUND(($Q54/($H54-($M54+$K54+$O54))*100),3) -> 0 | Q54: =SUMIFS('IN STORE SALES RECORD'!$E$6:$E$97,'IN STORE SALES RECORD'!$A$6:$A$97, "WEEK 6",'IN STORE SALES RECORD'!$D$6:$D$97,'WHS STK MGT & ALLOC.'!$A54) -> 0 | R54: =ROUND(($S54/($H54-($M54+$K54+$O54+$Q54))*100),3) -> 0 | S54: =SUMIFS('IN STORE SALES RECORD'!$E$6:$E$97,'IN STORE SALES RECORD'!$A$6:$A$97, "WEEK 6",'IN STORE SALES RECORD'!$D$6:$D$97,'WHS STK MGT & ALLOC.'!$A54) -> 0 | T54: =ROUND(($U54/($H54-($M54+$K54+$O54+$Q54+$S54))*100),3) -> 0 | U54: =SUMIFS('IN STORE SALES RECORD'!$E$6:$E$97,'IN STORE SALES RECORD'!$A$6:$A$97, "WEEK 6",'IN STORE SALES RECORD'!$D$6:$D$97,'WHS STK MGT & ALLOC.'!$A54) -> 0 | V54: =ROUND(($W54/($H54-($M54+$K54+$O54+$Q54+$S54+$U54))*100),3) -> 0 | W54: =SUMIFS('IN STORE SALES RECORD'!$E$6:$E$97,'IN STORE SALES RECORD'!$A$6:$A$97, "WEEK 6",'IN STORE SALES RECORD'!$D$6:$D$97,'WHS STK MGT & ALLOC.'!$A54) -> 0 | X54: =ROUND(($Y54/($H54-($M54+$K54+$O54+$Q54+$S54+$U54+$W54))*100),3) -> 0 | Y54: =SUMIFS('IN STORE SALES RECORD'!$E$6:$E$97,'IN STORE SALES RECORD'!$A$6:$A$97, "WEEK 6",'IN STORE SALES RECORD'!$D$6:$D$97,'WHS STK MGT & ALLOC.'!$A54) -> 0
A55: AC-BE-GE-BL-35 | B55: =IFERROR(INDEX('REFERENCING & DATABASE'!$E$7:$E$131,MATCH($A55,'REFERENCING & DATABASE'!$D$7:$D$131,0)),"") -> Genuine Leather Belt | C55: =IFERROR(INDEX('REFERENCING & DATABASE'!$B$7:$B$131,MATCH($A55,'REFERENCING & DATABASE'!$D$7:$D$131,0)),"") -> ACCESSORIES | D55: =IFERROR(INDEX('REFERENCING & DATABASE'!$C$7:$C$131,MATCH($A55,'REFERENCING & DATABASE'!$D$7:$D$131,0)),"") -> BELTS | E55: =IFERROR(INDEX('REFERENCING & DATABASE'!$F$7:$F$131,MATCH($A55,'REFERENCING & DATABASE'!$D$7:$D$131,0)),"") -> A classic and durable belt for everyday use. | F55: =IFERROR(INDEX('REFERENCING & DATABASE'!$G$7:$G$131,MATCH($A55,'REFERENCING & DATABASE'!$D$7:$D$131,0)),"Not Available") -> Black,Brown | G55: =IFERROR(INDEX('REFERENCING & DATABASE'!$H$7:$H$131,MATCH($A55,'REFERENCING & DATABASE'!$D$7:$D$131,0)),"") -> 35 | H55: =IFERROR(INDEX('REFERENCING & DATABASE'!$A$7:$A$131,MATCH($A55,'REFERENCING & DATABASE'!$D$7:$D$131,0)),"") -> 765 | I55: =H55-SUM($K55,$M55,$O55,$Q55) -> 755 | J55: =ROUND((($K55/$H55)*100),3) -> 1.307 | K55: =SUMIFS('IN STORE SALES RECORD'!$E$6:$E$97,'IN STORE SALES RECORD'!$A$6:$A$97, "WEEK 1",'IN STORE SALES RECORD'!$D$6:$D$97,'WHS STK MGT & ALLOC.'!$A55)+10 -> 10 | L55: =ROUND(($M55/($H55-$K55))*100,3) -> 0 | M55: =SUMIFS('IN STORE SALES RECORD'!$E$6:$E$97,'IN STORE SALES RECORD'!$A$6:$A$97, "WEEK 6",'IN STORE SALES RECORD'!$D$6:$D$97,'WHS STK MGT & ALLOC.'!$A55) -> 0 | N55: =ROUND(($O55/($H55-($M55+$K55))*100),3) -> 0 | O55: =SUMIFS('IN STORE SALES RECORD'!$E$6:$E$97,'IN STORE SALES RECORD'!$A$6:$A$97, "WEEK 6",'IN STORE SALES RECORD'!$D$6:$D$97,'WHS STK MGT & ALLOC.'!$A55) -> 0 | P55: =ROUND(($Q55/($H55-($M55+$K55+$O55))*100),3) -> 0 | Q55: =SUMIFS('IN STORE SALES RECORD'!$E$6:$E$97,'IN STORE SALES RECORD'!$A$6:$A$97, "WEEK 6",'IN STORE SALES RECORD'!$D$6:$D$97,'WHS STK MGT & ALLOC.'!$A55) -> 0 | R55: =ROUND(($S55/($H55-($M55+$K55+$O55+$Q55))*100),3) -> 0 | S55: =SUMIFS('IN STORE SALES RECORD'!$E$6:$E$97,'IN STORE SALES RECORD'!$A$6:$A$97, "WEEK 6",'IN STORE SALES RECORD'!$D$6:$D$97,'WHS STK MGT & ALLOC.'!$A55) -> 0 | T55: =ROUND(($U55/($H55-($M55+$K55+$O55+$Q55+$S55))*100),3) -> 0 | U55: =SUMIFS('IN STORE SALES RECORD'!$E$6:$E$97,'IN STORE SALES RECORD'!$A$6:$A$97, "WEEK 6",'IN STORE SALES RECORD'!$D$6:$D$97,'WHS STK MGT & ALLOC.'!$A55) -> 0 | V55: =ROUND(($W55/($H55-($M55+$K55+$O55+$Q55+$S55+$U55))*100),3) -> 0 | W55: =SUMIFS('IN STORE SALES RECORD'!$E$6:$E$97,'IN STORE SALES RECORD'!$A$6:$A$97, "WEEK 6",'IN STORE SALES RECORD'!$D$6:$D$97,'WHS STK MGT & ALLOC.'!$A55) -> 0 | X55: =ROUND(($Y55/($H55-($M55+$K55+$O55+$Q55+$S55+$U55+$W55))*100),3) -> 0 | Y55: =SUMIFS('IN STORE SALES RECORD'!$E$6:$E$97,'IN STORE SALES RECORD'!$A$6:$A$97, "WEEK 6",'IN STORE SALES RECORD'!$D$6:$D$97,'WHS STK MGT & ALLOC.'!$A55) -> 0
A56: AC-BE-WO-BL-35 | B56: =IFERROR(INDEX('REFERENCING & DATABASE'!$E$7:$E$131,MATCH($A56,'REFERENCING & DATABASE'!$D$7:$D$131,0)),"") -> Woven Canvas Belt | C56: =IFERROR(INDEX('REFERENCING & DATABASE'!$B$7:$B$131,MATCH($A56,'REFERENCING & DATABASE'!$D$7:$D$131,0)),"") -> ACCESSORIES | D56: =IFERROR(INDEX('REFERENCING & DATABASE'!$C$7:$C$131,MATCH($A56,'REFERENCING & DATABASE'!$D$7:$D$131,0)),"") -> BELTS | E56: =IFERROR(INDEX('REFERENCING & DATABASE'!$F$7:$F$131,MATCH($A56,'REFERENCING & DATABASE'!$D$7:$D$131,0)),"") -> A casual and stylish belt perfect for summer outfits. | F56: =IFERROR(INDEX('REFERENCING & DATABASE'!$G$7:$G$131,MATCH($A56,'REFERENCING & DATABASE'!$D$7:$D$131,0)),"Not Available") -> Black,Brown | G56: =IFERROR(INDEX('REFERENCING & DATABASE'!$H$7:$H$131,MATCH($A56,'REFERENCING & DATABASE'!$D$7:$D$131,0)),"") -> 35 | H56: =IFERROR(INDEX('REFERENCING & DATABASE'!$A$7:$A$131,MATCH($A56,'REFERENCING & DATABASE'!$D$7:$D$131,0)),"") -> 445 | I56: =H56-SUM($K56,$M56,$O56,$Q56) -> 435 | J56: =ROUND((($K56/$H56)*100),3) -> 2.247 | K56: =SUMIFS('IN STORE SALES RECORD'!$E$6:$E$97,'IN STORE SALES RECORD'!$A$6:$A$97, "WEEK 1",'IN STORE SALES RECORD'!$D$6:$D$97,'WHS STK MGT & ALLOC.'!$A56)+10 -> 10 | L56: =ROUND(($M56/($H56-$K56))*100,3) -> 0 | M56: =SUMIFS('IN STORE SALES RECORD'!$E$6:$E$97,'IN STORE SALES RECORD'!$A$6:$A$97, "WEEK 6",'IN STORE SALES RECORD'!$D$6:$D$97,'WHS STK MGT & ALLOC.'!$A56) -> 0 | N56: =ROUND(($O56/($H56-($M56+$K56))*100),3) -> 0 | O56: =SUMIFS('IN STORE SALES RECORD'!$E$6:$E$97,'IN STORE SALES RECORD'!$A$6:$A$97, "WEEK 6",'IN STORE SALES RECORD'!$D$6:$D$97,'WHS STK MGT & ALLOC.'!$A56) -> 0 | P56: =ROUND(($Q56/($H56-($M56+$K56+$O56))*100),3) -> 0 | Q56: =SUMIFS('IN STORE SALES RECORD'!$E$6:$E$97,'IN STORE SALES RECORD'!$A$6:$A$97, "WEEK 6",'IN STORE SALES RECORD'!$D$6:$D$97,'WHS STK MGT & ALLOC.'!$A56) -> 0 | R56: =ROUND(($S56/($H56-($M56+$K56+$O56+$Q56))*100),3) -> 0 | S56: =SUMIFS('IN STORE SALES RECORD'!$E$6:$E$97,'IN STORE SALES RECORD'!$A$6:$A$97, "WEEK 6",'IN STORE SALES RECORD'!$D$6:$D$97,'WHS STK MGT & ALLOC.'!$A56) -> 0 | T56: =ROUND(($U56/($H56-($M56+$K56+$O56+$Q56+$S56))*100),3) -> 0 | U56: =SUMIFS('IN STORE SALES RECORD'!$E$6:$E$97,'IN STORE SALES RECORD'!$A$6:$A$97, "WEEK 6",'IN STORE SALES RECORD'!$D$6:$D$97,'WHS STK MGT & ALLOC.'!$A56) -> 0 | V56: =ROUND(($W56/($H56-($M56+$K56+$O56+$Q56+$S56+$U56))*100),3) -> 0 | W56: =SUMIFS('IN STORE SALES RECORD'!$E$6:$E$97,'IN STORE SALES RECORD'!$A$6:$A$97, "WEEK 6",'IN STORE SALES RECORD'!$D$6:$D$97,'WHS STK MGT & ALLOC.'!$A56) -> 0 | X56: =ROUND(($Y56/($H56-($M56+$K56+$O56+$Q56+$S56+$U56+$W56))*100),3) -> 0 | Y56: =SUMIFS('IN STORE SALES RECORD'!$E$6:$E$97,'IN STORE SALES RECORD'!$A$6:$A$97, "WEEK 6",'IN STORE SALES RECORD'!$D$6:$D$97,'WHS STK MGT & ALLOC.'!$A56) -> 0
A57: AC-BE-BR-BL-35 | B57: =IFERROR(INDEX('REFERENCING & DATABASE'!$E$7:$E$131,MATCH($A57,'REFERENCING & DATABASE'!$D$7:$D$131,0)),"") -> Braided Leather Belt | C57: =IFERROR(INDEX('REFERENCING & DATABASE'!$B$7:$B$131,MATCH($A57,'REFERENCING & DATABASE'!$D$7:$D$131,0)),"") -> ACCESSORIES | D57: =IFERROR(INDEX('REFERENCING & DATABASE'!$C$7:$C$131,MATCH($A57,'REFERENCING & DATABASE'!$D$7:$D$131,0)),"") -> BELTS | E57: =IFERROR(INDEX('REFERENCING & DATABASE'!$F$7:$F$131,MATCH($A57,'REFERENCING & DATABASE'!$D$7:$D$131,0)),"") -> Adds a touch of western-inspired style to your look. | F57: =IFERROR(INDEX('REFERENCING & DATABASE'!$G$7:$G$131,MATCH($A57,'REFERENCING & DATABASE'!$D$7:$D$131,0)),"Not Available") -> Black,Brown | G57: =IFERROR(INDEX('REFERENCING & DATABASE'!$H$7:$H$131,MATCH($A57,'REFERENCING & DATABASE'!$D$7:$D$131,0)),"") -> 35 | H57: =IFERROR(INDEX('REFERENCING & DATABASE'!$A$7:$A$131,MATCH($A57,'REFERENCING & DATABASE'!$D$7:$D$131,0)),"") -> 200 | I57: =H57-SUM($K57,$M57,$O57,$Q57) -> 190 | J57: =ROUND((($K57/$H57)*100),3) -> 5 | K57: =SUMIFS('IN STORE SALES RECORD'!$E$6:$E$97,'IN STORE SALES RECORD'!$A$6:$A$97, "WEEK 1",'IN STORE SALES RECORD'!$D$6:$D$97,'WHS STK MGT & ALLOC.'!$A57)+10 -> 10 | L57: =ROUND(($M57/($H57-$K57))*100,3) -> 0 | M57: =SUMIFS('IN STORE SALES RECORD'!$E$6:$E$97,'IN STORE SALES RECORD'!$A$6:$A$97, "WEEK 6",'IN STORE SALES RECORD'!$D$6:$D$97,'WHS STK MGT & ALLOC.'!$A57) -> 0 | N57: =ROUND(($O57/($H57-($M57+$K57))*100),3) -> 0 | O57: =SUMIFS('IN STORE SALES RECORD'!$E$6:$E$97,'IN STORE SALES RECORD'!$A$6:$A$97, "WEEK 6",'IN STORE SALES RECORD'!$D$6:$D$97,'WHS STK MGT & ALLOC.'!$A57) -> 0 | P57: =ROUND(($Q57/($H57-($M57+$K57+$O57))*100),3) -> 0 | Q57: =SUMIFS('IN STORE SALES RECORD'!$E$6:$E$97,'IN STORE SALES RECORD'!$A$6:$A$97, "WEEK 6",'IN STORE SALES RECORD'!$D$6:$D$97,'WHS STK MGT & ALLOC.'!$A57) -> 0 | R57: =ROUND(($S57/($H57-($M57+$K57+$O57+$Q57))*100),3) -> 0 | S57: =SUMIFS('IN STORE SALES RECORD'!$E$6:$E$97,'IN STORE SALES RECORD'!$A$6:$A$97, "WEEK 6",'IN STORE SALES RECORD'!$D$6:$D$97,'WHS STK MGT & ALLOC.'!$A57) -> 0 | T57: =ROUND(($U57/($H57-($M57+$K57+$O57+$Q57+$S57))*100),3) -> 0 | U57: =SUMIFS('IN STORE SALES RECORD'!$E$6:$E$97,'IN STORE SALES RECORD'!$A$6:$A$97, "WEEK 6",'IN STORE SALES RECORD'!$D$6:$D$97,'WHS STK MGT & ALLOC.'!$A57) -> 0 | V57: =ROUND(($W57/($H57-($M57+$K57+$O57+$Q57+$S57+$U57))*100),3) -> 0 | W57: =SUMIFS('IN STORE SALES RECORD'!$E$6:$E$97,'IN STORE SALES RECORD'!$A$6:$A$97, "WEEK 6",'IN STORE SALES RECORD'!$D$6:$D$97,'WHS STK MGT & ALLOC.'!$A57) -> 0 | X57: =ROUND(($Y57/($H57-($M57+$K57+$O57+$Q57+$S57+$U57+$W57))*100),3) -> 0 | Y57: =SUMIFS('IN STORE SALES RECORD'!$E$6:$E$97,'IN STORE SALES RECORD'!$A$6:$A$97, "WEEK 6",'IN STORE SALES RECORD'!$D$6:$D$97,'WHS STK MGT & ALLOC.'!$A57) -> 0
A58: AC-BE-SL-BL-35 | B58: =IFERROR(INDEX('REFERENCING & DATABASE'!$E$7:$E$131,MATCH($A58,'REFERENCING & DATABASE'!$D$7:$D$131,0)),"") -> Slim Dress Belt | C58: =IFERROR(INDEX('REFERENCING & DATABASE'!$B$7:$B$131,MATCH($A58,'REFERENCING & DATABASE'!$D$7:$D$131,0)),"") -> ACCESSORIES | D58: =IFERROR(INDEX('REFERENCING & DATABASE'!$C$7:$C$131,MATCH($A58,'REFERENCING & DATABASE'!$D$7:$D$131,0)),"") -> BELTS | E58: =IFERROR(INDEX('REFERENCING & DATABASE'!$F$7:$F$131,MATCH($A58,'REFERENCING & DATABASE'!$D$7:$D$131,0)),"") -> A polished and sophisticated belt for formal occasions. | F58: =IFERROR(INDEX('REFERENCING & DATABASE'!$G$7:$G$131,MATCH($A58,'REFERENCING & DATABASE'!$D$7:$D$131,0)),"Not Available") -> Black,Brown | G58: =IFERROR(INDEX('REFERENCING & DATABASE'!$H$7:$H$131,MATCH($A58,'REFERENCING & DATABASE'!$D$7:$D$131,0)),"") -> 35 | H58: =IFERROR(INDEX('REFERENCING & DATABASE'!$A$7:$A$131,MATCH($A58,'REFERENCING & DATABASE'!$D$7:$D$131,0)),"") -> 230 | I58: =H58-SUM($K58,$M58,$O58,$Q58) -> 220 | J58: =ROUND((($K58/$H58)*100),3) -> 4.348 | K58: =SUMIFS('IN STORE SALES RECORD'!$E$6:$E$97,'IN STORE SALES RECORD'!$A$6:$A$97, "WEEK 1",'IN STORE SALES RECORD'!$D$6:$D$97,'WHS STK MGT & ALLOC.'!$A58)+10 -> 10 | L58: =ROUND(($M58/($H58-$K58))*100,3) -> 0 | M58: =SUMIFS('IN STORE SALES RECORD'!$E$6:$E$97,'IN STORE SALES RECORD'!$A$6:$A$97, "WEEK 6",'IN STORE SALES RECORD'!$D$6:$D$97,'WHS STK MGT & ALLOC.'!$A58) -> 0 | N58: =ROUND(($O58/($H58-($M58+$K58))*100),3) -> 0 | O58: =SUMIFS('IN STORE SALES RECORD'!$E$6:$E$97,'IN STORE SALES RECORD'!$A$6:$A$97, "WEEK 6",'IN STORE SALES RECORD'!$D$6:$D$97,'WHS STK MGT & ALLOC.'!$A58) -> 0 | P58: =ROUND(($Q58/($H58-($M58+$K58+$O58))*100),3) -> 0 | Q58: =SUMIFS('IN STORE SALES RECORD'!$E$6:$E$97,'IN STORE SALES RECORD'!$A$6:$A$97, "WEEK 6",'IN STORE SALES RECORD'!$D$6:$D$97,'WHS STK MGT & ALLOC.'!$A58) -> 0 | R58: =ROUND(($S58/($H58-($M58+$K58+$O58+$Q58))*100),3) -> 0 | S58: =SUMIFS('IN STORE SALES RECORD'!$E$6:$E$97,'IN STORE SALES RECORD'!$A$6:$A$97, "WEEK 6",'IN STORE SALES RECORD'!$D$6:$D$97,'WHS STK MGT & ALLOC.'!$A58) -> 0 | T58: =ROUND(($U58/($H58-($M58+$K58+$O58+$Q58+$S58))*100),3) -> 0 | U58: =SUMIFS('IN STORE SALES RECORD'!$E$6:$E$97,'IN STORE SALES RECORD'!$A$6:$A$97, "WEEK 6",'IN STORE SALES RECORD'!$D$6:$D$97,'WHS STK MGT & ALLOC.'!$A58) -> 0 | V58: =ROUND(($W58/($H58-($M58+$K58+$O58+$Q58+$S58+$U58))*100),3) -> 0 | W58: =SUMIFS('IN STORE SALES RECORD'!$E$6:$E$97,'IN STORE SALES RECORD'!$A$6:$A$97, "WEEK 6",'IN STORE SALES RECORD'!$D$6:$D$97,'WHS STK MGT & ALLOC.'!$A58) -> 0 | X58: =ROUND(($Y58/($H58-($M58+$K58+$O58+$Q58+$S58+$U58+$W58))*100),3) -> 0 | Y58: =SUMIFS('IN STORE SALES RECORD'!$E$6:$E$97,'IN STORE SALES RECORD'!$A$6:$A$97, "WEEK 6",'IN STORE SALES RECORD'!$D$6:$D$97,'WHS STK MGT & ALLOC.'!$A58) -> 0
A59: AC-BE-CA-BL-35 | B59: =IFERROR(INDEX('REFERENCING & DATABASE'!$E$7:$E$131,MATCH($A59,'REFERENCING & DATABASE'!$D$7:$D$131,0)),"") -> Canvas Webbing Belt | C59: =IFERROR(INDEX('REFERENCING & DATABASE'!$B$7:$B$131,MATCH($A59,'REFERENCING & DATABASE'!$D$7:$D$131,0)),"") -> ACCESSORIES | D59: =IFERROR(INDEX('REFERENCING & DATABASE'!$C$7:$C$131,MATCH($A59,'REFERENCING & DATABASE'!$D$7:$D$131,0)),"") -> BELTS | E59: =IFERROR(INDEX('REFERENCING & DATABASE'!$F$7:$F$131,MATCH($A59,'REFERENCING & DATABASE'!$D$7:$D$131,0)),"") -> A versatile and adjustable belt for casual wear. | F59: =IFERROR(INDEX('REFERENCING & DATABASE'!$G$7:$G$131,MATCH($A59,'REFERENCING & DATABASE'!$D$7:$D$131,0)),"Not Available") -> Black,Brown | G59: =IFERROR(INDEX('REFERENCING & DATABASE'!$H$7:$H$131,MATCH($A59,'REFERENCING & DATABASE'!$D$7:$D$131,0)),"") -> 35 | H59: =IFERROR(INDEX('REFERENCING & DATABASE'!$A$7:$A$131,MATCH($A59,'REFERENCING & DATABASE'!$D$7:$D$131,0)),"") -> 120 | I59: =H59-SUM($K59,$M59,$O59,$Q59) -> 110 | J59: =ROUND((($K59/$H59)*100),3) -> 8.333 | K59: =SUMIFS('IN STORE SALES RECORD'!$E$6:$E$97,'IN STORE SALES RECORD'!$A$6:$A$97, "WEEK 1",'IN STORE SALES RECORD'!$D$6:$D$97,'WHS STK MGT & ALLOC.'!$A59)+10 -> 10 | L59: =ROUND(($M59/($H59-$K59))*100,3) -> 0 | M59: =SUMIFS('IN STORE SALES RECORD'!$E$6:$E$97,'IN STORE SALES RECORD'!$A$6:$A$97, "WEEK 6",'IN STORE SALES RECORD'!$D$6:$D$97,'WHS STK MGT & ALLOC.'!$A59) -> 0 | N59: =ROUND(($O59/($H59-($M59+$K59))*100),3) -> 0 | O59: =SUMIFS('IN STORE SALES RECORD'!$E$6:$E$97,'IN STORE SALES RECORD'!$A$6:$A$97, "WEEK 6",'IN STORE SALES RECORD'!$D$6:$D$97,'WHS STK MGT & ALLOC.'!$A59) -> 0 | P59: =ROUND(($Q59/($H59-($M59+$K59+$O59))*100),3) -> 0 | Q59: =SUMIFS('IN STORE SALES RECORD'!$E$6:$E$97,'IN STORE SALES RECORD'!$A$6:$A$97, "WEEK 6",'IN STORE SALES RECORD'!$D$6:$D$97,'WHS STK MGT & ALLOC.'!$A59) -> 0 | R59: =ROUND(($S59/($H59-($M59+$K59+$O59+$Q59))*100),3) -> 0 | S59: =SUMIFS('IN STORE SALES RECORD'!$E$6:$E$97,'IN STORE SALES RECORD'!$A$6:$A$97, "WEEK 6",'IN STORE SALES RECORD'!$D$6:$D$97,'WHS STK MGT & ALLOC.'!$A59) -> 0 | T59: =ROUND(($U59/($H59-($M59+$K59+$O59+$Q59+$S59))*100),3) -> 0 | U59: =SUMIFS('IN STORE SALES RECORD'!$E$6:$E$97,'IN STORE SALES RECORD'!$A$6:$A$97, "WEEK 6",'IN STORE SALES RECORD'!$D$6:$D$97,'WHS STK MGT & ALLOC.'!$A59) -> 0 | V59: =ROUND(($W59/($H59-($M59+$K59+$O59+$Q59+$S59+$U59))*100),3) -> 0 | W59: =SUMIFS('IN STORE SALES RECORD'!$E$6:$E$97,'IN STORE SALES RECORD'!$A$6:$A$97, "WEEK 6",'IN STORE SALES RECORD'!$D$6:$D$97,'WHS STK MGT & ALLOC.'!$A59) -> 0 | X59: =ROUND(($Y59/($H59-($M59+$K59+$O59+$Q59+$S59+$U59+$W59))*100),3) -> 0 | Y59: =SUMIFS('IN STORE SALES RECORD'!$E$6:$E$97,'IN STORE SALES RECORD'!$A$6:$A$97, "WEEK 6",'IN STORE SALES RECORD'!$D$6:$D$97,'WHS STK MGT & ALLOC.'!$A59) -> 0
A60: AC-HA-CO-BL-7 | B60: =IFERROR(INDEX('REFERENCING & DATABASE'!$E$7:$E$131,MATCH($A60,'REFERENCING & DATABASE'!$D$7:$D$131,0)),"") -> Cozy Cable-Knit Beanie | C60: =IFERROR(INDEX('REFERENCING & DATABASE'!$B$7:$B$131,MATCH($A60,'REFERENCING & DATABASE'!$D$7:$D$131,0)),"") -> ACCESSORIES | D60: =IFERROR(INDEX('REFERENCING & DATABASE'!$C$7:$C$131,MATCH($A60,'REFERENCING & DATABASE'!$D$7:$D$131,0)),"") -> HATS | E60: =IFERROR(INDEX('REFERENCING & DATABASE'!$F$7:$F$131,MATCH($A60,'REFERENCING & DATABASE'!$D$7:$D$131,0)),"") -> : A warm and stylish beanie perfect for winter weather. | F60: =IFERROR(INDEX('REFERENCING & DATABASE'!$G$7:$G$131,MATCH($A60,'REFERENCING & DATABASE'!$D$7:$D$131,0)),"Not Available") -> Blue | G60: =IFERROR(INDEX('REFERENCING & DATABASE'!$H$7:$H$131,MATCH($A60,'REFERENCING & DATABASE'!$D$7:$D$131,0)),"") -> 7 | H60: =IFERROR(INDEX('REFERENCING & DATABASE'!$A$7:$A$131,MATCH($A60,'REFERENCING & DATABASE'!$D$7:$D$131,0)),"") -> 200 | I60: =H60-SUM($K60,$M60,$O60,$Q60) -> 115 | J60: =ROUND((($K60/$H60)*100),3) -> 42.5 | K60: =SUMIFS('IN STORE SALES RECORD'!$E$6:$E$97,'IN STORE SALES RECORD'!$A$6:$A$97, "WEEK 1",'IN STORE SALES RECORD'!$D$6:$D$97,'WHS STK MGT & ALLOC.'!$A60)+10 -> 85 | L60: =ROUND(($M60/($H60-$K60))*100,3) -> 0 | M60: =SUMIFS('IN STORE SALES RECORD'!$E$6:$E$97,'IN STORE SALES RECORD'!$A$6:$A$97, "WEEK 6",'IN STORE SALES RECORD'!$D$6:$D$97,'WHS STK MGT & ALLOC.'!$A60) -> 0 | N60: =ROUND(($O60/($H60-($M60+$K60))*100),3) -> 0 | O60: =SUMIFS('IN STORE SALES RECORD'!$E$6:$E$97,'IN STORE SALES RECORD'!$A$6:$A$97, "WEEK 6",'IN STORE SALES RECORD'!$D$6:$D$97,'WHS STK MGT & ALLOC.'!$A60) -> 0 | P60: =ROUND(($Q60/($H60-($M60+$K60+$O60))*100),3) -> 0 | Q60: =SUMIFS('IN STORE SALES RECORD'!$E$6:$E$97,'IN STORE SALES RECORD'!$A$6:$A$97, "WEEK 6",'IN STORE SALES RECORD'!$D$6:$D$97,'WHS STK MGT & ALLOC.'!$A60) -> 0 | R60: =ROUND(($S60/($H60-($M60+$K60+$O60+$Q60))*100),3) -> 0 | S60: =SUMIFS('IN STORE SALES RECORD'!$E$6:$E$97,'IN STORE SALES RECORD'!$A$6:$A$97, "WEEK 6",'IN STORE SALES RECORD'!$D$6:$D$97,'WHS STK MGT & ALLOC.'!$A60) -> 0 | T60: =ROUND(($U60/($H60-($M60+$K60+$O60+$Q60+$S60))*100),3) -> 0 | U60: =SUMIFS('IN STORE SALES RECORD'!$E$6:$E$97,'IN STORE SALES RECORD'!$A$6:$A$97, "WEEK 6",'IN STORE SALES RECORD'!$D$6:$D$97,'WHS STK MGT & ALLOC.'!$A60) -> 0 | V60: =ROUND(($W60/($H60-($M60+$K60+$O60+$Q60+$S60+$U60))*100),3) -> 0 | W60: =SUMIFS('IN STORE SALES RECORD'!$E$6:$E$97,'IN STORE SALES RECORD'!$A$6:$A$97, "WEEK 6",'IN STORE SALES RECORD'!$D$6:$D$97,'WHS STK MGT & ALLOC.'!$A60) -> 0 | X60: =ROUND(($Y60/($H60-($M60+$K60+$O60+$Q60+$S60+$U60+$W60))*100),3) -> 0 | Y60: =SUMIFS('IN STORE SALES RECORD'!$E$6:$E$97,'IN STORE SALES RECORD'!$A$6:$A$97, "WEEK 6",'IN STORE SALES RECORD'!$D$6:$D$97,'WHS STK MGT & ALLOC.'!$A60) -> 0
A61: AC-HA-CL-GR-7 | B61: =IFERROR(INDEX('REFERENCING & DATABASE'!$E$7:$E$131,MATCH($A61,'REFERENCING & DATABASE'!$D$7:$D$131,0)),"") -> Classic Baseball Cap | C61: =IFERROR(INDEX('REFERENCING & DATABASE'!$B$7:$B$131,MATCH($A61,'REFERENCING & DATABASE'!$D$7:$D$131,0)),"") -> ACCESSORIES | D61: =IFERROR(INDEX('REFERENCING & DATABASE'!$C$7:$C$131,MATCH($A61,'REFERENCING & DATABASE'!$D$7:$D$131,0)),"") -> HATS | E61: =IFERROR(INDEX('REFERENCING & DATABASE'!$F$7:$F$131,MATCH($A61,'REFERENCING & DATABASE'!$D$7:$D$131,0)),"") -> : A timeless and versatile cap with an adjustable strap. | F61: =IFERROR(INDEX('REFERENCING & DATABASE'!$G$7:$G$131,MATCH($A61,'REFERENCING & DATABASE'!$D$7:$D$131,0)),"Not Available") -> Grey,Orange | G61: =IFERROR(INDEX('REFERENCING & DATABASE'!$H$7:$H$131,MATCH($A61,'REFERENCING & DATABASE'!$D$7:$D$131,0)),"") -> 7 | H61: =IFERROR(INDEX('REFERENCING & DATABASE'!$A$7:$A$131,MATCH($A61,'REFERENCING & DATABASE'!$D$7:$D$131,0)),"") -> 305 | I61: =H61-SUM($K61,$M61,$O61,$Q61) -> 295 | J61: =ROUND((($K61/$H61)*100),3) -> 3.279 | K61: =SUMIFS('IN STORE SALES RECORD'!$E$6:$E$97,'IN STORE SALES RECORD'!$A$6:$A$97, "WEEK 1",'IN STORE SALES RECORD'!$D$6:$D$97,'WHS STK MGT & ALLOC.'!$A61)+10 -> 10 | L61: =ROUND(($M61/($H61-$K61))*100,3) -> 0 | M61: =SUMIFS('IN STORE SALES RECORD'!$E$6:$E$97,'IN STORE SALES RECORD'!$A$6:$A$97, "WEEK 6",'IN STORE SALES RECORD'!$D$6:$D$97,'WHS STK MGT & ALLOC.'!$A61) -> 0 | N61: =ROUND(($O61/($H61-($M61+$K61))*100),3) -> 0 | O61: =SUMIFS('IN STORE SALES RECORD'!$E$6:$E$97,'IN STORE SALES RECORD'!$A$6:$A$97, "WEEK 6",'IN STORE SALES RECORD'!$D$6:$D$97,'WHS STK MGT & ALLOC.'!$A61) -> 0 | P61: =ROUND(($Q61/($H61-($M61+$K61+$O61))*100),3) -> 0 | Q61: =SUMIFS('IN STORE SALES RECORD'!$E$6:$E$97,'IN STORE SALES RECORD'!$A$6:$A$97, "WEEK 6",'IN STORE SALES RECORD'!$D$6:$D$97,'WHS STK MGT & ALLOC.'!$A61) -> 0 | R61: =ROUND(($S61/($H61-($M61+$K61+$O61+$Q61))*100),3) -> 0 | S61: =SUMIFS('IN STORE SALES RECORD'!$E$6:$E$97,'IN STORE SALES RECORD'!$A$6:$A$97, "WEEK 6",'IN STORE SALES RECORD'!$D$6:$D$97,'WHS STK MGT & ALLOC.'!$A61) -> 0 | T61: =ROUND(($U61/($H61-($M61+$K61+$O61+$Q61+$S61))*100),3) -> 0 | U61: =SUMIFS('IN STORE SALES RECORD'!$E$6:$E$97,'IN STORE SALES RECORD'!$A$6:$A$97, "WEEK 6",'IN STORE SALES RECORD'!$D$6:$D$97,'WHS STK MGT & ALLOC.'!$A61) -> 0 | V61: =ROUND(($W61/($H61-($M61+$K61+$O61+$Q61+$S61+$U61))*100),3) -> 0 | W61: =SUMIFS('IN STORE SALES RECORD'!$E$6:$E$97,'IN STORE SALES RECORD'!$A$6:$A$97, "WEEK 6",'IN STORE SALES RECORD'!$D$6:$D$97,'WHS STK MGT & ALLOC.'!$A61) -> 0 | X61: =ROUND(($Y61/($H61-($M61+$K61+$O61+$Q61+$S61+$U61+$W61))*100),3) -> 0 | Y61: =SUMIFS('IN STORE SALES RECORD'!$E$6:$E$97,'IN STORE SALES RECORD'!$A$6:$A$97, "WEEK 6",'IN STORE SALES RECORD'!$D$6:$D$97,'WHS STK MGT & ALLOC.'!$A61) -> 0
... A64: AC-HA-FE-BL-6 | B64: =IFERROR(INDEX('REFERENCING & DATABASE'!$E$7:$E$131,MATCH($A64,'REFERENCING & DATABASE'!$D$7:$D$131,0)),"") -> Felt Fedora | C64: =IFERROR(INDEX('REFERENCING & DATABASE'!$B$7:$B$131,MATCH($A64,'REFERENCING & DATABASE'!$D$7:$D$131,0)),"") -> ACCESSORIES | D64: =IFERROR(INDEX('REFERENCING & DATABASE'!$C$7:$C$131,MATCH($A64,'REFERENCING & DATABASE'!$D$7:$D$131,0)),"") -> HATS | E64: =IFERROR(INDEX('REFERENCING & DATABASE'!$F$7:$F$131,MATCH($A64,'REFERENCING & DATABASE'!$D$7:$D$131,0)),"") -> : A sophisticated and stylish fedora for a classic look. | F64: =IFERROR(INDEX('REFERENCING & DATABASE'!$G$7:$G$131,MATCH($A64,'REFERENCING & DATABASE'!$D$7:$D$131,0)),"Not Available") -> Black,Brown | G64: =IFERROR(INDEX('REFERENCING & DATABASE'!$H$7:$H$131,MATCH($A64,'REFERENCING & DATABASE'!$D$7:$D$131,0)),"") -> 6 | H64: =IFERROR(INDEX('REFERENCING & DATABASE'!$A$7:$A$131,MATCH($A64,'REFERENCING & DATABASE'!$D$7:$D$131,0)),"") -> 230 | I64: =H64-SUM($K64,$M64,$O64,$Q64) -> 220 | J64: =ROUND((($K64/$H64)*100),3) -> 4.348 | K64: =SUMIFS('IN STORE SALES RECORD'!$E$6:$E$97,'IN STORE SALES RECORD'!$A$6:$A$97, "WEEK 1",'IN STORE SALES RECORD'!$D$6:$D$97,'WHS STK MGT & ALLOC.'!$A64)+10 -> 10 | L64: =ROUND(($M64/($H64-$K64))*100,3) -> 0 | M64: =SUMIFS('IN STORE SALES RECORD'!$E$6:$E$97,'IN STORE SALES RECORD'!$A$6:$A$97, "WEEK 6",'IN STORE SALES RECORD'!$D$6:$D$97,'WHS STK MGT & ALLOC.'!$A64) -> 0 | N64: =ROUND(($O64/($H64-($M64+$K64))*100),3) -> 0 | O64: =SUMIFS('IN STORE SALES RECORD'!$E$6:$E$97,'IN STORE SALES RECORD'!$A$6:$A$97, "WEEK 6",'IN STORE SALES RECORD'!$D$6:$D$97,'WHS STK MGT & ALLOC.'!$A64) -> 0 | P64: =ROUND(($Q64/($H64-($M64+$K64+$O64))*100),3) -> 0 | Q64: =SUMIFS('IN STORE SALES RECORD'!$E$6:$E$97,'IN STORE SALES RECORD'!$A$6:$A$97, "WEEK 6",'IN STORE SALES RECORD'!$D$6:$D$97,'WHS STK MGT & ALLOC.'!$A64) -> 0 | R64: =ROUND(($S64/($H64-($M64+$K64+$O64+$Q64))*100),3) -> 0 | S64: =SUMIFS('IN STORE SALES RECORD'!$E$6:$E$97,'IN STORE SALES RECORD'!$A$6:$A$97, "WEEK 6",'IN STORE SALES RECORD'!$D$6:$D$97,'WHS STK MGT & ALLOC.'!$A64) -> 0 | T64: =ROUND(($U64/($H64-($M64+$K64+$O64+$Q64+$S64))*100),3) -> 0 | U64: =SUMIFS('IN STORE SALES RECORD'!$E$6:$E$97,'IN STORE SALES RECORD'!$A$6:$A$97, "WEEK 6",'IN STORE SALES RECORD'!$D$6:$D$97,'WHS STK MGT & ALLOC.'!$A64) -> 0 | V64: =ROUND(($W64/($H64-($M64+$K64+$O64+$Q64+$S64+$U64))*100),3) -> 0 | W64: =SUMIFS('IN STORE SALES RECORD'!$E$6:$E$97,'IN STORE SALES RECORD'!$A$6:$A$97, "WEEK 6",'IN STORE SALES RECORD'!$D$6:$D$97,'WHS STK MGT & ALLOC.'!$A64) -> 0 | X64: =ROUND(($Y64/($H64-($M64+$K64+$O64+$Q64+$S64+$U64+$W64))*100),3) -> 0 | Y64: =SUMIFS('IN STORE SALES RECORD'!$E$6:$E$97,'IN STORE SALES RECORD'!$A$6:$A$97, "WEEK 6",'IN STORE SALES RECORD'!$D$6:$D$97,'WHS STK MGT & ALLOC.'!$A64) -> 0

Sheet STORE STK & SALES MGT
A1: STORE STOCK & SALES MANAGEMENT
A4: STORE STOCK | N4: SALES MANAGEMENT
N5: WEEKLY | P5: WEEK 1 | T5: MONTHLY | U5: 1
A6: REFERENCE | B6: PRODUCT NAME | C6: CATEGORY | D6: SUB-CATEGORY | E6: DESCRIPTION | F6: COLOUR | G6: SIZE | H6: AVAILABLE WHS STOCK | I6: TOTAL STOCK ALLOCATED | J6: CUMULATIVE UNIT SALES | K6: CUMULATIVE SALES | L6: SALES MIX | M6: SELL THROUGH | N6: STOCK ALLOCATION | O6: OPENING STOCK | P6: UNIT SALES | Q6: SALES | R6: SALES MIX | S6: REMAINING STOCK | T6: TOTAL UNIT SALES | U6: TOTAL SALES | V6: TOTAL SALES MIX
A7: TO-TE-CO-GR-58 | B7: =IFERROR(INDEX('REFERENCING & DATABASE'!$E$7:$E$131,MATCH($A7,'REFERENCING & DATABASE'!$D$7:$D$131,0)),"") -> Cozy Comfort Tee | C7: =IFERROR(INDEX('REFERENCING & DATABASE'!$B$7:$B$131,MATCH($A7,'REFERENCING & DATABASE'!$D$7:$D$131,0)),"") -> TOPS | D7: =IFERROR(INDEX('REFERENCING & DATABASE'!$C$7:$C$131,MATCH($A7,'REFERENCING & DATABASE'!$D$7:$D$131,0)),"") -> TEES | E7: =IFERROR(INDEX('REFERENCING & DATABASE'!$F$7:$F$131,MATCH($A7,'REFERENCING & DATABASE'!$D$7:$D$131,0)),"") -> A relaxed-fit tee made from super-soft cotton, perfect for everyday wear. | F7: =IFERROR(INDEX('REFERENCING & DATABASE'!$G$7:$G$131,MATCH($A7,'REFERENCING & DATABASE'!$D$7:$D$131,0)),"") -> Grey,Black,Blue | G7: =IFERROR(INDEX('REFERENCING & DATABASE'!$H$7:$H$131,MATCH($A7,'REFERENCING & DATABASE'!$D$7:$D$131,0)),"") -> 58 | H7: =IFERROR(INDEX('WHS STK MGT & ALLOC.'!$I:$I,MATCH($A7,'WHS STK MGT & ALLOC.'!$A:$A,0)),"") -> 400 | I7: =SUM('WHS STK MGT & ALLOC.'!$K7,'WHS STK MGT & ALLOC.'!$M7,'WHS STK MGT & ALLOC.'!$O7,'WHS STK MGT & ALLOC.'!$Q7,'WHS STK MGT & ALLOC.'!$S7,'WHS STK MGT & ALLOC.'!$U7,'WHS STK MGT & ALLOC.'!$W7,'WHS STK MGT & ALLOC.'!$Y7) -> 50 | J7: =SUMIF('IN STORE SALES RECORD'!$D:$D,'STORE STK & SALES MGT'!$A7,'IN STORE SALES RECORD'!$E:$E) -> 40 | K7: =SUMIF('IN STORE SALES RECORD'!$D:$D,'STORE STK & SALES MGT'!$A7,'IN STORE SALES RECORD'!$H:$H) -> 1400 | L7: =IFERROR(ROUND(($K7/(SUM($K:$K))) * 100,3),"") -> 3.431 | M7: =IFERROR(ROUND($J7/$I7 * 100,2),"") -> 80 | N7: {=_xlfn.IFS($P$5 = "WEEK 1",'WHS STK MGT & ALLOC.'!$K7,$P$5 = "WEEK 2",'WHS STK MGT & ALLOC.'!$M7,$P$5 = "WEEK 3",'WHS STK MGT & ALLOC.'!$O7,$P$5 = "WEEK 4",'WHS STK MGT & ALLOC.'!Q7,$P$5 ="WEEK 5",'WHS STK MGT & ALLOC.'!$S7,$P$5 ="WEEK 6",'WHS STK MGT & ALLOC.'!$U7,$P$5 ="WEEK 7",'WHS STK MGT & ALLOC.'!$W7,$P$5 ="WEEK 6",'WHS STK MGT & ALLOC.'!$Y7)} -> 50 | O7: {=_xlfn.SWITCH($P$5, "WEEK 1",'WHS STK MGT & ALLOC.'!$H7, "WEEK 2",'WHS STK MGT & ALLOC.'!$H7-'WHS STK MGT & ALLOC.'!$K7, "WEEK 3",'WHS STK MGT & ALLOC.'!$H7-('WHS STK MGT & ALLOC.'!$K7+'WHS STK MGT & ALLOC.'!$M7), "WEEK 4",'WHS STK MGT & ALLOC.'!$H7-('WHS STK MGT & ALLOC.'!$K7+'WHS STK MGT & ALLOC.'!$M7+'WHS STK MGT & ALLOC.'!$O7), "WEEK 5",'WHS STK MGT & ALLOC.'!$H7-('WHS STK MGT & ALLOC.'!$K7+'WHS STK MGT & ALLOC.'!$M7+'WHS STK MGT & ALLOC.'!$O7+'WHS STK MGT & ALLOC.'!$Q7), "WEEK 6",'WHS STK MGT & ALLOC.'!$H7-('WHS STK MGT & ALLOC.'!$K7+'WHS STK MGT & ALLOC.'!$M7+'WHS STK MGT & ALLOC.'!$O7+'WHS STK MGT & ALLOC.'!$Q7+'WHS STK MGT & ALLOC.'!$S7), "WEEK 7",'WHS STK MGT & ALLOC.'!$H7-('WHS STK MGT & ALLOC.'!$K7+'WHS STK MGT & ALLOC.'!$M7+'WHS STK MGT & ALLOC.'!$O7+'WHS STK MGT & ALLOC.'!$Q7+'WHS STK MGT & ALLOC.'!$S7+'WHS STK MGT & ALLOC.'!$U7), "WEEK 8",'WHS STK MGT & ALLOC.'!$H7-('WHS STK MGT & ALLOC.'!$K7+'WHS STK MGT & ALLOC.'!$M7+'WHS STK MGT & ALLOC.'!$O7+'WHS STK MGT & ALLOC.'!$Q7+'WHS STK MGT & ALLOC.'!$S7+'WHS STK MGT & ALLOC.'!$U7+'WHS STK MGT & ALLOC.'!$W7 ))} -> 450 | P7: =SUMIFS('IN STORE SALES RECORD'!$E:$E,'IN STORE SALES RECORD'!$D:$D,'STORE STK & SALES MGT'!$A7,'IN STORE SALES RECORD'!$A:$A,'STORE STK & SALES MGT'!$P$5) -> 40 | Q7: =SUMIFS('IN STORE SALES RECORD'!$H:$H,'IN STORE SALES RECORD'!$D:$D,'STORE STK & SALES MGT'!$A7,'IN STORE SALES RECORD'!$A:$A,'STORE STK & SALES MGT'!$P$5) -> 1400 | R7: =IFERROR(ROUND(Q7/SUMIF('IN STORE SALES RECORD'!$A:$A,'STORE STK & SALES MGT'!$P$5,'IN STORE SALES RECORD'!$H:$H)*100,3),"") -> 6.984 | S7: {=_xlfn.IFS($P$5 ="WEEK 1",'WHS STK MGT & ALLOC.'!$H7-'WHS STK MGT & ALLOC.'!$K7,$P$5 ="WEEK 2",'WHS STK MGT & ALLOC.'!H7-('WHS STK MGT & ALLOC.'!$K7+'WHS STK MGT & ALLOC.'!$M7),$P$5 ="WEEK 3",'WHS STK MGT & ALLOC.'!$H7-'WHS STK MGT & ALLOC.'!$K7-'WHS STK MGT & ALLOC.'!$M7-'WHS STK MGT & ALLOC.'!$O7,$P$5 = "WEEK 4",'WHS STK MGT & ALLOC.'!H7-'WHS STK MGT & ALLOC.'!$K7-'WHS STK MGT & ALLOC.'!$M7-'WHS STK MGT & ALLOC.'!$O7-'WHS STK MGT & ALLOC.'!$Q7,$P$5 = "WEEK 5",'WHS STK MGT & ALLOC.'!H7-'WHS STK MGT & ALLOC.'!$K7-'WHS STK MGT & ALLOC.'!$M7-'WHS STK MGT & ALLOC.'!$O7-'WHS STK MGT & ALLOC.'!$Q7-'WHS STK MGT & ALLOC.'!$S7)} -> 400 | T7: =SUMIFS('IN STORE SALES RECORD'!$E:$E,'IN STORE SALES RECORD'!$D:$D,'STORE STK & SALES MGT'!$A7,'IN STORE SALES RECORD'!$C:$C,'STORE STK & SALES MGT'!$U$5) -> 40 | U7: =SUMIFS('IN STORE SALES RECORD'!$H:$H,'IN STORE SALES RECORD'!$D:$D,'STORE STK & SALES MGT'!$A7,'IN STORE SALES RECORD'!$C:$C,'STORE STK & SALES MGT'!$U$5) -> 1400 | V7: =IFERROR(ROUND(SUMIFS('IN STORE SALES RECORD'!$H:$H,'IN STORE SALES RECORD'!$C:$C,'STORE STK & SALES MGT'!$U$5,'STORE STK & SALES MGT'!$A:$A,'STORE STK & SALES MGT'!$A7)/SUMIF('IN STORE SALES RECORD'!$C:$C,'STORE STK & SALES MGT'!$U$5,'IN STORE SALES RECORD'!$H:$H)*100,3),"") -> 6.863
A8: TO-TE-GR-BL-58 | B8: =IFERROR(INDEX('REFERENCING & DATABASE'!$E$7:$E$131,MATCH($A8,'REFERENCING & DATABASE'!$D$7:$D$131,0)),"") -> Graphic Statement Tee | C8: =IFERROR(INDEX('REFERENCING & DATABASE'!$B$7:$B$131,MATCH($A8,'REFERENCING & DATABASE'!$D$7:$D$131,0)),"") -> TOPS | D8: =IFERROR(INDEX('REFERENCING & DATABASE'!$C$7:$C$131,MATCH($A8,'REFERENCING & DATABASE'!$D$7:$D$131,0)),"") -> TEES | E8: =IFERROR(INDEX('REFERENCING & DATABASE'!$F$7:$F$131,MATCH($A8,'REFERENCING & DATABASE'!$D$7:$D$131,0)),"") -> A bold graphic tee that expresses your unique style. | F8: =IFERROR(INDEX('REFERENCING & DATABASE'!$G$7:$G$131,MATCH($A8,'REFERENCING & DATABASE'!$D$7:$D$131,0)),"") -> Blue,Black,White | G8: =IFERROR(INDEX('REFERENCING & DATABASE'!$H$7:$H$131,MATCH($A8,'REFERENCING & DATABASE'!$D$7:$D$131,0)),"") -> 58 | H8: =IFERROR(INDEX('WHS STK MGT & ALLOC.'!$I:$I,MATCH($A8,'WHS STK MGT & ALLOC.'!$A:$A,0)),"") -> 290 | I8: =SUM('WHS STK MGT & ALLOC.'!$K8,'WHS STK MGT & ALLOC.'!$M8,'WHS STK MGT & ALLOC.'!$O8,'WHS STK MGT & ALLOC.'!$Q8,'WHS STK MGT & ALLOC.'!$S8,'WHS STK MGT & ALLOC.'!$U8,'WHS STK MGT & ALLOC.'!$W8,'WHS STK MGT & ALLOC.'!$Y8) -> 10 | J8: =SUMIF('IN STORE SALES RECORD'!$D:$D,'STORE STK & SALES MGT'!$A8,'IN STORE SALES RECORD'!$E:$E) -> 0 | K8: =SUMIF('IN STORE SALES RECORD'!$D:$D,'STORE STK & SALES MGT'!$A8,'IN STORE SALES RECORD'!$H:$H) -> 0 | L8: =IFERROR(ROUND(($K8/(SUM($K:$K))) * 100,3),"") -> 0 | M8: =IFERROR(ROUND($J8/$I8 * 100,2),"") -> 0 | N8: {=_xlfn.IFS($P$5 = "WEEK 1",'WHS STK MGT & ALLOC.'!$K8,$P$5 = "WEEK 2",'WHS STK MGT & ALLOC.'!$M8,$P$5 = "WEEK 3",'WHS STK MGT & ALLOC.'!$O8,$P$5 = "WEEK 4",'WHS STK MGT & ALLOC.'!Q8,$P$5 ="WEEK 5",'WHS STK MGT & ALLOC.'!$S8)} -> 10 | O8: {=_xlfn.SWITCH($P$5, "WEEK 1", 'WHS STK MGT & ALLOC.'!$H8, "WEEK 2", 'WHS STK MGT & ALLOC.'!$H8 - 'WHS STK MGT & ALLOC.'!$K8, "WEEK 3", 'WHS STK MGT & ALLOC.'!$H8 - ('WHS STK MGT & ALLOC.'!$K8 + 'WHS STK MGT & ALLOC.'!$M8), "WEEK 4", 'WHS STK MGT & ALLOC.'!$H8 - ('WHS STK MGT & ALLOC.'!$K8 + 'WHS STK MGT & ALLOC.'!$M8 + 'WHS STK MGT & ALLOC.'!$O8), "WEEK 5", 'WHS STK MGT & ALLOC.'!$H8 - ('WHS STK MGT & ALLOC.'!$K8 + 'WHS STK MGT & ALLOC.'!$M8 + 'WHS STK MGT & ALLOC.'!$O8 + 'WHS STK MGT & ALLOC.'!$Q8), "WEEK 6", 'WHS STK MGT & ALLOC.'!$H8 - ('WHS STK MGT & ALLOC.'!$K8 + 'WHS STK MGT & ALLOC.'!$M8 + 'WHS STK MGT & ALLOC.'!$O8 + 'WHS STK MGT & ALLOC.'!$Q8 + 'WHS STK MGT & ALLOC.'!$S8), "WEEK 7", 'WHS STK MGT & ALLOC.'!$H8 - ('WHS STK MGT & ALLOC.'!$K8 + 'WHS STK MGT & ALLOC.'!$M8 + 'WHS STK MGT & ALLOC.'!$O8 + 'WHS STK MGT & ALLOC.'!$Q8 + 'WHS STK MGT & ALLOC.'!$S8 + 'WHS STK MGT & ALLOC.'!$U8), "Other Weeks", 0 )} -> 300 | P8: =SUMIFS('IN STORE SALES RECORD'!$E:$E,'IN STORE SALES RECORD'!$D:$D,'STORE STK & SALES MGT'!$A8,'IN STORE SALES RECORD'!$A:$A,'STORE STK & SALES MGT'!$P$5) -> 0 | Q8: =SUMIFS('IN STORE SALES RECORD'!$H:$H,'IN STORE SALES RECORD'!$D:$D,'STORE STK & SALES MGT'!$A8,'IN STORE SALES RECORD'!$A:$A,'STORE STK & SALES MGT'!$P$5) -> 0 | R8: =IFERROR(ROUND(Q8/SUMIF('IN STORE SALES RECORD'!$A:$A,'STORE STK & SALES MGT'!$P$5,'IN STORE SALES RECORD'!$H:$H)*100,3),"") -> 0 | S8: {=_xlfn.IFS($P$5 ="WEEK 1",'WHS STK MGT & ALLOC.'!$H8-'WHS STK MGT & ALLOC.'!$K8,$P$5 ="WEEK 2",'WHS STK MGT & ALLOC.'!H8-('WHS STK MGT & ALLOC.'!$K8+'WHS STK MGT & ALLOC.'!$M8),$P$5 ="WEEK 3",'WHS STK MGT & ALLOC.'!$H8-'WHS STK MGT & ALLOC.'!$K8-'WHS STK MGT & ALLOC.'!$M8-'WHS STK MGT & ALLOC.'!$O8,$P$5 = "WEEK 4",'WHS STK MGT & ALLOC.'!H8-'WHS STK MGT & ALLOC.'!$K8-'WHS STK MGT & ALLOC.'!$M8-'WHS STK MGT & ALLOC.'!$O8-'WHS STK MGT & ALLOC.'!$Q8,$P$5 = "WEEK 5",'WHS STK MGT & ALLOC.'!H8-'WHS STK MGT & ALLOC.'!$K8-'WHS STK MGT & ALLOC.'!$M8-'WHS STK MGT & ALLOC.'!$O8-'WHS STK MGT & ALLOC.'!$Q8-'WHS STK MGT & ALLOC.'!$S8)} -> 290 | T8: =SUMIFS('IN STORE SALES RECORD'!$E:$E,'IN STORE SALES RECORD'!$D:$D,'STORE STK & SALES MGT'!$A8,'IN STORE SALES RECORD'!$C:$C,'STORE STK & SALES MGT'!$U$5) -> 0 | U8: =SUMIFS('IN STORE SALES RECORD'!$H:$H,'IN STORE SALES RECORD'!$D:$D,'STORE STK & SALES MGT'!$A8,'IN STORE SALES RECORD'!$C:$C,'STORE STK & SALES MGT'!$U$5) -> 0 | V8: =IFERROR(ROUND(SUMIFS('IN STORE SALES RECORD'!$H:$H,'IN STORE SALES RECORD'!$C:$C,'STORE STK & SALES MGT'!$U$5,'STORE STK & SALES MGT'!$A:$A,'STORE STK & SALES MGT'!$A8)/SUMIF('IN STORE SALES RECORD'!$C:$C,'STORE STK & SALES MGT'!$U$5,'IN STORE SALES RECORD'!$H:$H)*100,3),"") -> 4.596
A9: TO-SH-CL-PI-10 | B9: =IFERROR(INDEX('REFERENCING & DATABASE'!$E$7:$E$131,MATCH($A9,'REFERENCING & DATABASE'!$D$7:$D$131,0)),"") -> Classic Button-Down Shirt | C9: =IFERROR(INDEX('REFERENCING & DATABASE'!$B$7:$B$131,MATCH($A9,'REFERENCING & DATABASE'!$D$7:$D$131,0)),"") -> TOPS | D9: =IFERROR(INDEX('REFERENCING & DATABASE'!$C$7:$C$131,MATCH($A9,'REFERENCING & DATABASE'!$D$7:$D$131,0)),"") -> SHIRTS | E9: =IFERROR(INDEX('REFERENCING & DATABASE'!$F$7:$F$131,MATCH($A9,'REFERENCING & DATABASE'!$D$7:$D$131,0)),"") -> A timeless and versatile shirt for work or casual occasions. | F9: =IFERROR(INDEX('REFERENCING & DATABASE'!$G$7:$G$131,MATCH($A9,'REFERENCING & DATABASE'!$D$7:$D$131,0)),"") -> Pink, Brown,Yellow | G9: =IFERROR(INDEX('REFERENCING & DATABASE'!$H$7:$H$131,MATCH($A9,'REFERENCING & DATABASE'!$D$7:$D$131,0)),"") -> 10 | H9: =IFERROR(INDEX('WHS STK MGT & ALLOC.'!$I:$I,MATCH($A9,'WHS STK MGT & ALLOC.'!$A:$A,0)),"") -> 60 | I9: =SUM('WHS STK MGT & ALLOC.'!$K9,'WHS STK MGT & ALLOC.'!$M9,'WHS STK MGT & ALLOC.'!$O9,'WHS STK MGT & ALLOC.'!$Q9,'WHS STK MGT & ALLOC.'!$S9,'WHS STK MGT & ALLOC.'!$U9,'WHS STK MGT & ALLOC.'!$W9,'WHS STK MGT & ALLOC.'!$Y9) -> 240 | J9: =SUMIF('IN STORE SALES RECORD'!$D:$D,'STORE STK & SALES MGT'!$A9,'IN STORE SALES RECORD'!$E:$E) -> 230 | K9: =SUMIF('IN STORE SALES RECORD'!$D:$D,'STORE STK & SALES MGT'!$A9,'IN STORE SALES RECORD'!$H:$H) -> 9200 | L9: =IFERROR(ROUND(($K9/(SUM($K:$K))) * 100,3),"") -> 22.549 | M9: =IFERROR(ROUND($J9/$I9 * 100,2),"") -> 95.83 | N9: {=_xlfn.IFS($P$5 = "WEEK 1",'WHS STK MGT & ALLOC.'!$K9,$P$5 = "WEEK 2",'WHS STK MGT & ALLOC.'!$M9,$P$5 = "WEEK 3",'WHS STK MGT & ALLOC.'!$O9,$P$5 = "WEEK 4",'WHS STK MGT & ALLOC.'!Q9,$P$5 ="WEEK 5",'WHS STK MGT & ALLOC.'!$S9)} -> 240 | O9: {=_xlfn.SWITCH($P$5, "WEEK 1", 'WHS STK MGT & ALLOC.'!$H9, "WEEK 2", 'WHS STK MGT & ALLOC.'!$H9 - 'WHS STK MGT & ALLOC.'!$K9, "WEEK 3", 'WHS STK MGT & ALLOC.'!$H9 - ('WHS STK MGT & ALLOC.'!$K9 + 'WHS STK MGT & ALLOC.'!$M9), "WEEK 4", 'WHS STK MGT & ALLOC.'!$H9 - ('WHS STK MGT & ALLOC.'!$K9 + 'WHS STK MGT & ALLOC.'!$M9 + 'WHS STK MGT & ALLOC.'!$O9), "WEEK 5", 'WHS STK MGT & ALLOC.'!$H9 - ('WHS STK MGT & ALLOC.'!$K9 + 'WHS STK MGT & ALLOC.'!$M9 + 'WHS STK MGT & ALLOC.'!$O9 + 'WHS STK MGT & ALLOC.'!$Q9), "WEEK 6", 'WHS STK MGT & ALLOC.'!$H9 - ('WHS STK MGT & ALLOC.'!$K9 + 'WHS STK MGT & ALLOC.'!$M9 + 'WHS STK MGT & ALLOC.'!$O9 + 'WHS STK MGT & ALLOC.'!$Q9 + 'WHS STK MGT & ALLOC.'!$S9), "WEEK 7", 'WHS STK MGT & ALLOC.'!$H9 - ('WHS STK MGT & ALLOC.'!$K9 + 'WHS STK MGT & ALLOC.'!$M9 + 'WHS STK MGT & ALLOC.'!$O9 + 'WHS STK MGT & ALLOC.'!$Q9 + 'WHS STK MGT & ALLOC.'!$S9 + 'WHS STK MGT & ALLOC.'!$U9), "Other Weeks", 0 )} -> 300 | P9: =SUMIFS('IN STORE SALES RECORD'!$E:$E,'IN STORE SALES RECORD'!$D:$D,'STORE STK & SALES MGT'!$A9,'IN STORE SALES RECORD'!$A:$A,'STORE STK & SALES MGT'!$P$5) -> 230 | Q9: =SUMIFS('IN STORE SALES RECORD'!$H:$H,'IN STORE SALES RECORD'!$D:$D,'STORE STK & SALES MGT'!$A9,'IN STORE SALES RECORD'!$A:$A,'STORE STK & SALES MGT'!$P$5) -> 9200 | R9: =IFERROR(ROUND(Q9/SUMIF('IN STORE SALES RECORD'!$A:$A,'STORE STK & SALES MGT'!$P$5,'IN STORE SALES RECORD'!$H:$H)*100,3),"") -> 45.897 | S9: {=_xlfn.IFS($P$5 ="WEEK 1",'WHS STK MGT & ALLOC.'!$H9-'WHS STK MGT & ALLOC.'!$K9,$P$5 ="WEEK 2",'WHS STK MGT & ALLOC.'!H9-('WHS STK MGT & ALLOC.'!$K9+'WHS STK MGT & ALLOC.'!$M9),$P$5 ="WEEK 3",'WHS STK MGT & ALLOC.'!$H9-'WHS STK MGT & ALLOC.'!$K9-'WHS STK MGT & ALLOC.'!$M9-'WHS STK MGT & ALLOC.'!$O9,$P$5 = "WEEK 4",'WHS STK MGT & ALLOC.'!H9-'WHS STK MGT & ALLOC.'!$K9-'WHS STK MGT & ALLOC.'!$M9-'WHS STK MGT & ALLOC.'!$O9-'WHS STK MGT & ALLOC.'!$Q9,$P$5 = "WEEK 5",'WHS STK MGT & ALLOC.'!H9-'WHS STK MGT & ALLOC.'!$K9-'WHS STK MGT & ALLOC.'!$M9-'WHS STK MGT & ALLOC.'!$O9-'WHS STK MGT & ALLOC.'!$Q9-'WHS STK MGT & ALLOC.'!$S9)} -> 60 | T9: =SUMIFS('IN STORE SALES RECORD'!$E:$E,'IN STORE SALES RECORD'!$D:$D,'STORE STK & SALES MGT'!$A9,'IN STORE SALES RECORD'!$C:$C,'STORE STK & SALES MGT'!$U$5) -> 230 | U9: =SUMIFS('IN STORE SALES RECORD'!$H:$H,'IN STORE SALES RECORD'!$D:$D,'STORE STK & SALES MGT'!$A9,'IN STORE SALES RECORD'!$C:$C,'STORE STK & SALES MGT'!$U$5) -> 9200 | V9: =IFERROR(ROUND(SUMIFS('IN STORE SALES RECORD'!$H:$H,'IN STORE SALES RECORD'!$C:$C,'STORE STK & SALES MGT'!$U$5,'STORE STK & SALES MGT'!$A:$A,'STORE STK & SALES MGT'!$A9)/SUMIF('IN STORE SALES RECORD'!$C:$C,'STORE STK & SALES MGT'!$U$5,'IN STORE SALES RECORD'!$H:$H)*100,3),"") -> 22.549
A10: TO-SH-LI-PI-10 | B10: =IFERROR(INDEX('REFERENCING & DATABASE'!$E$7:$E$131,MATCH($A10,'REFERENCING & DATABASE'!$D$7:$D$131,0)),"") -> Linen Blend Shirt | C10: =IFERROR(INDEX('REFERENCING & DATABASE'!$B$7:$B$131,MATCH($A10,'REFERENCING & DATABASE'!$D$7:$D$131,0)),"") -> TOPS | D10: =IFERROR(INDEX('REFERENCING & DATABASE'!$C$7:$C$131,MATCH($A10,'REFERENCING & DATABASE'!$D$7:$D$131,0)),"") -> SHIRTS | E10: =IFERROR(INDEX('REFERENCING & DATABASE'!$F$7:$F$131,MATCH($A10,'REFERENCING & DATABASE'!$D$7:$D$131,0)),"") -> A lightweight and breathable shirt for warmer weather. | F10: =IFERROR(INDEX('REFERENCING & DATABASE'!$G$7:$G$131,MATCH($A10,'REFERENCING & DATABASE'!$D$7:$D$131,0)),"") -> Pink, Clear | G10: =IFERROR(INDEX('REFERENCING & DATABASE'!$H$7:$H$131,MATCH($A10,'REFERENCING & DATABASE'!$D$7:$D$131,0)),"") -> 10 | H10: =IFERROR(INDEX('WHS STK MGT & ALLOC.'!$I:$I,MATCH($A10,'WHS STK MGT & ALLOC.'!$A:$A,0)),"") -> 390 | I10: =SUM('WHS STK MGT & ALLOC.'!$K10,'WHS STK MGT & ALLOC.'!$M10,'WHS STK MGT & ALLOC.'!$O10,'WHS STK MGT & ALLOC.'!$Q10,'WHS STK MGT & ALLOC.'!$S10,'WHS STK MGT & ALLOC.'!$U10,'WHS STK MGT & ALLOC.'!$W10,'WHS STK MGT & ALLOC.'!$Y10) -> 10 | J10: =SUMIF('IN STORE SALES RECORD'!$D:$D,'STORE STK & SALES MGT'!$A10,'IN STORE SALES RECORD'!$E:$E) -> 0 | K10: =SUMIF('IN STORE SALES RECORD'!$D:$D,'STORE STK & SALES MGT'!$A10,'IN STORE SALES RECORD'!$H:$H) -> 0 | L10: =IFERROR(ROUND(($K10/(SUM($K:$K))) * 100,3),"") -> 0 | M10: =IFERROR(ROUND($J10/$I10 * 100,2),"") -> 0 | N10: {=_xlfn.IFS($P$5 = "WEEK 1",'WHS STK MGT & ALLOC.'!$K10,$P$5 = "WEEK 2",'WHS STK MGT & ALLOC.'!$M10,$P$5 = "WEEK 3",'WHS STK MGT & ALLOC.'!$O10,$P$5 = "WEEK 4",'WHS STK MGT & ALLOC.'!Q10,$P$5 ="WEEK 5",'WHS STK MGT & ALLOC.'!$S10)} -> 10 | O10: {=_xlfn.SWITCH($P$5, "WEEK 1", 'WHS STK MGT & ALLOC.'!$H10, "WEEK 2", 'WHS STK MGT & ALLOC.'!$H10 - 'WHS STK MGT & ALLOC.'!$K10, "WEEK 3", 'WHS STK MGT & ALLOC.'!$H10 - ('WHS STK MGT & ALLOC.'!$K10 + 'WHS STK MGT & ALLOC.'!$M10), "WEEK 4", 'WHS STK MGT & ALLOC.'!$H10 - ('WHS STK MGT & ALLOC.'!$K10 + 'WHS STK MGT & ALLOC.'!$M10 + 'WHS STK MGT & ALLOC.'!$O10), "WEEK 5", 'WHS STK MGT & ALLOC.'!$H10 - ('WHS STK MGT & ALLOC.'!$K10 + 'WHS STK MGT & ALLOC.'!$M10 + 'WHS STK MGT & ALLOC.'!$O10 + 'WHS STK MGT & ALLOC.'!$Q10), "WEEK 6", 'WHS STK MGT & ALLOC.'!$H10 - ('WHS STK MGT & ALLOC.'!$K10 + 'WHS STK MGT & ALLOC.'!$M10 + 'WHS STK MGT & ALLOC.'!$O10 + 'WHS STK MGT & ALLOC.'!$Q10 + 'WHS STK MGT & ALLOC.'!$S10), "WEEK 7", 'WHS STK MGT & ALLOC.'!$H10 - ('WHS STK MGT & ALLOC.'!$K10 + 'WHS STK MGT & ALLOC.'!$M10 + 'WHS STK MGT & ALLOC.'!$O10 + 'WHS STK MGT & ALLOC.'!$Q10 + 'WHS STK MGT & ALLOC.'!$S10 + 'WHS STK MGT & ALLOC.'!$U10), "Other Weeks", 0 )} -> 400 | P10: =SUMIFS('IN STORE SALES RECORD'!$E:$E,'IN STORE SALES RECORD'!$D:$D,'STORE STK & SALES MGT'!$A10,'IN STORE SALES RECORD'!$A:$A,'STORE STK & SALES MGT'!$P$5) -> 0 | Q10: =SUMIFS('IN STORE SALES RECORD'!$H:$H,'IN STORE SALES RECORD'!$D:$D,'STORE STK & SALES MGT'!$A10,'IN STORE SALES RECORD'!$A:$A,'STORE STK & SALES MGT'!$P$5) -> 0 | R10: =IFERROR(ROUND(Q10/SUMIF('IN STORE SALES RECORD'!$A:$A,'STORE STK & SALES MGT'!$P$5,'IN STORE SALES RECORD'!$H:$H)*100,3),"") -> 0 | S10: {=_xlfn.IFS($P$5 ="WEEK 1",'WHS STK MGT & ALLOC.'!$H10-'WHS STK MGT & ALLOC.'!$K10,$P$5 ="WEEK 2",'WHS STK MGT & ALLOC.'!H10-('WHS STK MGT & ALLOC.'!$K10+'WHS STK MGT & ALLOC.'!$M10),$P$5 ="WEEK 3",'WHS STK MGT & ALLOC.'!$H10-'WHS STK MGT & ALLOC.'!$K10-'WHS STK MGT & ALLOC.'!$M10-'WHS STK MGT & ALLOC.'!$O10,$P$5 = "WEEK 4",'WHS STK MGT & ALLOC.'!H10-'WHS STK MGT & ALLOC.'!$K10-'WHS STK MGT & ALLOC.'!$M10-'WHS STK MGT & ALLOC.'!$O10-'WHS STK MGT & ALLOC.'!$Q10,$P$5 = "WEEK 5",'WHS STK MGT & ALLOC.'!H10-'WHS STK MGT & ALLOC.'!$K10-'WHS STK MGT & ALLOC.'!$M10-'WHS STK MGT & ALLOC.'!$O10-'WHS STK MGT & ALLOC.'!$Q10-'WHS STK MGT & ALLOC.'!$S10)} -> 390 | T10: =SUMIFS('IN STORE SALES RECORD'!$E:$E,'IN STORE SALES RECORD'!$D:$D,'STORE STK & SALES MGT'!$A10,'IN STORE SALES RECORD'!$C:$C,'STORE STK & SALES MGT'!$U$5) -> 0 | U10: =SUMIFS('IN STORE SALES RECORD'!$H:$H,'IN STORE SALES RECORD'!$D:$D,'STORE STK & SALES MGT'!$A10,'IN STORE SALES RECORD'!$C:$C,'STORE STK & SALES MGT'!$U$5) -> 0 | V10: =IFERROR(ROUND(SUMIFS('IN STORE SALES RECORD'!$H:$H,'IN STORE SALES RECORD'!$C:$C,'STORE STK & SALES MGT'!$U$5,'STORE STK & SALES MGT'!$A:$A,'STORE STK & SALES MGT'!$A10)/SUMIF('IN STORE SALES RECORD'!$C:$C,'STORE STK & SALES MGT'!$U$5,'IN STORE SALES RECORD'!$H:$H)*100,3),"") -> 0
A11: TO-SW-CO-NU-10 | B11: =IFERROR(INDEX('REFERENCING & DATABASE'!$E$7:$E$131,MATCH($A11,'REFERENCING & DATABASE'!$D$7:$D$131,0)),"") -> Cozy Cable-Knit Sweater | C11: =IFERROR(INDEX('REFERENCING & DATABASE'!$B$7:$B$131,MATCH($A11,'REFERENCING & DATABASE'!$D$7:$D$131,0)),"") -> TOPS | D11: =IFERROR(INDEX('REFERENCING & DATABASE'!$C$7:$C$131,MATCH($A11,'REFERENCING & DATABASE'!$D$7:$D$131,0)),"") -> SWEATERS | E11: =IFERROR(INDEX('REFERENCING & DATABASE'!$F$7:$F$131,MATCH($A11,'REFERENCING & DATABASE'!$D$7:$D$131,0)),"") -> A warm and stylish sweater for cooler days. | F11: =IFERROR(INDEX('REFERENCING & DATABASE'!$G$7:$G$131,MATCH($A11,'REFERENCING & DATABASE'!$D$7:$D$131,0)),"") -> Nude, Brown | G11: =IFERROR(INDEX('REFERENCING & DATABASE'!$H$7:$H$131,MATCH($A11,'REFERENCING & DATABASE'!$D$7:$D$131,0)),"") -> 10 | H11: =IFERROR(INDEX('WHS STK MGT & ALLOC.'!$I:$I,MATCH($A11,'WHS STK MGT & ALLOC.'!$A:$A,0)),"") -> 190 | I11: =SUM('WHS STK MGT & ALLOC.'!$K11,'WHS STK MGT & ALLOC.'!$M11,'WHS STK MGT & ALLOC.'!$O11,'WHS STK MGT & ALLOC.'!$Q11,'WHS STK MGT & ALLOC.'!$S11,'WHS STK MGT & ALLOC.'!$U11,'WHS STK MGT & ALLOC.'!$W11,'WHS STK MGT & ALLOC.'!$Y11) -> 10 | J11: =SUMIF('IN STORE SALES RECORD'!$D:$D,'STORE STK & SALES MGT'!$A11,'IN STORE SALES RECORD'!$E:$E) -> 90 | K11: =SUMIF('IN STORE SALES RECORD'!$D:$D,'STORE STK & SALES MGT'!$A11,'IN STORE SALES RECORD'!$H:$H) -> 6300 | L11: =IFERROR(ROUND(($K11/(SUM($K:$K))) * 100,3),"") -> 15.441 | M11: =IFERROR(ROUND($J11/$I11 * 100,2),"") -> 900 | N11: {=_xlfn.IFS($P$5 = "WEEK 1",'WHS STK MGT & ALLOC.'!$K11,$P$5 = "WEEK 2",'WHS STK MGT & ALLOC.'!$M11,$P$5 = "WEEK 3",'WHS STK MGT & ALLOC.'!$O11,$P$5 = "WEEK 4",'WHS STK MGT & ALLOC.'!Q11,$P$5 ="WEEK 5",'WHS STK MGT & ALLOC.'!$S11)} -> 10 | O11: {=_xlfn.SWITCH($P$5, "WEEK 1", 'WHS STK MGT & ALLOC.'!$H11, "WEEK 2", 'WHS STK MGT & ALLOC.'!$H11 - 'WHS STK MGT & ALLOC.'!$K11, "WEEK 3", 'WHS STK MGT & ALLOC.'!$H11 - ('WHS STK MGT & ALLOC.'!$K11 + 'WHS STK MGT & ALLOC.'!$M11), "WEEK 4", 'WHS STK MGT & ALLOC.'!$H11 - ('WHS STK MGT & ALLOC.'!$K11 + 'WHS STK MGT & ALLOC.'!$M11 + 'WHS STK MGT & ALLOC.'!$O11), "WEEK 5", 'WHS STK MGT & ALLOC.'!$H11 - ('WHS STK MGT & ALLOC.'!$K11 + 'WHS STK MGT & ALLOC.'!$M11 + 'WHS STK MGT & ALLOC.'!$O11 + 'WHS STK MGT & ALLOC.'!$Q11), "WEEK 6", 'WHS STK MGT & ALLOC.'!$H11 - ('WHS STK MGT & ALLOC.'!$K11 + 'WHS STK MGT & ALLOC.'!$M11 + 'WHS STK MGT & ALLOC.'!$O11 + 'WHS STK MGT & ALLOC.'!$Q11 + 'WHS STK MGT & ALLOC.'!$S11), "WEEK 7", 'WHS STK MGT & ALLOC.'!$H11 - ('WHS STK MGT & ALLOC.'!$K11 + 'WHS STK MGT & ALLOC.'!$M11 + 'WHS STK MGT & ALLOC.'!$O11 + 'WHS STK MGT & ALLOC.'!$Q11 + 'WHS STK MGT & ALLOC.'!$S11 + 'WHS STK MGT & ALLOC.'!$U11), "Other Weeks", 0 )} -> 200 | P11: =SUMIFS('IN STORE SALES RECORD'!$E:$E,'IN STORE SALES RECORD'!$D:$D,'STORE STK & SALES MGT'!$A11,'IN STORE SALES RECORD'!$A:$A,'STORE STK & SALES MGT'!$P$5) -> 0 | Q11: =SUMIFS('IN STORE SALES RECORD'!$H:$H,'IN STORE SALES RECORD'!$D:$D,'STORE STK & SALES MGT'!$A11,'IN STORE SALES RECORD'!$A:$A,'STORE STK & SALES MGT'!$P$5) -> 0 | R11: =IFERROR(ROUND(Q11/SUMIF('IN STORE SALES RECORD'!$A:$A,'STORE STK & SALES MGT'!$P$5,'IN STORE SALES RECORD'!$H:$H)*100,3),"") -> 0 | S11: {=_xlfn.IFS($P$5 ="WEEK 1",'WHS STK MGT & ALLOC.'!$H11-'WHS STK MGT & ALLOC.'!$K11,$P$5 ="WEEK 2",'WHS STK MGT & ALLOC.'!H11-('WHS STK MGT & ALLOC.'!$K11+'WHS STK MGT & ALLOC.'!$M11),$P$5 ="WEEK 3",'WHS STK MGT & ALLOC.'!$H11-'WHS STK MGT & ALLOC.'!$K11-'WHS STK MGT & ALLOC.'!$M11-'WHS STK MGT & ALLOC.'!$O11,$P$5 = "WEEK 4",'WHS STK MGT & ALLOC.'!H11-'WHS STK MGT & ALLOC.'!$K11-'WHS STK MGT & ALLOC.'!$M11-'WHS STK MGT & ALLOC.'!$O11-'WHS STK MGT & ALLOC.'!$Q11,$P$5 = "WEEK 5",'WHS STK MGT & ALLOC.'!H11-'WHS STK MGT & ALLOC.'!$K11-'WHS STK MGT & ALLOC.'!$M11-'WHS STK MGT & ALLOC.'!$O11-'WHS STK MGT & ALLOC.'!$Q11-'WHS STK MGT & ALLOC.'!$S11)} -> 190 | T11: =SUMIFS('IN STORE SALES RECORD'!$E:$E,'IN STORE SALES RECORD'!$D:$D,'STORE STK & SALES MGT'!$A11,'IN STORE SALES RECORD'!$C:$C,'STORE STK & SALES MGT'!$U$5) -> 90 | U11: =SUMIFS('IN STORE SALES RECORD'!$H:$H,'IN STORE SALES RECORD'!$D:$D,'STORE STK & SALES MGT'!$A11,'IN STORE SALES RECORD'!$C:$C,'STORE STK & SALES MGT'!$U$5) -> 6300 | V11: =IFERROR(ROUND(SUMIFS('IN STORE SALES RECORD'!$H:$H,'IN STORE SALES RECORD'!$C:$C,'STORE STK & SALES MGT'!$U$5,'STORE STK & SALES MGT'!$A:$A,'STORE STK & SALES MGT'!$A11)/SUMIF('IN STORE SALES RECORD'!$C:$C,'STORE STK & SALES MGT'!$U$5,'IN STORE SALES RECORD'!$H:$H)*100,3),"") -> 11.691
A12: TO-SW-HO-BL-10 | B12: =IFERROR(INDEX('REFERENCING & DATABASE'!$E$7:$E$131,MATCH($A12,'REFERENCING & DATABASE'!$D$7:$D$131,0)),"") -> Hooded Sweatshirt | C12: =IFERROR(INDEX('REFERENCING & DATABASE'!$B$7:$B$131,MATCH($A12,'REFERENCING & DATABASE'!$D$7:$D$131,0)),"") -> TOPS | D12: =IFERROR(INDEX('REFERENCING & DATABASE'!$C$7:$C$131,MATCH($A12,'REFERENCING & DATABASE'!$D$7:$D$131,0)),"") -> SWEATERS | E12: =IFERROR(INDEX('REFERENCING & DATABASE'!$F$7:$F$131,MATCH($A12,'REFERENCING & DATABASE'!$D$7:$D$131,0)),"") -> A comfortable and casual sweatshirt perfect for lounging or layering. | F12: =IFERROR(INDEX('REFERENCING & DATABASE'!$G$7:$G$131,MATCH($A12,'REFERENCING & DATABASE'!$D$7:$D$131,0)),"") -> Black,Grey | G12: =IFERROR(INDEX('REFERENCING & DATABASE'!$H$7:$H$131,MATCH($A12,'REFERENCING & DATABASE'!$D$7:$D$131,0)),"") -> 10 | H12: =IFERROR(INDEX('WHS STK MGT & ALLOC.'!$I:$I,MATCH($A12,'WHS STK MGT & ALLOC.'!$A:$A,0)),"") -> 290 | I12: =SUM('WHS STK MGT & ALLOC.'!$K12,'WHS STK MGT & ALLOC.'!$M12,'WHS STK MGT & ALLOC.'!$O12,'WHS STK MGT & ALLOC.'!$Q12,'WHS STK MGT & ALLOC.'!$S12,'WHS STK MGT & ALLOC.'!$U12,'WHS STK MGT & ALLOC.'!$W12,'WHS STK MGT & ALLOC.'!$Y12) -> 10 | J12: =SUMIF('IN STORE SALES RECORD'!$D:$D,'STORE STK & SALES MGT'!$A12,'IN STORE SALES RECORD'!$E:$E) -> 0 | K12: =SUMIF('IN STORE SALES RECORD'!$D:$D,'STORE STK & SALES MGT'!$A12,'IN STORE SALES RECORD'!$H:$H) -> 0 | L12: =IFERROR(ROUND(($K12/(SUM($K:$K))) * 100,3),"") -> 0 | M12: =IFERROR(ROUND($J12/$I12 * 100,2),"") -> 0 | N12: {=_xlfn.IFS($P$5 = "WEEK 1",'WHS STK MGT & ALLOC.'!$K12,$P$5 = "WEEK 2",'WHS STK MGT & ALLOC.'!$M12,$P$5 = "WEEK 3",'WHS STK MGT & ALLOC.'!$O12,$P$5 = "WEEK 4",'WHS STK MGT & ALLOC.'!Q12,$P$5 ="WEEK 5",'WHS STK MGT & ALLOC.'!$S12)} -> 10 | O12: {=_xlfn.SWITCH($P$5, "WEEK 1", 'WHS STK MGT & ALLOC.'!$H12, "WEEK 2", 'WHS STK MGT & ALLOC.'!$H12 - 'WHS STK MGT & ALLOC.'!$K12, "WEEK 3", 'WHS STK MGT & ALLOC.'!$H12 - ('WHS STK MGT & ALLOC.'!$K12 + 'WHS STK MGT & ALLOC.'!$M12), "WEEK 4", 'WHS STK MGT & ALLOC.'!$H12 - ('WHS STK MGT & ALLOC.'!$K12 + 'WHS STK MGT & ALLOC.'!$M12 + 'WHS STK MGT & ALLOC.'!$O12), "WEEK 5", 'WHS STK MGT & ALLOC.'!$H12 - ('WHS STK MGT & ALLOC.'!$K12 + 'WHS STK MGT & ALLOC.'!$M12 + 'WHS STK MGT & ALLOC.'!$O12 + 'WHS STK MGT & ALLOC.'!$Q12), "WEEK 6", 'WHS STK MGT & ALLOC.'!$H12 - ('WHS STK MGT & ALLOC.'!$K12 + 'WHS STK MGT & ALLOC.'!$M12 + 'WHS STK MGT & ALLOC.'!$O12 + 'WHS STK MGT & ALLOC.'!$Q12 + 'WHS STK MGT & ALLOC.'!$S12), "WEEK 7", 'WHS STK MGT & ALLOC.'!$H12 - ('WHS STK MGT & ALLOC.'!$K12 + 'WHS STK MGT & ALLOC.'!$M12 + 'WHS STK MGT & ALLOC.'!$O12 + 'WHS STK MGT & ALLOC.'!$Q12 + 'WHS STK MGT & ALLOC.'!$S12 + 'WHS STK MGT & ALLOC.'!$U12), "Other Weeks", 0 )} -> 300 | P12: =SUMIFS('IN STORE SALES RECORD'!$E:$E,'IN STORE SALES RECORD'!$D:$D,'STORE STK & SALES MGT'!$A12,'IN STORE SALES RECORD'!$A:$A,'STORE STK & SALES MGT'!$P$5) -> 0 | Q12: =SUMIFS('IN STORE SALES RECORD'!$H:$H,'IN STORE SALES RECORD'!$D:$D,'STORE STK & SALES MGT'!$A12,'IN STORE SALES RECORD'!$A:$A,'STORE STK & SALES MGT'!$P$5) -> 0 | R12: =IFERROR(ROUND(Q12/SUMIF('IN STORE SALES RECORD'!$A:$A,'STORE STK & SALES MGT'!$P$5,'IN STORE SALES RECORD'!$H:$H)*100,3),"") -> 0 | S12: {=_xlfn.IFS($P$5 ="WEEK 1",'WHS STK MGT & ALLOC.'!$H12-'WHS STK MGT & ALLOC.'!$K12,$P$5 ="WEEK 2",'WHS STK MGT & ALLOC.'!H12-('WHS STK MGT & ALLOC.'!$K12+'WHS STK MGT & ALLOC.'!$M12),$P$5 ="WEEK 3",'WHS STK MGT & ALLOC.'!$H12-'WHS STK MGT & ALLOC.'!$K12-'WHS STK MGT & ALLOC.'!$M12-'WHS STK MGT & ALLOC.'!$O12,$P$5 = "WEEK 4",'WHS STK MGT & ALLOC.'!H12-'WHS STK MGT & ALLOC.'!$K12-'WHS STK MGT & ALLOC.'!$M12-'WHS STK MGT & ALLOC.'!$O12-'WHS STK MGT & ALLOC.'!$Q12,$P$5 = "WEEK 5",'WHS STK MGT & ALLOC.'!H12-'WHS STK MGT & ALLOC.'!$K12-'WHS STK MGT & ALLOC.'!$M12-'WHS STK MGT & ALLOC.'!$O12-'WHS STK MGT & ALLOC.'!$Q12-'WHS STK MGT & ALLOC.'!$S12)} -> 290 | T12: =SUMIFS('IN STORE SALES RECORD'!$E:$E,'IN STORE SALES RECORD'!$D:$D,'STORE STK & SALES MGT'!$A12,'IN STORE SALES RECORD'!$C:$C,'STORE STK & SALES MGT'!$U$5) -> 0 | U12: =SUMIFS('IN STORE SALES RECORD'!$H:$H,'IN STORE SALES RECORD'!$D:$D,'STORE STK & SALES MGT'!$A12,'IN STORE SALES RECORD'!$C:$C,'STORE STK & SALES MGT'!$U$5) -> 0 | V12: =IFERROR(ROUND(SUMIFS('IN STORE SALES RECORD'!$H:$H,'IN STORE SALES RECORD'!$C:$C,'STORE STK & SALES MGT'!$U$5,'STORE STK & SALES MGT'!$A:$A,'STORE STK & SALES MGT'!$A12)/SUMIF('IN STORE SALES RECORD'!$C:$C,'STORE STK & SALES MGT'!$U$5,'IN STORE SALES RECORD'!$H:$H)*100,3),"") -> 0
A13: TO-JA-DE-NU-10 | B13: =IFERROR(INDEX('REFERENCING & DATABASE'!$E$7:$E$131,MATCH($A13,'REFERENCING & DATABASE'!$D$7:$D$131,0)),"") -> Denim Jacket | C13: =IFERROR(INDEX('REFERENCING & DATABASE'!$B$7:$B$131,MATCH($A13,'REFERENCING & DATABASE'!$D$7:$D$131,0)),"") -> TOPS | D13: =IFERROR(INDEX('REFERENCING & DATABASE'!$C$7:$C$131,MATCH($A13,'REFERENCING & DATABASE'!$D$7:$D$131,0)),"") -> JACKETS | E13: =IFERROR(INDEX('REFERENCING & DATABASE'!$F$7:$F$131,MATCH($A13,'REFERENCING & DATABASE'!$D$7:$D$131,0)),"") -> A timeless and versatile jacket that adds an edge to any outfit. | F13: =IFERROR(INDEX('REFERENCING & DATABASE'!$G$7:$G$131,MATCH($A13,'REFERENCING & DATABASE'!$D$7:$D$131,0)),"") -> Nude, Purple | G13: =IFERROR(INDEX('REFERENCING & DATABASE'!$H$7:$H$131,MATCH($A13,'REFERENCING & DATABASE'!$D$7:$D$131,0)),"") -> 10 | H13: =IFERROR(INDEX('WHS STK MGT & ALLOC.'!$I:$I,MATCH($A13,'WHS STK MGT & ALLOC.'!$A:$A,0)),"") -> 90 | I13: =SUM('WHS STK MGT & ALLOC.'!$K13,'WHS STK MGT & ALLOC.'!$M13,'WHS STK MGT & ALLOC.'!$O13,'WHS STK MGT & ALLOC.'!$Q13,'WHS STK MGT & ALLOC.'!$S13,'WHS STK MGT & ALLOC.'!$U13,'WHS STK MGT & ALLOC.'!$W13,'WHS STK MGT & ALLOC.'!$Y13) -> 10 | J13: =SUMIF('IN STORE SALES RECORD'!$D:$D,'STORE STK & SALES MGT'!$A13,'IN STORE SALES RECORD'!$E:$E) -> 0 | K13: =SUMIF('IN STORE SALES RECORD'!$D:$D,'STORE STK & SALES MGT'!$A13,'IN STORE SALES RECORD'!$H:$H) -> 0 | L13: =IFERROR(ROUND(($K13/(SUM($K:$K))) * 100,3),"") -> 0 | M13: =IFERROR(ROUND($J13/$I13 * 100,2),"") -> 0 | N13: {=_xlfn.IFS($P$5 = "WEEK 1",'WHS STK MGT & ALLOC.'!$K13,$P$5 = "WEEK 2",'WHS STK MGT & ALLOC.'!$M13,$P$5 = "WEEK 3",'WHS STK MGT & ALLOC.'!$O13,$P$5 = "WEEK 4",'WHS STK MGT & ALLOC.'!Q13,$P$5 ="WEEK 5",'WHS STK MGT & ALLOC.'!$S13)} -> 10 | O13: {=_xlfn.SWITCH($P$5, "WEEK 1", 'WHS STK MGT & ALLOC.'!$H13, "WEEK 2", 'WHS STK MGT & ALLOC.'!$H13 - 'WHS STK MGT & ALLOC.'!$K13, "WEEK 3", 'WHS STK MGT & ALLOC.'!$H13 - ('WHS STK MGT & ALLOC.'!$K13 + 'WHS STK MGT & ALLOC.'!$M13), "WEEK 4", 'WHS STK MGT & ALLOC.'!$H13 - ('WHS STK MGT & ALLOC.'!$K13 + 'WHS STK MGT & ALLOC.'!$M13 + 'WHS STK MGT & ALLOC.'!$O13), "WEEK 5", 'WHS STK MGT & ALLOC.'!$H13 - ('WHS STK MGT & ALLOC.'!$K13 + 'WHS STK MGT & ALLOC.'!$M13 + 'WHS STK MGT & ALLOC.'!$O13 + 'WHS STK MGT & ALLOC.'!$Q13), "WEEK 6", 'WHS STK MGT & ALLOC.'!$H13 - ('WHS STK MGT & ALLOC.'!$K13 + 'WHS STK MGT & ALLOC.'!$M13 + 'WHS STK MGT & ALLOC.'!$O13 + 'WHS STK MGT & ALLOC.'!$Q13 + 'WHS STK MGT & ALLOC.'!$S13), "WEEK 7", 'WHS STK MGT & ALLOC.'!$H13 - ('WHS STK MGT & ALLOC.'!$K13 + 'WHS STK MGT & ALLOC.'!$M13 + 'WHS STK MGT & ALLOC.'!$O13 + 'WHS STK MGT & ALLOC.'!$Q13 + 'WHS STK MGT & ALLOC.'!$S13 + 'WHS STK MGT & ALLOC.'!$U13), "Other Weeks", 0 )} -> 100 | P13: =SUMIFS('IN STORE SALES RECORD'!$E:$E,'IN STORE SALES RECORD'!$D:$D,'STORE STK & SALES MGT'!$A13,'IN STORE SALES RECORD'!$A:$A,'STORE STK & SALES MGT'!$P$5) -> 0 | Q13: =SUMIFS('IN STORE SALES RECORD'!$H:$H,'IN STORE SALES RECORD'!$D:$D,'STORE STK & SALES MGT'!$A13,'IN STORE SALES RECORD'!$A:$A,'STORE STK & SALES MGT'!$P$5) -> 0 | R13: =IFERROR(ROUND(Q13/SUMIF('IN STORE SALES RECORD'!$A:$A,'STORE STK & SALES MGT'!$P$5,'IN STORE SALES RECORD'!$H:$H)*100,3),"") -> 0 | S13: {=_xlfn.IFS($P$5 ="WEEK 1",'WHS STK MGT & ALLOC.'!$H13-'WHS STK MGT & ALLOC.'!$K13,$P$5 ="WEEK 2",'WHS STK MGT & ALLOC.'!H13-('WHS STK MGT & ALLOC.'!$K13+'WHS STK MGT & ALLOC.'!$M13),$P$5 ="WEEK 3",'WHS STK MGT & ALLOC.'!$H13-'WHS STK MGT & ALLOC.'!$K13-'WHS STK MGT & ALLOC.'!$M13-'WHS STK MGT & ALLOC.'!$O13,$P$5 = "WEEK 4",'WHS STK MGT & ALLOC.'!H13-'WHS STK MGT & ALLOC.'!$K13-'WHS STK MGT & ALLOC.'!$M13-'WHS STK MGT & ALLOC.'!$O13-'WHS STK MGT & ALLOC.'!$Q13,$P$5 = "WEEK 5",'WHS STK MGT & ALLOC.'!H13-'WHS STK MGT & ALLOC.'!$K13-'WHS STK MGT & ALLOC.'!$M13-'WHS STK MGT & ALLOC.'!$O13-'WHS STK MGT & ALLOC.'!$Q13-'WHS STK MGT & ALLOC.'!$S13)} -> 90 | T13: =SUMIFS('IN STORE SALES RECORD'!$E:$E,'IN STORE SALES RECORD'!$D:$D,'STORE STK & SALES MGT'!$A13,'IN STORE SALES RECORD'!$C:$C,'STORE STK & SALES MGT'!$U$5) -> 0 | U13: =SUMIFS('IN STORE SALES RECORD'!$H:$H,'IN STORE SALES RECORD'!$D:$D,'STORE STK & SALES MGT'!$A13,'IN STORE SALES RECORD'!$C:$C,'STORE STK & SALES MGT'!$U$5) -> 0 | V13: =IFERROR(ROUND(SUMIFS('IN STORE SALES RECORD'!$H:$H,'IN STORE SALES RECORD'!$C:$C,'STORE STK & SALES MGT'!$U$5,'STORE STK & SALES MGT'!$A:$A,'STORE STK & SALES MGT'!$A13)/SUMIF('IN STORE SALES RECORD'!$C:$C,'STORE STK & SALES MGT'!$U$5,'IN STORE SALES RECORD'!$H:$H)*100,3),"") -> 6.066
A14: TO-JA-LI-NU-10 | B14: =IFERROR(INDEX('REFERENCING & DATABASE'!$E$7:$E$131,MATCH($A14,'REFERENCING & DATABASE'!$D$7:$D$131,0)),"") -> Lightweight Puffer Jacket | C14: =IFERROR(INDEX('REFERENCING & DATABASE'!$B$7:$B$131,MATCH($A14,'REFERENCING & DATABASE'!$D$7:$D$131,0)),"") -> TOPS | D14: =IFERROR(INDEX('REFERENCING & DATABASE'!$C$7:$C$131,MATCH($A14,'REFERENCING & DATABASE'!$D$7:$D$131,0)),"") -> JACKETS | E14: =IFERROR(INDEX('REFERENCING & DATABASE'!$F$7:$F$131,MATCH($A14,'REFERENCING & DATABASE'!$D$7:$D$131,0)),"") -> : A warm and packable jacket for all your adventures. | F14: =IFERROR(INDEX('REFERENCING & DATABASE'!$G$7:$G$131,MATCH($A14,'REFERENCING & DATABASE'!$D$7:$D$131,0)),"") -> Nude, Pink, Red | G14: =IFERROR(INDEX('REFERENCING & DATABASE'!$H$7:$H$131,MATCH($A14,'REFERENCING & DATABASE'!$D$7:$D$131,0)),"") -> 10 | H14: =IFERROR(INDEX('WHS STK MGT & ALLOC.'!$I:$I,MATCH($A14,'WHS STK MGT & ALLOC.'!$A:$A,0)),"") -> 140 | I14: =SUM('WHS STK MGT & ALLOC.'!$K14,'WHS STK MGT & ALLOC.'!$M14,'WHS STK MGT & ALLOC.'!$O14,'WHS STK MGT & ALLOC.'!$Q14,'WHS STK MGT & ALLOC.'!$S14,'WHS STK MGT & ALLOC.'!$U14,'WHS STK MGT & ALLOC.'!$W14,'WHS STK MGT & ALLOC.'!$Y14) -> 10 | J14: =SUMIF('IN STORE SALES RECORD'!$D:$D,'STORE STK & SALES MGT'!$A14,'IN STORE SALES RECORD'!$E:$E) -> 0 | K14: =SUMIF('IN STORE SALES RECORD'!$D:$D,'STORE STK & SALES MGT'!$A14,'IN STORE SALES RECORD'!$H:$H) -> 0 | L14: =IFERROR(ROUND(($K14/(SUM($K:$K))) * 100,3),"") -> 0 | M14: =IFERROR(ROUND($J14/$I14 * 100,2),"") -> 0 | N14: {=_xlfn.IFS($P$5 = "WEEK 1",'WHS STK MGT & ALLOC.'!$K14,$P$5 = "WEEK 2",'WHS STK MGT & ALLOC.'!$M14,$P$5 = "WEEK 3",'WHS STK MGT & ALLOC.'!$O14,$P$5 = "WEEK 4",'WHS STK MGT & ALLOC.'!Q14,$P$5 ="WEEK 5",'WHS STK MGT & ALLOC.'!$S14)} -> 10 | O14: {=_xlfn.SWITCH($P$5, "WEEK 1", 'WHS STK MGT & ALLOC.'!$H14, "WEEK 2", 'WHS STK MGT & ALLOC.'!$H14 - 'WHS STK MGT & ALLOC.'!$K14, "WEEK 3", 'WHS STK MGT & ALLOC.'!$H14 - ('WHS STK MGT & ALLOC.'!$K14 + 'WHS STK MGT & ALLOC.'!$M14), "WEEK 4", 'WHS STK MGT & ALLOC.'!$H14 - ('WHS STK MGT & ALLOC.'!$K14 + 'WHS STK MGT & ALLOC.'!$M14 + 'WHS STK MGT & ALLOC.'!$O14), "WEEK 5", 'WHS STK MGT & ALLOC.'!$H14 - ('WHS STK MGT & ALLOC.'!$K14 + 'WHS STK MGT & ALLOC.'!$M14 + 'WHS STK MGT & ALLOC.'!$O14 + 'WHS STK MGT & ALLOC.'!$Q14), "WEEK 6", 'WHS STK MGT & ALLOC.'!$H14 - ('WHS STK MGT & ALLOC.'!$K14 + 'WHS STK MGT & ALLOC.'!$M14 + 'WHS STK MGT & ALLOC.'!$O14 + 'WHS STK MGT & ALLOC.'!$Q14 + 'WHS STK MGT & ALLOC.'!$S14), "WEEK 7", 'WHS STK MGT & ALLOC.'!$H14 - ('WHS STK MGT & ALLOC.'!$K14 + 'WHS STK MGT & ALLOC.'!$M14 + 'WHS STK MGT & ALLOC.'!$O14 + 'WHS STK MGT & ALLOC.'!$Q14 + 'WHS STK MGT & ALLOC.'!$S14 + 'WHS STK MGT & ALLOC.'!$U14), "Other Weeks", 0 )} -> 150 | P14: =SUMIFS('IN STORE SALES RECORD'!$E:$E,'IN STORE SALES RECORD'!$D:$D,'STORE STK & SALES MGT'!$A14,'IN STORE SALES RECORD'!$A:$A,'STORE STK & SALES MGT'!$P$5) -> 0 | Q14: =SUMIFS('IN STORE SALES RECORD'!$H:$H,'IN STORE SALES RECORD'!$D:$D,'STORE STK & SALES MGT'!$A14,'IN STORE SALES RECORD'!$A:$A,'STORE STK & SALES MGT'!$P$5) -> 0 | R14: =IFERROR(ROUND(Q14/SUMIF('IN STORE SALES RECORD'!$A:$A,'STORE STK & SALES MGT'!$P$5,'IN STORE SALES RECORD'!$H:$H)*100,3),"") -> 0 | S14: {=_xlfn.IFS($P$5 ="WEEK 1",'WHS STK MGT & ALLOC.'!$H14-'WHS STK MGT & ALLOC.'!$K14,$P$5 ="WEEK 2",'WHS STK MGT & ALLOC.'!H14-('WHS STK MGT & ALLOC.'!$K14+'WHS STK MGT & ALLOC.'!$M14),$P$5 ="WEEK 3",'WHS STK MGT & ALLOC.'!$H14-'WHS STK MGT & ALLOC.'!$K14-'WHS STK MGT & ALLOC.'!$M14-'WHS STK MGT & ALLOC.'!$O14,$P$5 = "WEEK 4",'WHS STK MGT & ALLOC.'!H14-'WHS STK MGT & ALLOC.'!$K14-'WHS STK MGT & ALLOC.'!$M14-'WHS STK MGT & ALLOC.'!$O14-'WHS STK MGT & ALLOC.'!$Q14,$P$5 = "WEEK 5",'WHS STK MGT & ALLOC.'!H14-'WHS STK MGT & ALLOC.'!$K14-'WHS STK MGT & ALLOC.'!$M14-'WHS STK MGT & ALLOC.'!$O14-'WHS STK MGT & ALLOC.'!$Q14-'WHS STK MGT & ALLOC.'!$S14)} -> 140 | T14: =SUMIFS('IN STORE SALES RECORD'!$E:$E,'IN STORE SALES RECORD'!$D:$D,'STORE STK & SALES MGT'!$A14,'IN STORE SALES RECORD'!$C:$C,'STORE STK & SALES MGT'!$U$5) -> 0 | U14: =SUMIFS('IN STORE SALES RECORD'!$H:$H,'IN STORE SALES RECORD'!$D:$D,'STORE STK & SALES MGT'!$A14,'IN STORE SALES RECORD'!$C:$C,'STORE STK & SALES MGT'!$U$5) -> 0 | V14: =IFERROR(ROUND(SUMIFS('IN STORE SALES RECORD'!$H:$H,'IN STORE SALES RECORD'!$C:$C,'STORE STK & SALES MGT'!$U$5,'STORE STK & SALES MGT'!$A:$A,'STORE STK & SALES MGT'!$A14)/SUMIF('IN STORE SALES RECORD'!$C:$C,'STORE STK & SALES MGT'!$U$5,'IN STORE SALES RECORD'!$H:$H)*100,3),"") -> 0
A18: REFERENCE | B18: PRODUCT NAME | C18: CATEGORY | D18: SUB-CATEGORY | E18: DESCRIPTION | F18: COLOUR | G18: SIZE | H18: AVAILABLE WHS STOCK | I18: TOTAL STOCK ALLOCATED | J18: CUMULATIVE UNIT SALES | K18: CUMULATIVE SALES | L18: SALES MIX | M18: SELL THROUGH | N18: STOCK ALLOCATION - 1ST WEEK | O18: OPENING STOCK | P18: UNIT SALES | Q18: SALES | R18: SALES MIX | S18: REMAINING STOCK | T18: TOTAL UNIT | U18: TOTAL SALES | V18: TOTAL SALES MIX
A19: BO-JE-CL-BL-10 | B19: =IFERROR(INDEX('REFERENCING & DATABASE'!$E$7:$E$131,MATCH($A19,'REFERENCING & DATABASE'!$D$7:$D$131,0)),"") -> Classic Straight Leg Jeans | C19: =IFERROR(INDEX('REFERENCING & DATABASE'!$B$7:$B$131,MATCH($A19,'REFERENCING & DATABASE'!$D$7:$D$131,0)),"") -> BOTTOMS | D19: =IFERROR(INDEX('REFERENCING & DATABASE'!$C$7:$C$131,MATCH($A19,'REFERENCING & DATABASE'!$D$7:$D$131,0)),"") -> JEANS | E19: =IFERROR(INDEX('REFERENCING & DATABASE'!$F$7:$F$131,MATCH($A19,'REFERENCING & DATABASE'!$D$7:$D$131,0)),"") -> A timeless and versatile style that flatters all body types. | F19: =IFERROR(INDEX('REFERENCING & DATABASE'!$G$7:$G$131,MATCH($A19,'REFERENCING & DATABASE'!$D$7:$D$131,0)),"") -> Blue,Black,Grey | G19: =IFERROR(INDEX('REFERENCING & DATABASE'!$H$7:$H$131,MATCH($A19,'REFERENCING & DATABASE'!$D$7:$D$131,0)),"") -> 10 | H19: =IFERROR(INDEX('WHS STK MGT & ALLOC.'!$I:$I,MATCH($A19,'WHS STK MGT & ALLOC.'!$A:$A,0)),"") -> 616 | I19: =SUM('WHS STK MGT & ALLOC.'!$K19,'WHS STK MGT & ALLOC.'!$M19,'WHS STK MGT & ALLOC.'!$O19,'WHS STK MGT & ALLOC.'!$Q19,'WHS STK MGT & ALLOC.'!$S19,'WHS STK MGT & ALLOC.'!$U19,'WHS STK MGT & ALLOC.'!$W19,'WHS STK MGT & ALLOC.'!$Y19) -> 10 | J19: =SUMIF('IN STORE SALES RECORD'!$D:$D,'STORE STK & SALES MGT'!$A19,'IN STORE SALES RECORD'!$E:$E) -> 0 | K19: =SUMIF('IN STORE SALES RECORD'!$D:$D,'STORE STK & SALES MGT'!$A19,'IN STORE SALES RECORD'!$H:$H) -> 0 | L19: =IFERROR(ROUND(($K19/(SUM($K:$K))) * 100,3),"") -> 0 | M19: =IFERROR(ROUND($J19/$I19 * 100,2),"") -> 0 | N19: {=_xlfn.IFS($P$5 = "WEEK 1",'WHS STK MGT & ALLOC.'!$K19,$P$5 = "WEEK 2",'WHS STK MGT & ALLOC.'!$M19,$P$5 = "WEEK 3",'WHS STK MGT & ALLOC.'!$O19,$P$5 = "WEEK 4",'WHS STK MGT & ALLOC.'!Q19,$P$5 ="WEEK 5",'WHS STK MGT & ALLOC.'!$S19)} -> 10 | O19: {=_xlfn.SWITCH($P$5, "WEEK 1", 'WHS STK MGT & ALLOC.'!$H19, "WEEK 2", 'WHS STK MGT & ALLOC.'!$H19 - 'WHS STK MGT & ALLOC.'!$K19, "WEEK 3", 'WHS STK MGT & ALLOC.'!$H19 - ('WHS STK MGT & ALLOC.'!$K19 + 'WHS STK MGT & ALLOC.'!$M19), "WEEK 4", 'WHS STK MGT & ALLOC.'!$H19 - ('WHS STK MGT & ALLOC.'!$K19 + 'WHS STK MGT & ALLOC.'!$M19 + 'WHS STK MGT & ALLOC.'!$O19), "WEEK 5", 'WHS STK MGT & ALLOC.'!$H19 - ('WHS STK MGT & ALLOC.'!$K19 + 'WHS STK MGT & ALLOC.'!$M19 + 'WHS STK MGT & ALLOC.'!$O19 + 'WHS STK MGT & ALLOC.'!$Q19), "WEEK 6", 'WHS STK MGT & ALLOC.'!$H19 - ('WHS STK MGT & ALLOC.'!$K19 + 'WHS STK MGT & ALLOC.'!$M19 + 'WHS STK MGT & ALLOC.'!$O19 + 'WHS STK MGT & ALLOC.'!$Q19 + 'WHS STK MGT & ALLOC.'!$S19), "WEEK 7", 'WHS STK MGT & ALLOC.'!$H19 - ('WHS STK MGT & ALLOC.'!$K19 + 'WHS STK MGT & ALLOC.'!$M19 + 'WHS STK MGT & ALLOC.'!$O19 + 'WHS STK MGT & ALLOC.'!$Q19 + 'WHS STK MGT & ALLOC.'!$S19 + 'WHS STK MGT & ALLOC.'!$U19), "Other Weeks", 0 )} -> 626 | P19: =SUMIFS('IN STORE SALES RECORD'!$E:$E,'IN STORE SALES RECORD'!$D:$D,'STORE STK & SALES MGT'!$A19,'IN STORE SALES RECORD'!$A:$A,'STORE STK & SALES MGT'!$P$5) -> 0 | Q19: =SUMIFS('IN STORE SALES RECORD'!$H:$H,'IN STORE SALES RECORD'!$D:$D,'STORE STK & SALES MGT'!$A19,'IN STORE SALES RECORD'!$A:$A,'STORE STK & SALES MGT'!$P$5) -> 0 | R19: =IFERROR(ROUND(Q19/SUMIF('IN STORE SALES RECORD'!$A:$A,'STORE STK & SALES MGT'!$P$5,'IN STORE SALES RECORD'!$H:$H)*100,3),"") -> 0 | S19: {=_xlfn.IFS($P$5 ="WEEK 1",'WHS STK MGT & ALLOC.'!$H19-'WHS STK MGT & ALLOC.'!$K19,$P$5 ="WEEK 2",'WHS STK MGT & ALLOC.'!H19-('WHS STK MGT & ALLOC.'!$K19+'WHS STK MGT & ALLOC.'!$M19),$P$5 ="WEEK 3",'WHS STK MGT & ALLOC.'!$H19-'WHS STK MGT & ALLOC.'!$K19-'WHS STK MGT & ALLOC.'!$M19-'WHS STK MGT & ALLOC.'!$O19,$P$5 = "WEEK 4",'WHS STK MGT & ALLOC.'!H19-'WHS STK MGT & ALLOC.'!$K19-'WHS STK MGT & ALLOC.'!$M19-'WHS STK MGT & ALLOC.'!$O19-'WHS STK MGT & ALLOC.'!$Q19,$P$5 = "WEEK 5",'WHS STK MGT & ALLOC.'!H19-'WHS STK MGT & ALLOC.'!$K19-'WHS STK MGT & ALLOC.'!$M19-'WHS STK MGT & ALLOC.'!$O19-'WHS STK MGT & ALLOC.'!$Q19-'WHS STK MGT & ALLOC.'!$S19)} -> 616 | T19: =SUMIFS('IN STORE SALES RECORD'!$E:$E,'IN STORE SALES RECORD'!$D:$D,'STORE STK & SALES MGT'!$A19,'IN STORE SALES RECORD'!$C:$C,'STORE STK & SALES MGT'!$U$5) -> 0 | U19: =SUMIFS('IN STORE SALES RECORD'!$H:$H,'IN STORE SALES RECORD'!$D:$D,'STORE STK & SALES MGT'!$A19,'IN STORE SALES RECORD'!$C:$C,'STORE STK & SALES MGT'!$U$5) -> 0 | V19: =IFERROR(ROUND(SUMIFS('IN STORE SALES RECORD'!$H:$H,'IN STORE SALES RECORD'!$C:$C,'STORE STK & SALES MGT'!$U$5,'STORE STK & SALES MGT'!$A:$A,'STORE STK & SALES MGT'!$A19)/SUMIF('IN STORE SALES RECORD'!$C:$C,'STORE STK & SALES MGT'!$U$5,'IN STORE SALES RECORD'!$H:$H)*100,3),"") -> 0
A20: BO-JE-SK-BL-10 | B20: =IFERROR(INDEX('REFERENCING & DATABASE'!$E$7:$E$131,MATCH($A20,'REFERENCING & DATABASE'!$D$7:$D$131,0)),"") -> Skinny Fit Jeans | C20: =IFERROR(INDEX('REFERENCING & DATABASE'!$B$7:$B$131,MATCH($A20,'REFERENCING & DATABASE'!$D$7:$D$131,0)),"") -> BOTTOMS | D20: =IFERROR(INDEX('REFERENCING & DATABASE'!$C$7:$C$131,MATCH($A20,'REFERENCING & DATABASE'!$D$7:$D$131,0)),"") -> JEANS | E20: =IFERROR(INDEX('REFERENCING & DATABASE'!$F$7:$F$131,MATCH($A20,'REFERENCING & DATABASE'!$D$7:$D$131,0)),"") -> A form-fitting silhouette that hugs your curves. | F20: =IFERROR(INDEX('REFERENCING & DATABASE'!$G$7:$G$131,MATCH($A20,'REFERENCING & DATABASE'!$D$7:$D$131,0)),"") -> Blue,Black,Grey | G20: =IFERROR(INDEX('REFERENCING & DATABASE'!$H$7:$H$131,MATCH($A20,'REFERENCING & DATABASE'!$D$7:$D$131,0)),"") -> 10 | H20: =IFERROR(INDEX('WHS STK MGT & ALLOC.'!$I:$I,MATCH($A20,'WHS STK MGT & ALLOC.'!$A:$A,0)),"") -> 197 | I20: =SUM('WHS STK MGT & ALLOC.'!$K20,'WHS STK MGT & ALLOC.'!$M20,'WHS STK MGT & ALLOC.'!$O20,'WHS STK MGT & ALLOC.'!$Q20,'WHS STK MGT & ALLOC.'!$S20,'WHS STK MGT & ALLOC.'!$U20,'WHS STK MGT & ALLOC.'!$W20,'WHS STK MGT & ALLOC.'!$Y20) -> 10 | J20: =SUMIF('IN STORE SALES RECORD'!$D:$D,'STORE STK & SALES MGT'!$A20,'IN STORE SALES RECORD'!$E:$E) -> 55 | K20: =SUMIF('IN STORE SALES RECORD'!$D:$D,'STORE STK & SALES MGT'!$A20,'IN STORE SALES RECORD'!$H:$H) -> 2475 | L20: =IFERROR(ROUND(($K20/(SUM($K:$K))) * 100,3),"") -> 6.066 | M20: =IFERROR(ROUND($J20/$I20 * 100,2),"") -> 550 | N20: {=_xlfn.IFS($P$5 = "WEEK 1",'WHS STK MGT & ALLOC.'!$K20,$P$5 = "WEEK 2",'WHS STK MGT & ALLOC.'!$M20,$P$5 = "WEEK 3",'WHS STK MGT & ALLOC.'!$O20,$P$5 = "WEEK 4",'WHS STK MGT & ALLOC.'!Q20,$P$5 ="WEEK 5",'WHS STK MGT & ALLOC.'!$S20)} -> 10 | O20: {=_xlfn.SWITCH($P$5, "WEEK 1", 'WHS STK MGT & ALLOC.'!$H20, "WEEK 2", 'WHS STK MGT & ALLOC.'!$H20 - 'WHS STK MGT & ALLOC.'!$K20, "WEEK 3", 'WHS STK MGT & ALLOC.'!$H20 - ('WHS STK MGT & ALLOC.'!$K20 + 'WHS STK MGT & ALLOC.'!$M20), "WEEK 4", 'WHS STK MGT & ALLOC.'!$H20 - ('WHS STK MGT & ALLOC.'!$K20 + 'WHS STK MGT & ALLOC.'!$M20 + 'WHS STK MGT & ALLOC.'!$O20), "WEEK 5", 'WHS STK MGT & ALLOC.'!$H20 - ('WHS STK MGT & ALLOC.'!$K20 + 'WHS STK MGT & ALLOC.'!$M20 + 'WHS STK MGT & ALLOC.'!$O20 + 'WHS STK MGT & ALLOC.'!$Q20), "WEEK 6", 'WHS STK MGT & ALLOC.'!$H20 - ('WHS STK MGT & ALLOC.'!$K20 + 'WHS STK MGT & ALLOC.'!$M20 + 'WHS STK MGT & ALLOC.'!$O20 + 'WHS STK MGT & ALLOC.'!$Q20 + 'WHS STK MGT & ALLOC.'!$S20), "WEEK 7", 'WHS STK MGT & ALLOC.'!$H20 - ('WHS STK MGT & ALLOC.'!$K20 + 'WHS STK MGT & ALLOC.'!$M20 + 'WHS STK MGT & ALLOC.'!$O20 + 'WHS STK MGT & ALLOC.'!$Q20 + 'WHS STK MGT & ALLOC.'!$S20 + 'WHS STK MGT & ALLOC.'!$U20), "Other Weeks", 0 )} -> 207 | P20: =SUMIFS('IN STORE SALES RECORD'!$E:$E,'IN STORE SALES RECORD'!$D:$D,'STORE STK & SALES MGT'!$A20,'IN STORE SALES RECORD'!$A:$A,'STORE STK & SALES MGT'!$P$5) -> 0 | Q20: =SUMIFS('IN STORE SALES RECORD'!$H:$H,'IN STORE SALES RECORD'!$D:$D,'STORE STK & SALES MGT'!$A20,'IN STORE SALES RECORD'!$A:$A,'STORE STK & SALES MGT'!$P$5) -> 0 | R20: =IFERROR(ROUND(Q20/SUMIF('IN STORE SALES RECORD'!$A:$A,'STORE STK & SALES MGT'!$P$5,'IN STORE SALES RECORD'!$H:$H)*100,3),"") -> 0 | S20: {=_xlfn.IFS($P$5 ="WEEK 1",'WHS STK MGT & ALLOC.'!$H20-'WHS STK MGT & ALLOC.'!$K20,$P$5 ="WEEK 2",'WHS STK MGT & ALLOC.'!H20-('WHS STK MGT & ALLOC.'!$K20+'WHS STK MGT & ALLOC.'!$M20),$P$5 ="WEEK 3",'WHS STK MGT & ALLOC.'!$H20-'WHS STK MGT & ALLOC.'!$K20-'WHS STK MGT & ALLOC.'!$M20-'WHS STK MGT & ALLOC.'!$O20,$P$5 = "WEEK 4",'WHS STK MGT & ALLOC.'!H20-'WHS STK MGT & ALLOC.'!$K20-'WHS STK MGT & ALLOC.'!$M20-'WHS STK MGT & ALLOC.'!$O20-'WHS STK MGT & ALLOC.'!$Q20,$P$5 = "WEEK 5",'WHS STK MGT & ALLOC.'!H20-'WHS STK MGT & ALLOC.'!$K20-'WHS STK MGT & ALLOC.'!$M20-'WHS STK MGT & ALLOC.'!$O20-'WHS STK MGT & ALLOC.'!$Q20-'WHS STK MGT & ALLOC.'!$S20)} -> 197 | T20: =SUMIFS('IN STORE SALES RECORD'!$E:$E,'IN STORE SALES RECORD'!$D:$D,'STORE STK & SALES MGT'!$A20,'IN STORE SALES RECORD'!$C:$C,'STORE STK & SALES MGT'!$U$5) -> 55 | U20: =SUMIFS('IN STORE SALES RECORD'!$H:$H,'IN STORE SALES RECORD'!$D:$D,'STORE STK & SALES MGT'!$A20,'IN STORE SALES RECORD'!$C:$C,'STORE STK & SALES MGT'!$U$5) -> 2475 | V20: =IFERROR(ROUND(SUMIFS('IN STORE SALES RECORD'!$H:$H,'IN STORE SALES RECORD'!$C:$C,'STORE STK & SALES MGT'!$U$5,'STORE STK & SALES MGT'!$A:$A,'STORE STK & SALES MGT'!$A20)/SUMIF('IN STORE SALES RECORD'!$C:$C,'STORE STK & SALES MGT'!$U$5,'IN STORE SALES RECORD'!$H:$H)*100,3),"") -> 2.745
A21: BO-JE-BO-BL-10 | B21: =IFERROR(INDEX('REFERENCING & DATABASE'!$E$7:$E$131,MATCH($A21,'REFERENCING & DATABASE'!$D$7:$D$131,0)),"") -> Bootcut Jeans | C21: =IFERROR(INDEX('REFERENCING & DATABASE'!$B$7:$B$131,MATCH($A21,'REFERENCING & DATABASE'!$D$7:$D$131,0)),"") -> BOTTOMS | D21: =IFERROR(INDEX('REFERENCING & DATABASE'!$C$7:$C$131,MATCH($A21,'REFERENCING & DATABASE'!$D$7:$D$131,0)),"") -> JEANS | E21: =IFERROR(INDEX('REFERENCING & DATABASE'!$F$7:$F$131,MATCH($A21,'REFERENCING & DATABASE'!$D$7:$D$131,0)),"") -> A flattering style that flares slightly at the ankle. | F21: =IFERROR(INDEX('REFERENCING & DATABASE'!$G$7:$G$131,MATCH($A21,'REFERENCING & DATABASE'!$D$7:$D$131,0)),"") -> Blue,Black,Grey | G21: =IFERROR(INDEX('REFERENCING & DATABASE'!$H$7:$H$131,MATCH($A21,'REFERENCING & DATABASE'!$D$7:$D$131,0)),"") -> 10 | H21: =IFERROR(INDEX('WHS STK MGT & ALLOC.'!$I:$I,MATCH($A21,'WHS STK MGT & ALLOC.'!$A:$A,0)),"") -> 634 | I21: =SUM('WHS STK MGT & ALLOC.'!$K21,'WHS STK MGT & ALLOC.'!$M21,'WHS STK MGT & ALLOC.'!$O21,'WHS STK MGT & ALLOC.'!$Q21,'WHS STK MGT & ALLOC.'!$S21,'WHS STK MGT & ALLOC.'!$U21,'WHS STK MGT & ALLOC.'!$W21,'WHS STK MGT & ALLOC.'!$Y21) -> 10 | J21: =SUMIF('IN STORE SALES RECORD'!$D:$D,'STORE STK & SALES MGT'!$A21,'IN STORE SALES RECORD'!$E:$E) -> 0 | K21: =SUMIF('IN STORE SALES RECORD'!$D:$D,'STORE STK & SALES MGT'!$A21,'IN STORE SALES RECORD'!$H:$H) -> 0 | L21: =IFERROR(ROUND(($K21/(SUM($K:$K))) * 100,3),"") -> 0 | M21: =IFERROR(ROUND($J21/$I21 * 100,2),"") -> 0 | N21: {=_xlfn.IFS($P$5 = "WEEK 1",'WHS STK MGT & ALLOC.'!$K21,$P$5 = "WEEK 2",'WHS STK MGT & ALLOC.'!$M21,$P$5 = "WEEK 3",'WHS STK MGT & ALLOC.'!$O21,$P$5 = "WEEK 4",'WHS STK MGT & ALLOC.'!Q21,$P$5 ="WEEK 5",'WHS STK MGT & ALLOC.'!$S21)} -> 10 | O21: {=_xlfn.SWITCH($P$5, "WEEK 1", 'WHS STK MGT & ALLOC.'!$H21, "WEEK 2", 'WHS STK MGT & ALLOC.'!$H21 - 'WHS STK MGT & ALLOC.'!$K21, "WEEK 3", 'WHS STK MGT & ALLOC.'!$H21 - ('WHS STK MGT & ALLOC.'!$K21 + 'WHS STK MGT & ALLOC.'!$M21), "WEEK 4", 'WHS STK MGT & ALLOC.'!$H21 - ('WHS STK MGT & ALLOC.'!$K21 + 'WHS STK MGT & ALLOC.'!$M21 + 'WHS STK MGT & ALLOC.'!$O21), "WEEK 5", 'WHS STK MGT & ALLOC.'!$H21 - ('WHS STK MGT & ALLOC.'!$K21 + 'WHS STK MGT & ALLOC.'!$M21 + 'WHS STK MGT & ALLOC.'!$O21 + 'WHS STK MGT & ALLOC.'!$Q21), "WEEK 6", 'WHS STK MGT & ALLOC.'!$H21 - ('WHS STK MGT & ALLOC.'!$K21 + 'WHS STK MGT & ALLOC.'!$M21 + 'WHS STK MGT & ALLOC.'!$O21 + 'WHS STK MGT & ALLOC.'!$Q21 + 'WHS STK MGT & ALLOC.'!$S21), "WEEK 7", 'WHS STK MGT & ALLOC.'!$H21 - ('WHS STK MGT & ALLOC.'!$K21 + 'WHS STK MGT & ALLOC.'!$M21 + 'WHS STK MGT & ALLOC.'!$O21 + 'WHS STK MGT & ALLOC.'!$Q21 + 'WHS STK MGT & ALLOC.'!$S21 + 'WHS STK MGT & ALLOC.'!$U21), "Other Weeks", 0 )} -> 644 | P21: =SUMIFS('IN STORE SALES RECORD'!$E:$E,'IN STORE SALES RECORD'!$D:$D,'STORE STK & SALES MGT'!$A21,'IN STORE SALES RECORD'!$A:$A,'STORE STK & SALES MGT'!$P$5) -> 0 | Q21: =SUMIFS('IN STORE SALES RECORD'!$H:$H,'IN STORE SALES RECORD'!$D:$D,'STORE STK & SALES MGT'!$A21,'IN STORE SALES RECORD'!$A:$A,'STORE STK & SALES MGT'!$P$5) -> 0 | R21: =IFERROR(ROUND(Q21/SUMIF('IN STORE SALES RECORD'!$A:$A,'STORE STK & SALES MGT'!$P$5,'IN STORE SALES RECORD'!$H:$H)*100,3),"") -> 0 | S21: {=_xlfn.IFS($P$5 ="WEEK 1",'WHS STK MGT & ALLOC.'!$H21-'WHS STK MGT & ALLOC.'!$K21,$P$5 ="WEEK 2",'WHS STK MGT & ALLOC.'!H21-('WHS STK MGT & ALLOC.'!$K21+'WHS STK MGT & ALLOC.'!$M21),$P$5 ="WEEK 3",'WHS STK MGT & ALLOC.'!$H21-'WHS STK MGT & ALLOC.'!$K21-'WHS STK MGT & ALLOC.'!$M21-'WHS STK MGT & ALLOC.'!$O21,$P$5 = "WEEK 4",'WHS STK MGT & ALLOC.'!H21-'WHS STK MGT & ALLOC.'!$K21-'WHS STK MGT & ALLOC.'!$M21-'WHS STK MGT & ALLOC.'!$O21-'WHS STK MGT & ALLOC.'!$Q21,$P$5 = "WEEK 5",'WHS STK MGT & ALLOC.'!H21-'WHS STK MGT & ALLOC.'!$K21-'WHS STK MGT & ALLOC.'!$M21-'WHS STK MGT & ALLOC.'!$O21-'WHS STK MGT & ALLOC.'!$Q21-'WHS STK MGT & ALLOC.'!$S21)} -> 634 | T21: =SUMIFS('IN STORE SALES RECORD'!$E:$E,'IN STORE SALES RECORD'!$D:$D,'STORE STK & SALES MGT'!$A21,'IN STORE SALES RECORD'!$C:$C,'STORE STK & SALES MGT'!$U$5) -> 0 | U21: =SUMIFS('IN STORE SALES RECORD'!$H:$H,'IN STORE SALES RECORD'!$D:$D,'STORE STK & SALES MGT'!$A21,'IN STORE SALES RECORD'!$C:$C,'STORE STK & SALES MGT'!$U$5) -> 0 | V21: =IFERROR(ROUND(SUMIFS('IN STORE SALES RECORD'!$H:$H,'IN STORE SALES RECORD'!$C:$C,'STORE STK & SALES MGT'!$U$5,'STORE STK & SALES MGT'!$A:$A,'STORE STK & SALES MGT'!$A21)/SUMIF('IN STORE SALES RECORD'!$C:$C,'STORE STK & SALES MGT'!$U$5,'IN STORE SALES RECORD'!$H:$H)*100,3),"") -> 26.618
